src/p0_counter_16bits/up_counter_16bit.vhd
library ieee;
use ieee.std_logic_1164.all;
use ieee.numeric_std.all;

entity up_counter_16bit is
    port (
        clk    : in  std_logic;             -- Clock input
        reset  : in  std_logic;             -- Reset input
        count  : out std_logic_vector(15 downto 0)  -- 16-bit count output
    );
end entity up_counter_16bit;

architecture rtl of up_counter_16bit is
    signal counter : unsigned(15 downto 0);  -- 16-bit counter signal
begin
    process (clk, reset)
    begin
        if reset = '1' then
            counter <= (others => '0');  -- Reset counter to zero
        elsif rising_edge(clk) then
            counter <= counter + 1;      -- Increment counter on rising edge of clock
        end if;
    end process;

    -- Output the counter value
    count <= std_logic_vector(counter);
end architecture rtl;

src/p0_counter_16bits/up_counter_16bit_testbench.vhd
library ieee;
use ieee.std_logic_1164.all;
use ieee.numeric_std.all;

entity up_counter_16bit_tb is
end entity up_counter_16bit_tb;

architecture testbench of up_counter_16bit_tb is
    constant CLK_PERIOD : time := 10 ns;  -- Clock period
    signal clk : std_logic := '0';        -- Clock signal
    signal reset : std_logic := '0';      -- Reset signal
    signal count : std_logic_vector(15 downto 0);  -- Counter output

    -- Instantiate the up counter module
    component up_counter_16bit
        port (
            clk    : in  std_logic;
            reset  : in  std_logic;
            count  : out std_logic_vector(15 downto 0)
        );
    end component;

begin
    -- Instantiate the up counter
    uut : up_counter_16bit
    port map (
        clk => clk,
        reset => reset,
        count => count
    );

    -- Clock process
    clk_process : process
    begin
        while now < 10000 ns loop  -- Run for 100 ns
            clk <= '0';
            wait for CLK_PERIOD / 2;
            clk <= '1';
            wait for CLK_PERIOD / 2;
        end loop;
        wait;
    end process;

    -- Stimulus process
    stimulus : process
    begin
        reset <= '1';  -- Assert reset
        wait for 20 ns;
        reset <= '0';  -- Deassert reset
        wait for 10000 ns;
        wait;
    end process;

end architecture testbench;

src/p0_counter_16bits/p0_counter_16bits_wave.vcd
$date
  Thu May  2 15:39:06 2024
$end
$version
  GHDL v0
$end
$timescale
  1 fs
$end
$scope module standard $end
$upscope $end
$scope module std_logic_1164 $end
$upscope $end
$scope module numeric_std $end
$upscope $end
$scope module up_counter_16bit_tb $end
$var reg 1 ! clk $end
$var reg 1 " reset $end
$var reg 16 # count[15:0] $end
$scope module uut $end
$var reg 1 $ clk $end
$var reg 1 % reset $end
$var reg 16 & count[15:0] $end
$var reg 16 ' counter[15:0] $end
$upscope $end
$upscope $end
$enddefinitions $end
#0
0!
1"
b0000000000000000 #
0$
1%
b0000000000000000 &
b0000000000000000 '
#5000000
1!
1$
#10000000
0!
0$
#15000000
1!
1$
#20000000
0!
0"
0$
0%
#25000000
1!
b0000000000000001 #
1$
b0000000000000001 &
b0000000000000001 '
#30000000
0!
0$
#35000000
1!
b0000000000000010 #
1$
b0000000000000010 &
b0000000000000010 '
#40000000
0!
0$
#45000000
1!
b0000000000000011 #
1$
b0000000000000011 &
b0000000000000011 '
#50000000
0!
0$
#55000000
1!
b0000000000000100 #
1$
b0000000000000100 &
b0000000000000100 '
#60000000
0!
0$
#65000000
1!
b0000000000000101 #
1$
b0000000000000101 &
b0000000000000101 '
#70000000
0!
0$
#75000000
1!
b0000000000000110 #
1$
b0000000000000110 &
b0000000000000110 '
#80000000
0!
0$
#85000000
1!
b0000000000000111 #
1$
b0000000000000111 &
b0000000000000111 '
#90000000
0!
0$
#95000000
1!
b0000000000001000 #
1$
b0000000000001000 &
b0000000000001000 '
#100000000
0!
0$
#105000000
1!
b0000000000001001 #
1$
b0000000000001001 &
b0000000000001001 '
#110000000
0!
0$
#115000000
1!
b0000000000001010 #
1$
b0000000000001010 &
b0000000000001010 '
#120000000
0!
0$
#125000000
1!
b0000000000001011 #
1$
b0000000000001011 &
b0000000000001011 '
#130000000
0!
0$
#135000000
1!
b0000000000001100 #
1$
b0000000000001100 &
b0000000000001100 '
#140000000
0!
0$
#145000000
1!
b0000000000001101 #
1$
b0000000000001101 &
b0000000000001101 '
#150000000
0!
0$
#155000000
1!
b0000000000001110 #
1$
b0000000000001110 &
b0000000000001110 '
#160000000
0!
0$
#165000000
1!
b0000000000001111 #
1$
b0000000000001111 &
b0000000000001111 '
#170000000
0!
0$
#175000000
1!
b0000000000010000 #
1$
b0000000000010000 &
b0000000000010000 '
#180000000
0!
0$
#185000000
1!
b0000000000010001 #
1$
b0000000000010001 &
b0000000000010001 '
#190000000
0!
0$
#195000000
1!
b0000000000010010 #
1$
b0000000000010010 &
b0000000000010010 '
#200000000
0!
0$
#205000000
1!
b0000000000010011 #
1$
b0000000000010011 &
b0000000000010011 '
#210000000
0!
0$
#215000000
1!
b0000000000010100 #
1$
b0000000000010100 &
b0000000000010100 '
#220000000
0!
0$
#225000000
1!
b0000000000010101 #
1$
b0000000000010101 &
b0000000000010101 '
#230000000
0!
0$
#235000000
1!
b0000000000010110 #
1$
b0000000000010110 &
b0000000000010110 '
#240000000
0!
0$
#245000000
1!
b0000000000010111 #
1$
b0000000000010111 &
b0000000000010111 '
#250000000
0!
0$
#255000000
1!
b0000000000011000 #
1$
b0000000000011000 &
b0000000000011000 '
#260000000
0!
0$
#265000000
1!
b0000000000011001 #
1$
b0000000000011001 &
b0000000000011001 '
#270000000
0!
0$
#275000000
1!
b0000000000011010 #
1$
b0000000000011010 &
b0000000000011010 '
#280000000
0!
0$
#285000000
1!
b0000000000011011 #
1$
b0000000000011011 &
b0000000000011011 '
#290000000
0!
0$
#295000000
1!
b0000000000011100 #
1$
b0000000000011100 &
b0000000000011100 '
#300000000
0!
0$
#305000000
1!
b0000000000011101 #
1$
b0000000000011101 &
b0000000000011101 '
#310000000
0!
0$
#315000000
1!
b0000000000011110 #
1$
b0000000000011110 &
b0000000000011110 '
#320000000
0!
0$
#325000000
1!
b0000000000011111 #
1$
b0000000000011111 &
b0000000000011111 '
#330000000
0!
0$
#335000000
1!
b0000000000100000 #
1$
b0000000000100000 &
b0000000000100000 '
#340000000
0!
0$
#345000000
1!
b0000000000100001 #
1$
b0000000000100001 &
b0000000000100001 '
#350000000
0!
0$
#355000000
1!
b0000000000100010 #
1$
b0000000000100010 &
b0000000000100010 '
#360000000
0!
0$
#365000000
1!
b0000000000100011 #
1$
b0000000000100011 &
b0000000000100011 '
#370000000
0!
0$
#375000000
1!
b0000000000100100 #
1$
b0000000000100100 &
b0000000000100100 '
#380000000
0!
0$
#385000000
1!
b0000000000100101 #
1$
b0000000000100101 &
b0000000000100101 '
#390000000
0!
0$
#395000000
1!
b0000000000100110 #
1$
b0000000000100110 &
b0000000000100110 '
#400000000
0!
0$
#405000000
1!
b0000000000100111 #
1$
b0000000000100111 &
b0000000000100111 '
#410000000
0!
0$
#415000000
1!
b0000000000101000 #
1$
b0000000000101000 &
b0000000000101000 '
#420000000
0!
0$
#425000000
1!
b0000000000101001 #
1$
b0000000000101001 &
b0000000000101001 '
#430000000
0!
0$
#435000000
1!
b0000000000101010 #
1$
b0000000000101010 &
b0000000000101010 '
#440000000
0!
0$
#445000000
1!
b0000000000101011 #
1$
b0000000000101011 &
b0000000000101011 '
#450000000
0!
0$
#455000000
1!
b0000000000101100 #
1$
b0000000000101100 &
b0000000000101100 '
#460000000
0!
0$
#465000000
1!
b0000000000101101 #
1$
b0000000000101101 &
b0000000000101101 '
#470000000
0!
0$
#475000000
1!
b0000000000101110 #
1$
b0000000000101110 &
b0000000000101110 '
#480000000
0!
0$
#485000000
1!
b0000000000101111 #
1$
b0000000000101111 &
b0000000000101111 '
#490000000
0!
0$
#495000000
1!
b0000000000110000 #
1$
b0000000000110000 &
b0000000000110000 '
#500000000
0!
0$
#505000000
1!
b0000000000110001 #
1$
b0000000000110001 &
b0000000000110001 '
#510000000
0!
0$
#515000000
1!
b0000000000110010 #
1$
b0000000000110010 &
b0000000000110010 '
#520000000
0!
0$
#525000000
1!
b0000000000110011 #
1$
b0000000000110011 &
b0000000000110011 '
#530000000
0!
0$
#535000000
1!
b0000000000110100 #
1$
b0000000000110100 &
b0000000000110100 '
#540000000
0!
0$
#545000000
1!
b0000000000110101 #
1$
b0000000000110101 &
b0000000000110101 '
#550000000
0!
0$
#555000000
1!
b0000000000110110 #
1$
b0000000000110110 &
b0000000000110110 '
#560000000
0!
0$
#565000000
1!
b0000000000110111 #
1$
b0000000000110111 &
b0000000000110111 '
#570000000
0!
0$
#575000000
1!
b0000000000111000 #
1$
b0000000000111000 &
b0000000000111000 '
#580000000
0!
0$
#585000000
1!
b0000000000111001 #
1$
b0000000000111001 &
b0000000000111001 '
#590000000
0!
0$
#595000000
1!
b0000000000111010 #
1$
b0000000000111010 &
b0000000000111010 '
#600000000
0!
0$
#605000000
1!
b0000000000111011 #
1$
b0000000000111011 &
b0000000000111011 '
#610000000
0!
0$
#615000000
1!
b0000000000111100 #
1$
b0000000000111100 &
b0000000000111100 '
#620000000
0!
0$
#625000000
1!
b0000000000111101 #
1$
b0000000000111101 &
b0000000000111101 '
#630000000
0!
0$
#635000000
1!
b0000000000111110 #
1$
b0000000000111110 &
b0000000000111110 '
#640000000
0!
0$
#645000000
1!
b0000000000111111 #
1$
b0000000000111111 &
b0000000000111111 '
#650000000
0!
0$
#655000000
1!
b0000000001000000 #
1$
b0000000001000000 &
b0000000001000000 '
#660000000
0!
0$
#665000000
1!
b0000000001000001 #
1$
b0000000001000001 &
b0000000001000001 '
#670000000
0!
0$
#675000000
1!
b0000000001000010 #
1$
b0000000001000010 &
b0000000001000010 '
#680000000
0!
0$
#685000000
1!
b0000000001000011 #
1$
b0000000001000011 &
b0000000001000011 '
#690000000
0!
0$
#695000000
1!
b0000000001000100 #
1$
b0000000001000100 &
b0000000001000100 '
#700000000
0!
0$
#705000000
1!
b0000000001000101 #
1$
b0000000001000101 &
b0000000001000101 '
#710000000
0!
0$
#715000000
1!
b0000000001000110 #
1$
b0000000001000110 &
b0000000001000110 '
#720000000
0!
0$
#725000000
1!
b0000000001000111 #
1$
b0000000001000111 &
b0000000001000111 '
#730000000
0!
0$
#735000000
1!
b0000000001001000 #
1$
b0000000001001000 &
b0000000001001000 '
#740000000
0!
0$
#745000000
1!
b0000000001001001 #
1$
b0000000001001001 &
b0000000001001001 '
#750000000
0!
0$
#755000000
1!
b0000000001001010 #
1$
b0000000001001010 &
b0000000001001010 '
#760000000
0!
0$
#765000000
1!
b0000000001001011 #
1$
b0000000001001011 &
b0000000001001011 '
#770000000
0!
0$
#775000000
1!
b0000000001001100 #
1$
b0000000001001100 &
b0000000001001100 '
#780000000
0!
0$
#785000000
1!
b0000000001001101 #
1$
b0000000001001101 &
b0000000001001101 '
#790000000
0!
0$
#795000000
1!
b0000000001001110 #
1$
b0000000001001110 &
b0000000001001110 '
#800000000
0!
0$
#805000000
1!
b0000000001001111 #
1$
b0000000001001111 &
b0000000001001111 '
#810000000
0!
0$
#815000000
1!
b0000000001010000 #
1$
b0000000001010000 &
b0000000001010000 '
#820000000
0!
0$
#825000000
1!
b0000000001010001 #
1$
b0000000001010001 &
b0000000001010001 '
#830000000
0!
0$
#835000000
1!
b0000000001010010 #
1$
b0000000001010010 &
b0000000001010010 '
#840000000
0!
0$
#845000000
1!
b0000000001010011 #
1$
b0000000001010011 &
b0000000001010011 '
#850000000
0!
0$
#855000000
1!
b0000000001010100 #
1$
b0000000001010100 &
b0000000001010100 '
#860000000
0!
0$
#865000000
1!
b0000000001010101 #
1$
b0000000001010101 &
b0000000001010101 '
#870000000
0!
0$
#875000000
1!
b0000000001010110 #
1$
b0000000001010110 &
b0000000001010110 '
#880000000
0!
0$
#885000000
1!
b0000000001010111 #
1$
b0000000001010111 &
b0000000001010111 '
#890000000
0!
0$
#895000000
1!
b0000000001011000 #
1$
b0000000001011000 &
b0000000001011000 '
#900000000
0!
0$
#905000000
1!
b0000000001011001 #
1$
b0000000001011001 &
b0000000001011001 '
#910000000
0!
0$
#915000000
1!
b0000000001011010 #
1$
b0000000001011010 &
b0000000001011010 '
#920000000
0!
0$
#925000000
1!
b0000000001011011 #
1$
b0000000001011011 &
b0000000001011011 '
#930000000
0!
0$
#935000000
1!
b0000000001011100 #
1$
b0000000001011100 &
b0000000001011100 '
#940000000
0!
0$
#945000000
1!
b0000000001011101 #
1$
b0000000001011101 &
b0000000001011101 '
#950000000
0!
0$
#955000000
1!
b0000000001011110 #
1$
b0000000001011110 &
b0000000001011110 '
#960000000
0!
0$
#965000000
1!
b0000000001011111 #
1$
b0000000001011111 &
b0000000001011111 '
#970000000
0!
0$
#975000000
1!
b0000000001100000 #
1$
b0000000001100000 &
b0000000001100000 '
#980000000
0!
0$
#985000000
1!
b0000000001100001 #
1$
b0000000001100001 &
b0000000001100001 '
#990000000
0!
0$
#995000000
1!
b0000000001100010 #
1$
b0000000001100010 &
b0000000001100010 '
#1000000000
0!
0$
#1005000000
1!
b0000000001100011 #
1$
b0000000001100011 &
b0000000001100011 '
#1010000000
0!
0$
#1015000000
1!
b0000000001100100 #
1$
b0000000001100100 &
b0000000001100100 '
#1020000000
0!
0$
#1025000000
1!
b0000000001100101 #
1$
b0000000001100101 &
b0000000001100101 '
#1030000000
0!
0$
#1035000000
1!
b0000000001100110 #
1$
b0000000001100110 &
b0000000001100110 '
#1040000000
0!
0$
#1045000000
1!
b0000000001100111 #
1$
b0000000001100111 &
b0000000001100111 '
#1050000000
0!
0$
#1055000000
1!
b0000000001101000 #
1$
b0000000001101000 &
b0000000001101000 '
#1060000000
0!
0$
#1065000000
1!
b0000000001101001 #
1$
b0000000001101001 &
b0000000001101001 '
#1070000000
0!
0$
#1075000000
1!
b0000000001101010 #
1$
b0000000001101010 &
b0000000001101010 '
#1080000000
0!
0$
#1085000000
1!
b0000000001101011 #
1$
b0000000001101011 &
b0000000001101011 '
#1090000000
0!
0$
#1095000000
1!
b0000000001101100 #
1$
b0000000001101100 &
b0000000001101100 '
#1100000000
0!
0$
#1105000000
1!
b0000000001101101 #
1$
b0000000001101101 &
b0000000001101101 '
#1110000000
0!
0$
#1115000000
1!
b0000000001101110 #
1$
b0000000001101110 &
b0000000001101110 '
#1120000000
0!
0$
#1125000000
1!
b0000000001101111 #
1$
b0000000001101111 &
b0000000001101111 '
#1130000000
0!
0$
#1135000000
1!
b0000000001110000 #
1$
b0000000001110000 &
b0000000001110000 '
#1140000000
0!
0$
#1145000000
1!
b0000000001110001 #
1$
b0000000001110001 &
b0000000001110001 '
#1150000000
0!
0$
#1155000000
1!
b0000000001110010 #
1$
b0000000001110010 &
b0000000001110010 '
#1160000000
0!
0$
#1165000000
1!
b0000000001110011 #
1$
b0000000001110011 &
b0000000001110011 '
#1170000000
0!
0$
#1175000000
1!
b0000000001110100 #
1$
b0000000001110100 &
b0000000001110100 '
#1180000000
0!
0$
#1185000000
1!
b0000000001110101 #
1$
b0000000001110101 &
b0000000001110101 '
#1190000000
0!
0$
#1195000000
1!
b0000000001110110 #
1$
b0000000001110110 &
b0000000001110110 '
#1200000000
0!
0$
#1205000000
1!
b0000000001110111 #
1$
b0000000001110111 &
b0000000001110111 '
#1210000000
0!
0$
#1215000000
1!
b0000000001111000 #
1$
b0000000001111000 &
b0000000001111000 '
#1220000000
0!
0$
#1225000000
1!
b0000000001111001 #
1$
b0000000001111001 &
b0000000001111001 '
#1230000000
0!
0$
#1235000000
1!
b0000000001111010 #
1$
b0000000001111010 &
b0000000001111010 '
#1240000000
0!
0$
#1245000000
1!
b0000000001111011 #
1$
b0000000001111011 &
b0000000001111011 '
#1250000000
0!
0$
#1255000000
1!
b0000000001111100 #
1$
b0000000001111100 &
b0000000001111100 '
#1260000000
0!
0$
#1265000000
1!
b0000000001111101 #
1$
b0000000001111101 &
b0000000001111101 '
#1270000000
0!
0$
#1275000000
1!
b0000000001111110 #
1$
b0000000001111110 &
b0000000001111110 '
#1280000000
0!
0$
#1285000000
1!
b0000000001111111 #
1$
b0000000001111111 &
b0000000001111111 '
#1290000000
0!
0$
#1295000000
1!
b0000000010000000 #
1$
b0000000010000000 &
b0000000010000000 '
#1300000000
0!
0$
#1305000000
1!
b0000000010000001 #
1$
b0000000010000001 &
b0000000010000001 '
#1310000000
0!
0$
#1315000000
1!
b0000000010000010 #
1$
b0000000010000010 &
b0000000010000010 '
#1320000000
0!
0$
#1325000000
1!
b0000000010000011 #
1$
b0000000010000011 &
b0000000010000011 '
#1330000000
0!
0$
#1335000000
1!
b0000000010000100 #
1$
b0000000010000100 &
b0000000010000100 '
#1340000000
0!
0$
#1345000000
1!
b0000000010000101 #
1$
b0000000010000101 &
b0000000010000101 '
#1350000000
0!
0$
#1355000000
1!
b0000000010000110 #
1$
b0000000010000110 &
b0000000010000110 '
#1360000000
0!
0$
#1365000000
1!
b0000000010000111 #
1$
b0000000010000111 &
b0000000010000111 '
#1370000000
0!
0$
#1375000000
1!
b0000000010001000 #
1$
b0000000010001000 &
b0000000010001000 '
#1380000000
0!
0$
#1385000000
1!
b0000000010001001 #
1$
b0000000010001001 &
b0000000010001001 '
#1390000000
0!
0$
#1395000000
1!
b0000000010001010 #
1$
b0000000010001010 &
b0000000010001010 '
#1400000000
0!
0$
#1405000000
1!
b0000000010001011 #
1$
b0000000010001011 &
b0000000010001011 '
#1410000000
0!
0$
#1415000000
1!
b0000000010001100 #
1$
b0000000010001100 &
b0000000010001100 '
#1420000000
0!
0$
#1425000000
1!
b0000000010001101 #
1$
b0000000010001101 &
b0000000010001101 '
#1430000000
0!
0$
#1435000000
1!
b0000000010001110 #
1$
b0000000010001110 &
b0000000010001110 '
#1440000000
0!
0$
#1445000000
1!
b0000000010001111 #
1$
b0000000010001111 &
b0000000010001111 '
#1450000000
0!
0$
#1455000000
1!
b0000000010010000 #
1$
b0000000010010000 &
b0000000010010000 '
#1460000000
0!
0$
#1465000000
1!
b0000000010010001 #
1$
b0000000010010001 &
b0000000010010001 '
#1470000000
0!
0$
#1475000000
1!
b0000000010010010 #
1$
b0000000010010010 &
b0000000010010010 '
#1480000000
0!
0$
#1485000000
1!
b0000000010010011 #
1$
b0000000010010011 &
b0000000010010011 '
#1490000000
0!
0$
#1495000000
1!
b0000000010010100 #
1$
b0000000010010100 &
b0000000010010100 '
#1500000000
0!
0$
#1505000000
1!
b0000000010010101 #
1$
b0000000010010101 &
b0000000010010101 '
#1510000000
0!
0$
#1515000000
1!
b0000000010010110 #
1$
b0000000010010110 &
b0000000010010110 '
#1520000000
0!
0$
#1525000000
1!
b0000000010010111 #
1$
b0000000010010111 &
b0000000010010111 '
#1530000000
0!
0$
#1535000000
1!
b0000000010011000 #
1$
b0000000010011000 &
b0000000010011000 '
#1540000000
0!
0$
#1545000000
1!
b0000000010011001 #
1$
b0000000010011001 &
b0000000010011001 '
#1550000000
0!
0$
#1555000000
1!
b0000000010011010 #
1$
b0000000010011010 &
b0000000010011010 '
#1560000000
0!
0$
#1565000000
1!
b0000000010011011 #
1$
b0000000010011011 &
b0000000010011011 '
#1570000000
0!
0$
#1575000000
1!
b0000000010011100 #
1$
b0000000010011100 &
b0000000010011100 '
#1580000000
0!
0$
#1585000000
1!
b0000000010011101 #
1$
b0000000010011101 &
b0000000010011101 '
#1590000000
0!
0$
#1595000000
1!
b0000000010011110 #
1$
b0000000010011110 &
b0000000010011110 '
#1600000000
0!
0$
#1605000000
1!
b0000000010011111 #
1$
b0000000010011111 &
b0000000010011111 '
#1610000000
0!
0$
#1615000000
1!
b0000000010100000 #
1$
b0000000010100000 &
b0000000010100000 '
#1620000000
0!
0$
#1625000000
1!
b0000000010100001 #
1$
b0000000010100001 &
b0000000010100001 '
#1630000000
0!
0$
#1635000000
1!
b0000000010100010 #
1$
b0000000010100010 &
b0000000010100010 '
#1640000000
0!
0$
#1645000000
1!
b0000000010100011 #
1$
b0000000010100011 &
b0000000010100011 '
#1650000000
0!
0$
#1655000000
1!
b0000000010100100 #
1$
b0000000010100100 &
b0000000010100100 '
#1660000000
0!
0$
#1665000000
1!
b0000000010100101 #
1$
b0000000010100101 &
b0000000010100101 '
#1670000000
0!
0$
#1675000000
1!
b0000000010100110 #
1$
b0000000010100110 &
b0000000010100110 '
#1680000000
0!
0$
#1685000000
1!
b0000000010100111 #
1$
b0000000010100111 &
b0000000010100111 '
#1690000000
0!
0$
#1695000000
1!
b0000000010101000 #
1$
b0000000010101000 &
b0000000010101000 '
#1700000000
0!
0$
#1705000000
1!
b0000000010101001 #
1$
b0000000010101001 &
b0000000010101001 '
#1710000000
0!
0$
#1715000000
1!
b0000000010101010 #
1$
b0000000010101010 &
b0000000010101010 '
#1720000000
0!
0$
#1725000000
1!
b0000000010101011 #
1$
b0000000010101011 &
b0000000010101011 '
#1730000000
0!
0$
#1735000000
1!
b0000000010101100 #
1$
b0000000010101100 &
b0000000010101100 '
#1740000000
0!
0$
#1745000000
1!
b0000000010101101 #
1$
b0000000010101101 &
b0000000010101101 '
#1750000000
0!
0$
#1755000000
1!
b0000000010101110 #
1$
b0000000010101110 &
b0000000010101110 '
#1760000000
0!
0$
#1765000000
1!
b0000000010101111 #
1$
b0000000010101111 &
b0000000010101111 '
#1770000000
0!
0$
#1775000000
1!
b0000000010110000 #
1$
b0000000010110000 &
b0000000010110000 '
#1780000000
0!
0$
#1785000000
1!
b0000000010110001 #
1$
b0000000010110001 &
b0000000010110001 '
#1790000000
0!
0$
#1795000000
1!
b0000000010110010 #
1$
b0000000010110010 &
b0000000010110010 '
#1800000000
0!
0$
#1805000000
1!
b0000000010110011 #
1$
b0000000010110011 &
b0000000010110011 '
#1810000000
0!
0$
#1815000000
1!
b0000000010110100 #
1$
b0000000010110100 &
b0000000010110100 '
#1820000000
0!
0$
#1825000000
1!
b0000000010110101 #
1$
b0000000010110101 &
b0000000010110101 '
#1830000000
0!
0$
#1835000000
1!
b0000000010110110 #
1$
b0000000010110110 &
b0000000010110110 '
#1840000000
0!
0$
#1845000000
1!
b0000000010110111 #
1$
b0000000010110111 &
b0000000010110111 '
#1850000000
0!
0$
#1855000000
1!
b0000000010111000 #
1$
b0000000010111000 &
b0000000010111000 '
#1860000000
0!
0$
#1865000000
1!
b0000000010111001 #
1$
b0000000010111001 &
b0000000010111001 '
#1870000000
0!
0$
#1875000000
1!
b0000000010111010 #
1$
b0000000010111010 &
b0000000010111010 '
#1880000000
0!
0$
#1885000000
1!
b0000000010111011 #
1$
b0000000010111011 &
b0000000010111011 '
#1890000000
0!
0$
#1895000000
1!
b0000000010111100 #
1$
b0000000010111100 &
b0000000010111100 '
#1900000000
0!
0$
#1905000000
1!
b0000000010111101 #
1$
b0000000010111101 &
b0000000010111101 '
#1910000000
0!
0$
#1915000000
1!
b0000000010111110 #
1$
b0000000010111110 &
b0000000010111110 '
#1920000000
0!
0$
#1925000000
1!
b0000000010111111 #
1$
b0000000010111111 &
b0000000010111111 '
#1930000000
0!
0$
#1935000000
1!
b0000000011000000 #
1$
b0000000011000000 &
b0000000011000000 '
#1940000000
0!
0$
#1945000000
1!
b0000000011000001 #
1$
b0000000011000001 &
b0000000011000001 '
#1950000000
0!
0$
#1955000000
1!
b0000000011000010 #
1$
b0000000011000010 &
b0000000011000010 '
#1960000000
0!
0$
#1965000000
1!
b0000000011000011 #
1$
b0000000011000011 &
b0000000011000011 '
#1970000000
0!
0$
#1975000000
1!
b0000000011000100 #
1$
b0000000011000100 &
b0000000011000100 '
#1980000000
0!
0$
#1985000000
1!
b0000000011000101 #
1$
b0000000011000101 &
b0000000011000101 '
#1990000000
0!
0$
#1995000000
1!
b0000000011000110 #
1$
b0000000011000110 &
b0000000011000110 '
#2000000000
0!
0$
#2005000000
1!
b0000000011000111 #
1$
b0000000011000111 &
b0000000011000111 '
#2010000000
0!
0$
#2015000000
1!
b0000000011001000 #
1$
b0000000011001000 &
b0000000011001000 '
#2020000000
0!
0$
#2025000000
1!
b0000000011001001 #
1$
b0000000011001001 &
b0000000011001001 '
#2030000000
0!
0$
#2035000000
1!
b0000000011001010 #
1$
b0000000011001010 &
b0000000011001010 '
#2040000000
0!
0$
#2045000000
1!
b0000000011001011 #
1$
b0000000011001011 &
b0000000011001011 '
#2050000000
0!
0$
#2055000000
1!
b0000000011001100 #
1$
b0000000011001100 &
b0000000011001100 '
#2060000000
0!
0$
#2065000000
1!
b0000000011001101 #
1$
b0000000011001101 &
b0000000011001101 '
#2070000000
0!
0$
#2075000000
1!
b0000000011001110 #
1$
b0000000011001110 &
b0000000011001110 '
#2080000000
0!
0$
#2085000000
1!
b0000000011001111 #
1$
b0000000011001111 &
b0000000011001111 '
#2090000000
0!
0$
#2095000000
1!
b0000000011010000 #
1$
b0000000011010000 &
b0000000011010000 '
#2100000000
0!
0$
#2105000000
1!
b0000000011010001 #
1$
b0000000011010001 &
b0000000011010001 '
#2110000000
0!
0$
#2115000000
1!
b0000000011010010 #
1$
b0000000011010010 &
b0000000011010010 '
#2120000000
0!
0$
#2125000000
1!
b0000000011010011 #
1$
b0000000011010011 &
b0000000011010011 '
#2130000000
0!
0$
#2135000000
1!
b0000000011010100 #
1$
b0000000011010100 &
b0000000011010100 '
#2140000000
0!
0$
#2145000000
1!
b0000000011010101 #
1$
b0000000011010101 &
b0000000011010101 '
#2150000000
0!
0$
#2155000000
1!
b0000000011010110 #
1$
b0000000011010110 &
b0000000011010110 '
#2160000000
0!
0$
#2165000000
1!
b0000000011010111 #
1$
b0000000011010111 &
b0000000011010111 '
#2170000000
0!
0$
#2175000000
1!
b0000000011011000 #
1$
b0000000011011000 &
b0000000011011000 '
#2180000000
0!
0$
#2185000000
1!
b0000000011011001 #
1$
b0000000011011001 &
b0000000011011001 '
#2190000000
0!
0$
#2195000000
1!
b0000000011011010 #
1$
b0000000011011010 &
b0000000011011010 '
#2200000000
0!
0$
#2205000000
1!
b0000000011011011 #
1$
b0000000011011011 &
b0000000011011011 '
#2210000000
0!
0$
#2215000000
1!
b0000000011011100 #
1$
b0000000011011100 &
b0000000011011100 '
#2220000000
0!
0$
#2225000000
1!
b0000000011011101 #
1$
b0000000011011101 &
b0000000011011101 '
#2230000000
0!
0$
#2235000000
1!
b0000000011011110 #
1$
b0000000011011110 &
b0000000011011110 '
#2240000000
0!
0$
#2245000000
1!
b0000000011011111 #
1$
b0000000011011111 &
b0000000011011111 '
#2250000000
0!
0$
#2255000000
1!
b0000000011100000 #
1$
b0000000011100000 &
b0000000011100000 '
#2260000000
0!
0$
#2265000000
1!
b0000000011100001 #
1$
b0000000011100001 &
b0000000011100001 '
#2270000000
0!
0$
#2275000000
1!
b0000000011100010 #
1$
b0000000011100010 &
b0000000011100010 '
#2280000000
0!
0$
#2285000000
1!
b0000000011100011 #
1$
b0000000011100011 &
b0000000011100011 '
#2290000000
0!
0$
#2295000000
1!
b0000000011100100 #
1$
b0000000011100100 &
b0000000011100100 '
#2300000000
0!
0$
#2305000000
1!
b0000000011100101 #
1$
b0000000011100101 &
b0000000011100101 '
#2310000000
0!
0$
#2315000000
1!
b0000000011100110 #
1$
b0000000011100110 &
b0000000011100110 '
#2320000000
0!
0$
#2325000000
1!
b0000000011100111 #
1$
b0000000011100111 &
b0000000011100111 '
#2330000000
0!
0$
#2335000000
1!
b0000000011101000 #
1$
b0000000011101000 &
b0000000011101000 '
#2340000000
0!
0$
#2345000000
1!
b0000000011101001 #
1$
b0000000011101001 &
b0000000011101001 '
#2350000000
0!
0$
#2355000000
1!
b0000000011101010 #
1$
b0000000011101010 &
b0000000011101010 '
#2360000000
0!
0$
#2365000000
1!
b0000000011101011 #
1$
b0000000011101011 &
b0000000011101011 '
#2370000000
0!
0$
#2375000000
1!
b0000000011101100 #
1$
b0000000011101100 &
b0000000011101100 '
#2380000000
0!
0$
#2385000000
1!
b0000000011101101 #
1$
b0000000011101101 &
b0000000011101101 '
#2390000000
0!
0$
#2395000000
1!
b0000000011101110 #
1$
b0000000011101110 &
b0000000011101110 '
#2400000000
0!
0$
#2405000000
1!
b0000000011101111 #
1$
b0000000011101111 &
b0000000011101111 '
#2410000000
0!
0$
#2415000000
1!
b0000000011110000 #
1$
b0000000011110000 &
b0000000011110000 '
#2420000000
0!
0$
#2425000000
1!
b0000000011110001 #
1$
b0000000011110001 &
b0000000011110001 '
#2430000000
0!
0$
#2435000000
1!
b0000000011110010 #
1$
b0000000011110010 &
b0000000011110010 '
#2440000000
0!
0$
#2445000000
1!
b0000000011110011 #
1$
b0000000011110011 &
b0000000011110011 '
#2450000000
0!
0$
#2455000000
1!
b0000000011110100 #
1$
b0000000011110100 &
b0000000011110100 '
#2460000000
0!
0$
#2465000000
1!
b0000000011110101 #
1$
b0000000011110101 &
b0000000011110101 '
#2470000000
0!
0$
#2475000000
1!
b0000000011110110 #
1$
b0000000011110110 &
b0000000011110110 '
#2480000000
0!
0$
#2485000000
1!
b0000000011110111 #
1$
b0000000011110111 &
b0000000011110111 '
#2490000000
0!
0$
#2495000000
1!
b0000000011111000 #
1$
b0000000011111000 &
b0000000011111000 '
#2500000000
0!
0$
#2505000000
1!
b0000000011111001 #
1$
b0000000011111001 &
b0000000011111001 '
#2510000000
0!
0$
#2515000000
1!
b0000000011111010 #
1$
b0000000011111010 &
b0000000011111010 '
#2520000000
0!
0$
#2525000000
1!
b0000000011111011 #
1$
b0000000011111011 &
b0000000011111011 '
#2530000000
0!
0$
#2535000000
1!
b0000000011111100 #
1$
b0000000011111100 &
b0000000011111100 '
#2540000000
0!
0$
#2545000000
1!
b0000000011111101 #
1$
b0000000011111101 &
b0000000011111101 '
#2550000000
0!
0$
#2555000000
1!
b0000000011111110 #
1$
b0000000011111110 &
b0000000011111110 '
#2560000000
0!
0$
#2565000000
1!
b0000000011111111 #
1$
b0000000011111111 &
b0000000011111111 '
#2570000000
0!
0$
#2575000000
1!
b0000000100000000 #
1$
b0000000100000000 &
b0000000100000000 '
#2580000000
0!
0$
#2585000000
1!
b0000000100000001 #
1$
b0000000100000001 &
b0000000100000001 '
#2590000000
0!
0$
