src/p0_counter_16bits/up_counter_16bit.vhd
library ieee;
use ieee.std_logic_1164.all;
use ieee.numeric_std.all;

entity up_counter_16bit is
    port (
        clk    : in  std_logic;             -- Clock input
        reset  : in  std_logic;             -- Reset input
        count  : out std_logic_vector(15 downto 0)  -- 16-bit count output
    );
end entity up_counter_16bit;

architecture rtl of up_counter_16bit is
    signal counter : unsigned(15 downto 0);  -- 16-bit counter signal
begin
    process (clk, reset)
    begin
        if reset = '1' then
            counter <= (others => '0');  -- Reset counter to zero
        elsif rising_edge(clk) then
            counter <= counter + 1;      -- Increment counter on rising edge of clock
        end if;
    end process;

    -- Output the counter value
    count <= std_logic_vector(counter);
end architecture rtl;

src/p0_counter_16bits/up_counter_16bit_testbench.vhd
library ieee;
use ieee.std_logic_1164.all;
use ieee.numeric_std.all;

entity up_counter_16bit_tb is
end entity up_counter_16bit_tb;

architecture testbench of up_counter_16bit_tb is
    constant CLK_PERIOD : time := 10 ns;  -- Clock period
    signal clk : std_logic := '0';        -- Clock signal
    signal reset : std_logic := '0';      -- Reset signal
    signal count : std_logic_vector(15 downto 0);  -- Counter output

    -- Instantiate the up counter module
    component up_counter_16bit
        port (
            clk    : in  std_logic;
            reset  : in  std_logic;
            count  : out std_logic_vector(15 downto 0)
        );
    end component;

begin
    -- Instantiate the up counter
    uut : up_counter_16bit
    port map (
        clk => clk,
        reset => reset,
        count => count
    );

    -- Clock process
    clk_process : process
    begin
        while now < 10000 ns loop  -- Run for 100 ns
            clk <= '0';
            wait for CLK_PERIOD / 2;
            clk <= '1';
            wait for CLK_PERIOD / 2;
        end loop;
        wait;
    end process;

    -- Stimulus process
    stimulus : process
    begin
        reset <= '1';  -- Assert reset
        wait for 20 ns;
        reset <= '0';  -- Deassert reset
        wait for 10000 ns;
        wait;
    end process;

end architecture testbench;

src/p0_counter_16bits/p0_counter_16bits_wave.vcd
$date
  Mon Jun 24 19:19:19 2024
$end
$version
  GHDL v0
$end
$timescale
  1 fs
$end
$scope module standard $end
$upscope $end
$scope module std_logic_1164 $end
$upscope $end
$scope module numeric_std $end
$upscope $end
$scope module up_counter_16bit_tb $end
$var reg 1 ! clk $end
$var reg 1 " reset $end
$var reg 16 # count[15:0] $end
$scope module uut $end
$var reg 1 $ clk $end
$var reg 1 % reset $end
$var reg 16 & count[15:0] $end
$var reg 16 ' counter[15:0] $end
$upscope $end
$upscope $end
$enddefinitions $end
#0
0!
1"
b0000000000000000 #
0$
1%
b0000000000000000 &
b0000000000000000 '
#5000000
1!
1$
#10000000
0!
0$
#15000000
1!
1$
#20000000
0!
0"
0$
0%
#25000000
1!
b0000000000000001 #
1$
b0000000000000001 &
b0000000000000001 '
#30000000
0!
0$
#35000000
1!
b0000000000000010 #
1$
b0000000000000010 &
b0000000000000010 '
#40000000
0!
0$
#45000000
1!
b0000000000000011 #
1$
b0000000000000011 &
b0000000000000011 '
#50000000
0!
0$
#55000000
1!
b0000000000000100 #
1$
b0000000000000100 &
b0000000000000100 '
#60000000
0!
0$
#65000000
1!
b0000000000000101 #
1$
b0000000000000101 &
b0000000000000101 '
#70000000
0!
0$
#75000000
1!
b0000000000000110 #
1$
b0000000000000110 &
b0000000000000110 '
#80000000
0!
0$
#85000000
1!
b0000000000000111 #
1$
b0000000000000111 &
b0000000000000111 '
#90000000
0!
0$
#95000000
1!
b0000000000001000 #
1$
b0000000000001000 &
b0000000000001000 '
#100000000
0!
0$
#105000000
1!
b0000000000001001 #
1$
b0000000000001001 &
b0000000000001001 '
#110000000
0!
0$
#115000000
1!
b0000000000001010 #
1$
b0000000000001010 &
b0000000000001010 '
#120000000
0!
0$
#125000000
1!
b0000000000001011 #
1$
b0000000000001011 &
b0000000000001011 '
#130000000
0!
0$
#135000000
1!
b0000000000001100 #
1$
b0000000000001100 &
b0000000000001100 '
#140000000
0!
0$
#145000000
1!
b0000000000001101 #
1$
b0000000000001101 &
b0000000000001101 '
#150000000
0!
0$
#155000000
1!
b0000000000001110 #
1$
b0000000000001110 &
b0000000000001110 '
#160000000
0!
0$
#165000000
1!
b0000000000001111 #
1$
b0000000000001111 &
b0000000000001111 '
#170000000
0!
0$
#175000000
1!
b0000000000010000 #
1$
b0000000000010000 &
b0000000000010000 '
#180000000
0!
0$
#185000000
1!
b0000000000010001 #
1$
b0000000000010001 &
b0000000000010001 '
#190000000
0!
0$
#195000000
1!
b0000000000010010 #
1$
b0000000000010010 &
b0000000000010010 '
#200000000
0!
0$
#205000000
1!
b0000000000010011 #
1$
b0000000000010011 &
b0000000000010011 '
#210000000
0!
0$
#215000000
1!
b0000000000010100 #
1$
b0000000000010100 &
b0000000000010100 '
#220000000
0!
0$
#225000000
1!
b0000000000010101 #
1$
b0000000000010101 &
b0000000000010101 '
#230000000
0!
0$
#235000000
1!
b0000000000010110 #
1$
b0000000000010110 &
b0000000000010110 '
#240000000
0!
0$
#245000000
1!
b0000000000010111 #
1$
b0000000000010111 &
b0000000000010111 '
