src/p1_2nd_system_step_response/lib/saturation.vhd
library IEEE;
use IEEE.STD_LOGIC_1164.ALL;
use IEEE.NUMERIC_STD.ALL;

-- Include the saturation module
-- Change the path to match the location of your Saturation.vhdl file
entity Saturation is
    Port (
        x       : in  integer;
        max_val : in  integer;
        min_val : in  integer;
        y       : out integer
    );
end entity Saturation;

architecture SaturationRTL of Saturation is
begin
    process(x, max_val, min_val)
    begin
        if x > max_val then
            y <= max_val;
        elsif x < min_val then
            y <= min_val;
        else
            y <= x;
        end if;
    end process;
end SaturationRTL;

src/p3_feedback_loop_pid_controller/lib/pid.vhd
library IEEE;
use IEEE.STD_LOGIC_1164.ALL;
use IEEE.NUMERIC_STD.ALL;

entity PID is
    Port (
        clk   : in  std_logic;
        rst   : in  std_logic;
        e     : in  integer;
        u     : out integer
    );
end entity PID;

architecture PIDRTL of PID is

    constant MAX_VALUE : integer := 65536;
    constant MIN_VALUE : integer := -65536;

    -- Internal signals for storing the previous output value
    signal s_sat_in : integer := 0;
    signal s_e : integer := 0;
    signal s_de : integer := 0;
    signal s_p, s_i, s_d : integer := 0;
    signal s_int_saturated : std_logic := '0';

    -- Filter coefficients (adjust these based on your desired cutoff frequency)
    constant K_p : integer := 2;
    constant K_i : integer := 1;
    constant K_d : integer := 110;

    component Saturation is
        Port (
            x       : in  integer;
            max_val : in  integer;
            min_val : in  integer;
            y       : out integer
        );
    end component;

begin
    process(clk, rst)
    begin
        if rst = '1' then
            -- Reset the internal state and output when the reset signal is asserted
            s_e <= 0;
            s_de <= 0;
            s_p <= 0;
            s_i <= 0;
            s_d <= 0;
            s_sat_in <= 0;
            s_int_saturated <= '0';
        elsif rising_edge(clk) then

             -- PID terms
             s_p <= K_p * s_e ;
             s_i <= s_i + K_i * s_e / 25;
             s_d <= K_d * (s_e - s_de);  -- calculate derivative

             s_de <= s_e;
             s_e <= e;

             -- Update output with saturation (adjust limits as needed)
             s_sat_in <= (s_p + s_i + s_d);

        end if;
    end process;

    saturation_inst : Saturation
    port map (
        max_val => MAX_VALUE,
        min_val => MIN_VALUE,
        x       => s_sat_in,
        y       => u
    );
end PIDRTL;

src/p3_feedback_loop_pid_controller/lib/plant.vhd
library IEEE;
use IEEE.STD_LOGIC_1164.ALL;
use IEEE.NUMERIC_STD.ALL;



entity Plant2ndOrder is
    Port (
        clk     : in  std_logic;
        rst     : in  std_logic;
        u       : in  integer;
        y       : out integer;
    );
end Main;

architecture Plant2ndOrderRTL of Plant2ndOrder is

    signal s_y : integer := 0;
    signal s_dy : integer := 0;
    signal s_ddy : integer := 0;

    constant SCALE_VALUE : integer := 8192;
    constant SCALE_DT : integer := 100;

    constant MAX_VALUE : integer := 65536;
    constant MIN_VALUE : integer := -65536;

    constant K : integer := 1 * SCALE_VALUE;

    constant b2 : integer := 1 * SCALE_VALUE;
    constant b1 : integer := 2 * SCALE_VALUE;
    constant b0 : integer := 10 * SCALE_VALUE;

    constant a0 : integer := 10 * SCALE_VALUE;

    component Saturation is
        Port (
            x       : in  integer;
            max_val : in  integer;
            min_val : in  integer;
            y       : out integer
        );
    end component;

    signal s_sat_in : integer;
    signal s_sat_out : integer;

begin
    process(clk, rst)
    begin
        if rst = '1' then
            s_y <= 0;
            s_dy <= 0;
            s_ddy <= 0;
            s_sat_in <= 0;
        elsif rising_edge(clk) then
            s_ddy <= (u) * (a0 / b2) - s_dy * (b1 / b2) - s_y * (b0 / b2);
            s_dy  <= s_dy + s_ddy / SCALE_DT;
            s_y   <= s_y + s_dy / SCALE_DT;

            s_sat_in <= s_y;
        end if;
    end process;

    saturation_inst : Saturation
    port map (
        max_val => MAX_VALUE,
        min_val => MIN_VALUE,
        x       => s_sat_in,
        y       => s_sat_out
    );

    y <= s_sat_out;

end Plant2ndOrderRTL;

src/p3_feedback_loop_pid_controller/src/main.vhd
library IEEE;
use IEEE.STD_LOGIC_1164.ALL;
use IEEE.NUMERIC_STD.ALL;


entity Main is
    Port (
        clk     : in  std_logic;
        rst     : in  std_logic;
        ref     : in  integer;
        dist    : in  integer;
        y       : out integer
    );
end Main;

architecture Behavioral of Main is

    signal s_pre_y : integer;
    signal s_y : integer;
    signal s_u : integer;
    signal s_e : integer;

    constant SCALE_VALUE : integer := 8192;
    constant SCALE_DT : integer := 100;

    constant MAX_VALUE : integer := 65536;
    constant MIN_VALUE : integer := -65536;

    component Plant2ndOrder is
        Port (
            clk   : in  std_logic;
            rst   : in  std_logic;
            u       : in  integer;
            y       : out integer
        );
    end component;


    component PID is
        Port (
            clk   : in  std_logic;
            rst   : in  std_logic;
            e     : in  integer;
            u     : out integer
        );
    end component;



begin
    process(clk, rst)
    begin
        if rst = '1' then
            s_e <= 0;
            s_y <= 0;
        elsif rising_edge(clk) then
            s_e <= ref - s_y ;
            s_y <= s_pre_y + dist;
        end if;
    end process;

    plant2ndOrder_inst : Plant2ndOrder
    port map (
        clk => clk,
        rst => rst,
        u => s_u,
        y => s_pre_y
    );

    pid_inst : PID
    port map (
        clk => clk,
        rst => rst,
        e => s_e,
        u => s_u
    );

    y <= s_y;

end Behavioral;

src/p3_feedback_loop_pid_controller/test/main_testbench.vhd
library IEEE;
use IEEE.STD_LOGIC_1164.ALL;
use IEEE.NUMERIC_STD.ALL;

entity Main_tb is
end Main_tb;

architecture testbench of Main_tb is
    -- Component declaration for the DUT (Design Under Test)
    component Main
        Port (
            clk   : in  std_logic;   -- Clock input
            rst   : in  std_logic;   -- Reset input
            ref     : in  integer;     -- Input integer
            y     : out integer;      -- Output scaled integer
            dist     : in integer      -- Output scaled integer
        );
    end component;

    -- Test signals
    signal clk   : std_logic := '0';   -- Test bench clock signal
    signal rst   : std_logic := '0';   -- Test bench reset signal
    signal ref   : integer := 0;       -- Test bench input signal
    signal y     : integer := 0;             -- Test bench output signal
    signal dist  : integer := 0;             -- Test bench output signal

begin
    -- Instantiate the DUT
    dut : Main
        port map (
            clk => clk,
            rst => rst,
            ref   => ref,
            dist   => dist,
            y   => y
        );

    -- Clock process
    clk_process : process
    begin
        while now < 30000 ns loop  -- Run for 1000 ns
            clk <= not clk;  -- Toggle clock every half period
            wait for 5 ns;         -- Wait for half period
        end loop;
        wait;  -- Stop simulation
    end process;

    -- Stimulus process
    stimulus : process
    begin
        ref <= 0;
        dist <= 0;
        rst <= '1';   -- Assert reset

        wait for 10 ns;
        ref <= 0;
        dist <= 0;
        rst <= '0';   -- Deassert reset

        wait for 10 ns;  -- u(t) = 0
        ref <= 0;
        dist <= 0;

        wait for 10 ns;   -- u(t) = 1
        ref <= 512;
        dist <= 0;

        wait for 1024 ns;   -- u(t) = 1
        ref <= 500;
        dist <= 100;

        wait for 1024 ns;   -- u(t) = 1
        ref <= 500;
        dist <= 0;

        wait for 1024 ns;   -- u(t) = 1
        ref <= 500;
        dist <= 0;

        wait for 1024 ns;   -- u(t) = 1
        ref <= 500;
        dist <= 0;

        wait;  -- Stop simulation
    end process;
end testbench;

src/p3_feedback_loop_pid_controller/test/main_wave.vcd
$date
  Fri Jul 12 16:02:39 2024
$end
$version
  GHDL v0
$end
$timescale
  1 fs
$end
$scope module standard $end
$upscope $end
$scope module std_logic_1164 $end
$upscope $end
$scope module numeric_std $end
$upscope $end
$scope module main_tb $end
$var reg 1 ! clk $end
$var reg 1 " rst $end
$var integer 32 # ref $end
$var integer 32 $ y $end
$var integer 32 % dist $end
$scope module dut $end
$var reg 1 & clk $end
$var reg 1 ' rst $end
$var integer 32 ( ref $end
$var integer 32 ) dist $end
$var integer 32 * y $end
$var integer 32 + s_pre_y $end
$var integer 32 , s_y $end
$var integer 32 - s_u $end
$var integer 32 . s_e $end
$scope module plant2ndorder_inst $end
$var reg 1 / clk $end
$var reg 1 0 rst $end
$var integer 32 1 u $end
$var integer 32 2 y $end
$var integer 32 3 s_y $end
$var integer 32 4 s_dy $end
$var integer 32 5 s_ddy $end
$var integer 32 6 s_sat_in $end
$var integer 32 7 s_sat_out $end
$scope module saturation_inst $end
$var integer 32 8 x $end
$var integer 32 9 max_val $end
$var integer 32 : min_val $end
$var integer 32 ; y $end
$upscope $end
$upscope $end
$scope module pid_inst $end
$var reg 1 < clk $end
$var reg 1 = rst $end
$var integer 32 > e $end
$var integer 32 ? u $end
$var integer 32 @ s_sat_in $end
$var integer 32 A s_e $end
$var integer 32 B s_de $end
$var integer 32 C s_p $end
$var integer 32 D s_i $end
$var integer 32 E s_d $end
$var reg 1 F s_int_saturated $end
$scope module saturation_inst $end
$var integer 32 G x $end
$var integer 32 H max_val $end
$var integer 32 I min_val $end
$var integer 32 J y $end
$upscope $end
$upscope $end
$upscope $end
$upscope $end
$enddefinitions $end
#0
1!
1"
b0 #
b0 $
b0 %
1&
1'
b0 (
b0 )
b0 *
b0 +
b0 ,
b0 -
b0 .
1/
10
b0 1
b0 2
b0 3
b0 4
b0 5
b0 6
b0 7
b0 8
b11111010000000000000000000 9
b11111100000110000000000000000000 :
b0 ;
1<
1=
b0 >
b0 ?
b0 @
b0 A
b0 B
b0 C
b0 D
b0 E
0F
b0 G
b11111010000000000000000000 H
b11111100000110000000000000000000 I
b0 J
#5000000
0!
0&
0/
0<
#10000000
1!
0"
1&
0'
1/
00
1<
0=
#15000000
0!
0&
0/
0<
#20000000
1!
1&
1/
1<
#25000000
0!
0&
0/
0<
#30000000
1!
b1000000000 #
1&
b1000000000 (
b1000000000 .
1/
1<
b1000000000 >
#35000000
0!
0&
0/
0<
#40000000
1!
1&
1/
1<
b1000000000 A
#45000000
0!
0&
0/
0<
#50000000
1!
1&
1/
1<
b1000000000 B
b1100100000000000 C
b10100000000000000 E
#55000000
0!
0&
0/
0<
#60000000
1!
1&
b100000100000000000 -
1/
b100000100000000000 1
1<
b100000100000000000 ?
b100000100000000000 @
b0 E
b100000100000000000 G
b100000100000000000 J
#65000000
0!
0&
0/
0<
#70000000
1!
1&
b1100100000000000 -
1/
b1100100000000000 1
b10000010000000000000 5
1<
b1100100000000000 ?
b1100100000000000 @
b1100100000000000 G
b1100100000000000 J
#75000000
0!
0&
0/
0<
#80000000
1!
1&
1/
b1010011001100 4
b110010000000000000 5
1<
#85000000
0!
0&
0/
0<
#90000000
1!
1&
1/
b110101 3
b1110011001100 4
b11111111111111111011011010001000 5
1<
#95000000
0!
0&
0/
0<
#100000000
1!
1&
b110101 +
1/
b110101 2
b1111110 3
b1110000010000 4
b11111111111111100110011001010011 5
b110101 6
b110101 7
b110101 8
b110101 ;
1<
#105000000
0!
0&
0/
0<
#110000000
1!
b110101 $
1&
b110101 *
b1111110 +
b110101 ,
1/
b1111110 2
b11000101 3
b1011111111000 4
b11111111111111101000010011100010 5
b1111110 6
b1111110 7
b1111110 8
b1111110 ;
1<
#115000000
0!
0&
0/
0<
#120000000
1!
b1111110 $
1&
b1111110 *
b11000101 +
b1111110 ,
b111001011 .
1/
b11000101 2
b100000010 3
b1010000101110 4
b11111111111111110011000010001011 5
b11000101 6
b11000101 7
b11000101 8
b11000101 ;
1<
b111001011 >
#125000000
0!
0&
0/
0<
#130000000
1!
b11000101 $
1&
b11000101 *
b100000010 +
b11000101 ,
b110000010 .
1/
b100000010 2
b100110101 3
b1001000011011 4
b11111111111111111100111101110010 5
b100000010 6
b100000010 7
b100000010 8
b100000010 ;
1<
b110000010 >
b111001011 A
#135000000
0!
0&
0/
0<
#140000000
1!
b100000010 $
1&
b100000010 *
b100110101 +
b100000010 ,
b100111011 .
1/
b100110101 2
b101100011 3
b1000110011111 4
b10011001011101 5
b100110101 6
b100110101 7
b100110101 8
b100110101 ;
1<
b100111011 >
b110000010 A
b111001011 B
b1011001101001100 C
b11111111111111111101111011100000 E
#145000000
0!
0&
0/
0<
#150000000
1!
b100110101 $
1&
b100110101 *
b101100011 +
b100110101 ,
b1001001000101100 -
b11111110 .
1/
b1001001000101100 1
b101100011 2
b110010000 3
b1001000000001 4
b11101010000111 5
b101100011 6
b101100011 7
b101100011 8
b101100011 ;
1<
b11111110 >
b1001001000101100 ?
b1001001000101100 @
b100111011 A
b110000010 B
b1001011011001000 C
b11111111111111111101001001100000 E
b1001001000101100 G
b1001001000101100 J
#155000000
0!
0&
0/
0<
#160000000
1!
b101100011 $
1&
b101100011 *
b110010000 +
b101100011 ,
b110100100101000 -
b11001011 .
1/
b110100100101000 1
b110010000 2
b110111110 3
b1001010010110 4
b11111111111111110101001011110110 5
b110010000 6
b110010000 7
b110010000 8
b110010000 ;
1<
b11001011 >
b110100100101000 ?
b110100100101000 @
b11111110 A
b100111011 B
b111101100001100 C
b11111111111111111101001110100000 E
b110100100101000 G
b110100100101000 J
#165000000
0!
0&
0/
0<
#170000000
1!
b110010000 $
1&
b110010000 *
b110111110 +
b110010000 ,
b100111010101100 -
b10011101 .
1/
b100111010101100 1
b110111110 2
b111101101 3
b1000011011100 4
b11111111111111101001011001000110 5
b110111110 6
b110111110 7
b110111110 8
b110111110 ;
1<
b10011101 >
b100111010101100 ?
b100111010101100 @
b11001011 A
b11111110 B
b110001100111000 C
b11111111111111111101100111100000 E
b100111010101100 G
b100111010101100 J
#175000000
0!
0&
0/
0<
#180000000
1!
b110111110 $
1&
b110111110 *
b111101101 +
b110111110 ,
b11110100011000 -
b1110000 .
1/
b11110100011000 1
b111101101 2
b1000011000 3
b110100111110 4
b11111111111111100111010010101011 5
b111101101 6
b111101101 7
b111101101 8
b111101101 ;
1<
b1110000 >
b11110100011000 ?
b11110100011000 @
b10011101 A
b11001011 B
b100111101001100 C
b11111111111111111110000000100000 E
b11110100011000 G
b11110100011000 J
#185000000
0!
0&
0/
0<
#190000000
1!
b111101101 $
1&
b111101101 *
b1000011000 +
b111101101 ,
b10111101101100 -
b1000010 .
1/
b10111101101100 1
b1000011000 2
b1000111001 3
b100101001010 4
b11111111111111101100011000011100 5
b1000011000 6
b1000011000 7
b1000011000 8
b1000011000 ;
1<
b1000010 >
b10111101101100 ?
b10111101101100 @
b1110000 A
b10011101 B
b11110101010100 C
b11111111111111111110001101000000 E
b10111101101100 G
b10111101101100 J
#195000000
0!
0&
0/
0<
#200000000
1!
b1000011000 $
1&
b1000011000 *
b1000111001 +
b1000011000 ,
b10000010010100 -
b10011 .
1/
b10000010010100 1
b1000111001 2
b1001010000 3
b11000100111 4
b11111111111111110011010101010011 5
b1000111001 6
b1000111001 7
b1000111001 8
b1000111001 ;
1<
b10011 >
b10000010010100 ?
b10000010010100 @
b1000010 A
b1110000 B
b10101111000000 C
b11111111111111111110001111100000 E
b10000010010100 G
b10000010010100 J
#205000000
0!
0&
0/
0<
#210000000
1!
b1000111001 $
1&
b1000111001 *
b1001010000 +
b1000111001 ,
b111110100000 -
b11111111111111111111111111101000 .
1/
b111110100000 1
b1001010000 2
b1001011111 3
b10000100001 4
b11111111111111110111110110011010 5
b1001010000 6
b1001010000 7
b1001010000 8
b1001010000 ;
1<
b11111111111111111111111111101000 >
b111110100000 ?
b111110100000 @
b10011 A
b1000010 B
b1100111001000 C
b11111111111111111110001101000000 E
b111110100000 G
b111110100000 J
#215000000
0!
0&
0/
0<
#220000000
1!
b1001010000 $
1&
b1001010000 *
b1001011111 +
b1001010000 ,
b11111111111111111111110100001000 -
b11111111111111111111111111000111 .
1/
b11111111111111111111110100001000 1
b1001011111 2
b1001101001 3
b1011010100 4
b11111111111111111000111010110111 5
b1001011111 6
b1001011111 7
b1001011111 8
b1001011111 ;
1<
b11111111111111111111111111000111 >
b11111111111111111111110100001000 ?
b11111111111111111111110100001000 @
b11111111111111111111111111101000 A
b10011 B
b11101101100 C
b11111111111111111110001010100000 E
b11111111111111111111110100001000 G
b11111111111111111111110100001000 J
#225000000
0!
0&
0/
0<
#230000000
1!
b1001011111 $
1&
b1001011111 *
b1001101001 +
b1001011111 ,
b11111111111111111110101000001100 -
b11111111111111111111111110110000 .
1/
b11111111111111111110101000001100 1
b1001101001 2
b1001110000 3
b110110010 4
b11111111111111110111101011101111 5
b1001101001 6
b1001101001 7
b1001101001 8
b1001101001 ;
1<
b11111111111111111111111110110000 >
b11111111111111111110101000001100 ?
b11111111111111111110101000001100 @
b11111111111111111111111111000111 A
b11111111111111111111111111101000 B
b11111111111111111111011010100000 C
b11111111111111111110010100100000 E
b11111111111111111110101000001100 G
b11111111111111111110101000001100 J
#235000000
0!
0&
0/
0<
#240000000
1!
b1001101001 $
1&
b1001101001 *
b1001110000 +
b1001101001 ,
b11111111111111111101101111000000 -
b11111111111111111111111110100001 .
1/
b11111111111111111101101111000000 1
b1001110000 2
b1001110100 3
b1011110 4
b11111111111111110101111010001100 5
b1001110000 6
b1001110000 7
b1001110000 8
b1001110000 ;
1<
b11111111111111111111111110100001 >
b11111111111111111101101111000000 ?
b11111111111111111101101111000000 @
b11111111111111111111111110110000 A
b11111111111111111111111111000111 B
b11111111111111111110100110111100 C
b11111111111111111110101101100000 E
b11111111111111111101101111000000 G
b11111111111111111101101111000000 J
#245000000
0!
0&
0/
0<
#250000000
1!
b1001110000 $
1&
b1001110000 *
b1001110100 +
b1001110000 ,
b11111111111111111101010100011100 -
b11111111111111111111111110010111 .
1/
b11111111111111111101010100011100 1
b1001110100 2
b11111111111111111111111011000001 4
b11111111111111110101110100100000 5
b1001110100 6
b1001110100 7
b1001110100 8
b1001110100 ;
1<
b11111111111111111111111110010111 >
b11111111111111111101010100011100 ?
b11111111111111111101010100011100 @
b11111111111111111111111110100001 A
b11111111111111111111111110110000 B
b11111111111111111110000011000000 C
b11111111111111111111000110100000 E
b11111111111111111101010100011100 G
b11111111111111111101010100011100 J
#255000000
0!
0&
0/
0<
#260000000
1!
b1001110100 $
1&
b1001110100 *
b1001110100 ,
b11111111111111111101001001100000 -
b11111111111111111111111110010000 .
1/
b11111111111111111101001001100000 1
b1001110001 3
b11111111111111111111110100100001 4
b11111111111111111000011001010010 5
1<
b11111111111111111111111110010000 >
b11111111111111111101001001100000 ?
b11111111111111111101001001100000 @
b11111111111111111111111110010111 A
b11111111111111111111111110100001 B
b11111111111111111101101011100100 C
b11111111111111111111011010100000 E
b11111111111111111101001001100000 G
b11111111111111111101001001100000 J
#265000000
0!
0&
0/
0<
#270000000
1!
1&
b1001110001 +
b11111111111111111101000110000100 -
b11111111111111111111111110001100 .
1/
b11111111111111111101000110000100 1
b1001110001 2
b1001101010 3
b11111111111111111111101111101010 4
b11111111111111111011111110100101 5
b1001110001 6
b1001110001 7
b1001110001 8
b1001110001 ;
1<
b11111111111111111111111110001100 >
b11111111111111111101000110000100 ?
b11111111111111111101000110000100 @
b11111111111111111111111110010000 A
b11111111111111111111111110010111 B
b11111111111111111101011011111100 C
b11111111111111111111100111000000 E
b11111111111111111101000110000100 G
b11111111111111111101000110000100 J
#275000000
0!
0&
0/
0<
#280000000
1!
b1001110001 $
1&
b1001110001 *
b1001101010 +
b1001110001 ,
b11111111111111111101000010111100 -
1/
b11111111111111111101000010111100 1
b1001101010 2
b1001100000 3
b11111111111111111111101101000110 4
b11111111111111111110111101000010 5
b1001101010 6
b1001101010 7
b1001101010 8
b1001101010 ;
1<
b11111111111111111101000010111100 ?
b11111111111111111101000010111100 @
b11111111111111111111111110001100 A
b11111111111111111111111110010000 B
b11111111111111111101010001000000 C
b11111111111111111111101110100000 E
b11111111111111111101000010111100 G
b11111111111111111101000010111100 J
#285000000
0!
0&
0/
0<
#290000000
1!
b1001101010 $
1&
b1001101010 *
b1001100000 +
b1001101010 ,
b11111111111111111100111111100000 -
b11111111111111111111111110001111 .
1/
b11111111111111111100111111100000 1
b1001100000 2
b1001010100 3
b11111111111111111111101100011100 4
b11100010100 5
b1001100000 6
b1001100000 7
b1001100000 8
b1001100000 ;
1<
b11111111111111111111111110001111 >
b11111111111111111100111111100000 ?
b11111111111111111100111111100000 @
b11111111111111111111111110001100 B
b11111111111111111101001010110000 C
b11111111111111111111110110000000 E
b11111111111111111100111111100000 G
b11111111111111111100111111100000 J
#295000000
0!
0&
0/
0<
#300000000
1!
b1001100000 $
1&
b1001100000 *
b1001010100 +
b1001100000 ,
b11111111111111111101000000110000 -
b11111111111111111111111110010110 .
1/
b11111111111111111101000000110000 1
b1001010100 2
b1001001000 3
b11111111111111111111101100101110 4
b101010010100 5
b1001010100 6
b1001010100 7
b1001010100 8
b1001010100 ;
1<
b11111111111111111111111110010110 >
b11111111111111111101000000110000 ?
b11111111111111111101000000110000 @
b11111111111111111111111110001111 A
b0 E
b11111111111111111101000000110000 G
b11111111111111111101000000110000 J
#305000000
0!
0&
0/
0<
#310000000
1!
b1001010100 $
1&
b1001010100 *
b1001001000 +
b1001010100 ,
b11111111111111111101001010110000 -
b11111111111111111111111110100000 .
1/
b11111111111111111101001010110000 1
b1001001000 2
b1000111100 3
b11111111111111111111101101001001 4
b100011101100 5
b1001001000 6
b1001001000 7
b1001001000 8
b1001001000 ;
1<
b11111111111111111111111110100000 >
b11111111111111111101001010110000 ?
b11111111111111111101001010110000 @
b11111111111111111111111110010110 A
b11111111111111111111111110001111 B
b11111111111111111101001111011100 C
b111100000 E
b11111111111111111101001010110000 G
b11111111111111111101001010110000 J
#315000000
0!
0&
0/
0<
#320000000
1!
b1001001000 $
1&
b1001001000 *
b1000111100 +
b1001001000 ,
b11111111111111111101010110111100 -
b11111111111111111111111110101100 .
1/
b11111111111111111101010110111100 1
b1000111100 2
b1000110000 3
b11111111111111111111101101011111 4
b111010001010 5
b1000111100 6
b1000111100 7
b1000111100 8
b1000111100 ;
1<
b11111111111111111111111110101100 >
b11111111111111111101010110111100 ?
b11111111111111111101010110111100 @
b11111111111111111111111110100000 A
b11111111111111111111111110010110 B
b11111111111111111101011010011000 C
b10001100000 E
b11111111111111111101010110111100 G
b11111111111111111101010110111100 J
#325000000
0!
0&
0/
0<
#330000000
1!
b1000111100 $
1&
b1000111100 *
b1000110000 +
b1000111100 ,
b11111111111111111101101011111000 -
b11111111111111111111111110111000 .
1/
b11111111111111111101101011111000 1
b1000110000 2
b1000100101 3
b11111111111111111111101110000100 4
b1011100101010 5
b1000110000 6
b1000110000 7
b1000110000 8
b1000110000 ;
1<
b11111111111111111111111110111000 >
b11111111111111111101101011111000 ?
b11111111111111111101101011111000 @
b11111111111111111111111110101100 A
b11111111111111111111111110100000 B
b11111111111111111101101010000000 C
b11001000000 E
b11111111111111111101101011111000 G
b11111111111111111101101011111000 J
#335000000
0!
0&
0/
0<
#340000000
1!
b1000110000 $
1&
b1000110000 *
b1000100101 +
b1000110000 ,
b11111111111111111110000011000000 -
b11111111111111111111111111000100 .
1/
b11111111111111111110000011000000 1
b1000100101 2
b1000011010 3
b11111111111111111111101110111111 4
b10011000010011 5
b1000100101 6
b1000100101 7
b1000100101 8
b1000100101 ;
1<
b11111111111111111111111111000100 >
b11111111111111111110000011000000 ?
b11111111111111111110000011000000 @
b11111111111111111111111110111000 A
b11111111111111111111111110101100 B
b11111111111111111101111100110000 C
b11110000000 E
b11111111111111111110000011000000 G
b11111111111111111110000011000000 J
#345000000
0!
0&
0/
0<
#350000000
1!
b1000100101 $
1&
b1000100101 *
b1000011010 +
b1000100101 ,
b11111111111111111110011010110000 -
b11111111111111111111111111010000 .
1/
b11111111111111111110011010110000 1
b1000011010 2
b1000010000 3
b11111111111111111111110000100000 4
b11001110010000 5
b1000011010 6
b1000011010 7
b1000011010 8
b1000011010 ;
1<
b11111111111111111111111111010000 >
b11111111111111111110011010110000 ?
b11111111111111111110011010110000 @
b11111111111111111111111111000100 A
b11111111111111111111111110111000 B
b11111111111111111110001111100000 C
b11111111111111111110011010110000 G
b11111111111111111110011010110000 J
#355000000
0!
0&
0/
0<
#360000000
1!
b1000011010 $
1&
b1000011010 *
b1000010000 +
b1000011010 ,
b11111111111111111110101101100000 -
b11111111111111111111111111011011 .
1/
b11111111111111111110101101100000 1
b1000010000 2
b1000000111 3
b11111111111111111111110010100100 4
b11101101110000 5
b1000010000 6
b1000010000 7
b1000010000 8
b1000010000 ;
1<
b11111111111111111111111111011011 >
b11111111111111111110101101100000 ?
b11111111111111111110101101100000 @
b11111111111111111111111111010000 A
b11111111111111111111111111000100 B
b11111111111111111110100010010000 C
b11111111111111111110101101100000 G
b11111111111111111110101101100000 J
#365000000
0!
0&
0/
0<
#370000000
1!
b1000010000 $
1&
b1000010000 *
b1000000111 +
b1000010000 ,
b11111111111111111111000000010000 -
b11111111111111111111111111100110 .
1/
b11111111111111111111000000010000 1
b1000000111 2
b111111111 3
b11111111111111111111110100111100 4
b11100010010001 5
b1000000111 6
b1000000111 7
b1000000111 8
b1000000111 ;
1<
b11111111111111111111111111100110 >
b11111111111111111111000000010000 ?
b11111111111111111111000000010000 @
b11111111111111111111111111011011 A
b11111111111111111111111111010000 B
b11111111111111111110110101000000 C
b11111111111111111111000000010000 G
b11111111111111111111000000010000 J
#375000000
0!
0&
0/
0<
#380000000
1!
b1000000111 $
1&
b1000000111 *
b111111111 +
b1000000111 ,
b11111111111111111111010011000000 -
b11111111111111111111111111110000 .
1/
b11111111111111111111010011000000 1
b111111111 2
b111111000 3
b11111111111111111111110111001100 4
b11001001101001 5
b111111111 6
b111111111 7
b111111111 8
b111111111 ;
1<
b11111111111111111111111111110000 >
b11111111111111111111010011000000 ?
b11111111111111111111010011000000 @
b11111111111111111111111111100110 A
b11111111111111111111111111011011 B
b11111111111111111111000110001100 C
b11011100000 E
b11111111111111111111010011000000 G
b11111111111111111111010011000000 J
#385000000
0!
0&
0/
0<
#390000000
1!
b111111111 $
1&
b111111111 *
b111111000 +
b111111111 ,
b11111111111111111111100001101100 -
b11111111111111111111111111111001 .
1/
b11111111111111111111100001101100 1
b111111000 2
b111110011 3
b11111111111111111111111001001101 4
b10110110010000 5
b111111000 6
b111111000 7
b111111000 8
b111111000 ;
1<
b11111111111111111111111111111001 >
b11111111111111111111100001101100 ?
b11111111111111111111100001101100 @
b11111111111111111111111111110000 A
b11111111111111111111111111100110 B
b11111111111111111111010111011000 C
b11111111111111111111100001101100 G
b11111111111111111111100001101100 J
#395000000
0!
0&
0/
0<
#400000000
1!
b111111000 $
1&
b111111000 *
b111110011 +
b111111000 ,
b11111111111111111111110010111000 -
b1 .
1/
b11111111111111111111110010111000 1
b111110011 2
b111101111 3
b11111111111111111111111011000001 4
b10011100011011 5
b111110011 6
b111110011 7
b111110011 8
b111110011 ;
1<
b1 >
b11111111111111111111110010111000 ?
b11111111111111111111110010111000 @
b11111111111111111111111111111001 A
b11111111111111111111111111110000 B
b11111111111111111111100111000000 C
b11001000000 E
b11111111111111111111110010111000 G
b11111111111111111111110010111000 J
#405000000
0!
0&
0/
0<
#410000000
1!
b111110011 $
1&
b111110011 *
b111101111 +
b111110011 ,
b0 -
b1000 .
1/
b0 1
b111101111 2
b111101100 3
b11111111111111111111111100100101 4
b10010101000111 5
b111101111 6
b111101111 7
b111101111 8
b111101111 ;
1<
b1000 >
b0 ?
b0 @
b1 A
b11111111111111111111111111111001 B
b11111111111111111111110101000100 C
b10110100000 E
b0 G
b0 J
#415000000
0!
0&
0/
0<
#420000000
1!
b111101111 $
1&
b111101111 *
b111101100 +
b111101111 ,
b1011100100 -
b1101 .
1/
b1011100100 1
b111101100 2
b111101010 3
b11111111111111111111111110000100 4
b10001000000010 5
b111101100 6
b111101100 7
b111101100 8
b111101100 ;
1<
b1101 >
b1011100100 ?
b1011100100 @
b1000 A
b1 B
b1100100 C
b10100000000 E
b1011100100 G
b1011100100 J
#425000000
0!
0&
0/
0<
#430000000
1!
b111101100 $
1&
b111101100 *
b111101010 +
b111101100 ,
b10101100100 -
b10001 .
1/
b10101100100 1
b111101010 2
b111101001 3
b11111111111111111111111111011011 4
b1110111111110 5
b111101010 6
b111101010 7
b111101010 8
b111101010 ;
1<
b10001 >
b10101100100 ?
b10101100100 @
b1101 A
b1000 B
b1100100000 C
b10001100000 E
b10101100100 G
b10101100100 J
#435000000
0!
0&
0/
0<
#440000000
1!
b111101010 $
1&
b111101010 *
b111101001 +
b111101010 ,
b11110000000 -
b10100 .
1/
b11110000000 1
b111101001 2
b100111 4
b1100110111001 5
b111101001 6
b111101001 7
b111101001 8
b111101001 ;
1<
b10100 >
b11110000000 ?
b11110000000 @
b10001 A
b1101 B
b10100010100 C
b1100100000 E
b11110000000 G
b11110000000 J
#445000000
0!
0&
0/
0<
#450000000
1!
b111101001 $
1&
b111101001 *
b111101001 ,
b100000110100 -
b10110 .
1/
b100000110100 1
b1101000 4
b1010110110001 5
1<
b10110 >
b100000110100 ?
b100000110100 @
b10100 A
b10001 B
b11010100100 C
b1010000000 E
b100000110100 G
b100000110100 J
#455000000
0!
0&
0/
0<
#460000000
1!
1&
b100100100100 -
b10111 .
1/
b100100100100 1
b111101010 3
b10011111 4
b110111010111 5
1<
b10111 >
b100100100100 ?
b100100100100 @
b10110 A
b10100 B
b11111010000 C
b111100000 E
b100100100100 G
b100100100100 J
#465000000
0!
0&
0/
0<
#470000000
1!
1&
b111101010 +
b100110110000 -
1/
b100110110000 1
b111101010 2
b111101011 3
b11000010 4
b100010010000 5
b111101010 6
b111101010 7
b111101010 8
b111101010 ;
1<
b100110110000 ?
b100110110000 @
b10111 A
b10110 B
b100010011000 C
b101000000 E
b100110110000 G
b100110110000 J
#475000000
0!
0&
0/
0<
#480000000
1!
b111101010 $
1&
b111101010 *
b111101011 +
b111101010 ,
b100111011000 -
1/
b100111011000 1
b111101011 2
b111101100 3
b11010111 4
b10100000001 5
b111101011 6
b111101011 7
b111101011 8
b111101011 ;
1<
b100111011000 ?
b100111011000 @
b10111 B
b100011111100 C
b10100000 E
b100111011000 G
b100111011000 J
#485000000
0!
0&
0/
0<
