src/p4_state_space_3th_system/lib/math/3x3/matrix_inverse_3x3.component.vhd
library IEEE;
use IEEE.STD_LOGIC_1164.ALL;
use IEEE.NUMERIC_STD.ALL;

entity Matrix_Inverse_3x3 is
    Port (
        clk   : in  std_logic;
        reset : in  std_logic;
        A11, A12, A13 : in  integer;
        A21, A22, A23 : in  integer;
        A31, A32, A33 : in  integer;
        SCALE         : in  integer;
        C11, C12, C13 : out integer;
        C21, C22, C23 : out integer;
        C31, C32, C33 : out integer;
        valid         : out std_logic
    );
end entity Matrix_Inverse_3x3;

architecture Matrix_Inverse_3x3_RTL of Matrix_Inverse_3x3 is
    signal determinant : integer;
begin
    process (clk, reset)
    begin
        if reset = '1' then
            -- Reset all output signals and internal signals
            C11 <= 0;
            C12 <= 0;
            C13 <= 0;
            C21 <= 0;
            C22 <= 0;
            C23 <= 0;
            C31 <= 0;
            C32 <= 0;
            C33 <= 0;
            valid <= '0';
            determinant <= 0;
        elsif rising_edge(clk) then
            -- Calculate the determinant of the 3x3 matrix
            --determinant <= A11 * (A22 * A33 - A23 * A32) -  A12 * (A21 * A33 - A23 * A31) +  A13 * (A21 * A32 - A22 * A31);
            determinant <= 13 + (A22 * A11);
            if determinant /= 0 then

                -- Calculate the inverse matrix elements
                C11 <= 0;
                C12 <= 0;
                C13 <= 0;
                C21 <= 0;
                C22 <= 0;
                C23 <= 0;
                C31 <= 0;
                C32 <= 0;
                C33 <= 0;

                valid <= '1'; -- Inverse is valid
            else
                -- If determinant is zero, inverse does not exist
                C11 <= 0;
                C12 <= 0;
                C13 <= 0;
                C21 <= 0;
                C22 <= 0;
                C23 <= 0;
                C31 <= 0;
                C32 <= 0;
                C33 <= 0;
                valid <= '0'; -- Inverse is not valid
            end if;
        end if;
    end process;
end architecture Matrix_Inverse_3x3_RTL;

src/p4_state_space_3th_system/lib/math/3x3/matrix_inverse_3x3.testbench.vhd
library IEEE;
use IEEE.STD_LOGIC_1164.ALL;
use IEEE.NUMERIC_STD.ALL;

entity Matrix_Inverse_3x3_Testbench is
end entity Matrix_Inverse_3x3_Testbench;

architecture testbench of Matrix_Inverse_3x3_Testbench is

    -- Component declaration
    component Matrix_Inverse_3x3
        Port (
            clk   : in  std_logic;
            reset : in  std_logic;

            SCALE         : in integer;  -- Scaling factor

            A11, A12, A13 : in integer;
            A21, A22, A23 : in integer;
            A31, A32, A33 : in integer;

            C11, C12, C13 : out integer;
            C21, C22, C23 : out integer;
            C31, C32, C33 : out integer;
            valid         : out std_logic
        );
    end component;

    -- Signals declaration
    signal clk, reset                          : std_logic := '0';  -- Clock and reset signals
    signal A11, A12, A13, A21, A22, A23, A31, A32, A33 : integer := 0;  -- Matrix A elements
    signal SCALE                              : integer := 1;  -- Scaling factor
    signal C11, C12, C13, C21, C22, C23, C31, C32, C33 : integer := 0;  -- Output matrix elements
    signal valid                                       : std_logic := '0'; -- Valid signal

    -- Clock generation
    constant clk_period : time := 10 ns;

begin

    -- Clock process definition
    clk_process : process
    begin
        while now < 500 ns loop
            clk <= '0';
            wait for clk_period / 2;
            clk <= '1';
            wait for clk_period / 2;
        end loop;
    end process clk_process;

    -- Instantiate the Matrix_Inverse_3x3 module
    dut : Matrix_Inverse_3x3
        port map (
            clk => clk,
            reset => reset,
            A11 => A11, A12 => A12, A13 => A13,
            A21 => A21, A22 => A22, A23 => A23,
            A31 => A31, A32 => A32, A33 => A33,
            SCALE => SCALE,
            C11 => C11, C12 => C12, C13 => C13,
            C21 => C21, C22 => C22, C23 => C23,
            C31 => C31, C32 => C32, C33 => C33,
            valid => valid
        );

    -- Stimulus process
    stimulus: process
    begin
        -- Initialize reset
        reset <= '1';
        wait for 20 ns;
        reset <= '0';

        -- Test Case 1: Identity Matrix (should result in Identity Matrix)
        SCALE <= 10000;
        wait for 10 ns;
        A11 <= 1 * SCALE; A12 <= 0 * SCALE; A13 <= 0 * SCALE;
        A21 <= 0 * SCALE; A22 <= 1 * SCALE; A23 <= 0 * SCALE;
        A31 <= 0 * SCALE; A32 <= 0 * SCALE; A33 <= 1 * SCALE;

        wait for 30 ns;
        assert C11 = 1 * SCALE and C12 = 0 * SCALE and C13 = 0 * SCALE and
               C21 = 0 * SCALE and C22 = 1 * SCALE and C23 = 0 * SCALE and
               C31 = 0 * SCALE and C32 = 0 * SCALE and C33 = 1 * SCALE and
               valid = '1'
            report "Test Case 1 Failed: Identity Matrix. Expected (10000,0,0; 0,10000,0; 0,0,10000, valid=1), Got (" & 
               integer'image(C11) & "," & integer'image(C12) & "," & integer'image(C13) & "; " &
               integer'image(C21) & "," & integer'image(C22) & "," & integer'image(C23) & "; " &
               integer'image(C31) & "," & integer'image(C32) & "," & integer'image(C33) & ", valid=" & std_logic'image(valid) & ")"
            severity error;

        -- Test Case 2: Arbitrary invertible matrix
        SCALE <= 10000;
        wait for 10 ns;
        A11 <=  2 * SCALE; A12 <= -1 * SCALE; A13 <=  0 * SCALE;
        A21 <= -1 * SCALE; A22 <=  2 * SCALE; A23 <= -1 * SCALE;
        A31 <=  0 * SCALE; A32 <= -1 * SCALE; A33 <=  2 * SCALE;

        wait for 30 ns;

        assert C11 = 2 * SCALE and C12 = 1 * SCALE and C13 = 0 * SCALE and
               C21 = 1 * SCALE and C22 = 2 * SCALE and C23 = 1 * SCALE and
               C31 = 0 * SCALE and C32 = 1 * SCALE and C33 = 2 * SCALE and
               valid = '1'
            report "Test Case 2 Failed: Arbitrary invertible matrix. Expected (20000,10000,0; 10000,20000,10000; 0,10000,20000, valid=1), Got (" & 
                integer'image(C11) & "," & integer'image(C12) & "," & integer'image(C13) & "; " &
                integer'image(C21) & "," & integer'image(C22) & "," & integer'image(C23) & "; " &
                integer'image(C31) & "," & integer'image(C32) & "," & integer'image(C33) & ", valid=" & std_logic'image(valid) & ")"
            severity error;

        -- Test Case 3: Non-invertible matrix (determinant = 0)
        SCALE <= 100;
        wait for 10 ns;
        A11 <= 1 * SCALE; A12 <= 2 * SCALE; A13 <= 3 * SCALE;
        A21 <= 4 * SCALE; A22 <= 5 * SCALE; A23 <= 6 * SCALE;
        A31 <= 7 * SCALE; A32 <= 8 * SCALE; A33 <= 9 * SCALE;

        wait for 30 ns;

        assert C11 = 0 * SCALE and C12 = 0 * SCALE and C13 = 0 * SCALE and
               C21 = 0 * SCALE and C22 = 0 * SCALE and C23 = 0 * SCALE and
               C31 = 0 * SCALE and C32 = 0 * SCALE and C33 = 0 * SCALE and
               valid = '0'
            report "Test Case 3 Failed: Non-invertible matrix. Expected (0,0,0; 0,0,0; 0,0,0, valid=0), Got (" & 
                integer'image(C11) & "," & integer'image(C12) & "," & integer'image(C13) & "; " &
                integer'image(C21) & "," & integer'image(C22) & "," & integer'image(C23) & "; " &
                integer'image(C31) & "," & integer'image(C32) & "," & integer'image(C33) & ", valid=" & std_logic'image(valid) & ")"
            severity error;

        -- Test Case 4: Invertible matrix
        wait for 10 ns;
        SCALE <= 10;
        A11 <= 4 * SCALE; A12 <= 7 * SCALE; A13 <= 2 * SCALE;
        A21 <= 3 * SCALE; A22 <= 6 * SCALE; A23 <= 1 * SCALE;
        A31 <= 2 * SCALE; A32 <= 5 * SCALE; A33 <= 1 * SCALE;



        wait for 50 ns;

        assert C11 = -1 * SCALE and C12 = 1 * SCALE and C13 = 0 * SCALE and
               C21 = 2 * SCALE and C22 = -2 * SCALE and C23 = 1 * SCALE and
               C31 = 1 * SCALE and C32 = -1 * SCALE and C33 = 0 * SCALE and
               valid = '1'
            report "Test Case 4 Failed: Invertible matrix. Expected (-10000,10000,0; 20000,-20000,10000; 10000,-10000,0, valid=1), Got (" & 
                integer'image(C11) & "," & integer'image(C12) & "," & integer'image(C13) & "; " &
                integer'image(C21) & "," & integer'image(C22) & "," & integer'image(C23) & "; " &
                integer'image(C31) & "," & integer'image(C32) & "," & integer'image(C33) & ", valid=" & std_logic'image(valid) & ")"
            severity error;

        -- End the simulation
        wait;
    end process stimulus;

end architecture testbench;

src/p4_state_space_3th_system/test/waves/Matrix_Inverse_3x3_Testbench_wave.vcd
$date
  Sun Jun  9 17:38:45 2024
$end
$version
  GHDL v0
$end
$timescale
  1 fs
$end
$scope module standard $end
$upscope $end
$scope module std_logic_1164 $end
$upscope $end
$scope module numeric_std $end
$upscope $end
$scope module matrix_inverse_3x3_testbench $end
$var reg 1 ! clk $end
$var reg 1 " reset $end
$var integer 32 # a11 $end
$var integer 32 $ a12 $end
$var integer 32 % a13 $end
$var integer 32 & a21 $end
$var integer 32 ' a22 $end
$var integer 32 ( a23 $end
$var integer 32 ) a31 $end
$var integer 32 * a32 $end
$var integer 32 + a33 $end
$var integer 32 , scale $end
$var integer 32 - c11 $end
$var integer 32 . c12 $end
$var integer 32 / c13 $end
$var integer 32 0 c21 $end
$var integer 32 1 c22 $end
$var integer 32 2 c23 $end
$var integer 32 3 c31 $end
$var integer 32 4 c32 $end
$var integer 32 5 c33 $end
$var reg 1 6 valid $end
$scope module dut $end
$var reg 1 7 clk $end
$var reg 1 8 reset $end
$var integer 32 9 a11 $end
$var integer 32 : a12 $end
$var integer 32 ; a13 $end
$var integer 32 < a21 $end
$var integer 32 = a22 $end
$var integer 32 > a23 $end
$var integer 32 ? a31 $end
$var integer 32 @ a32 $end
$var integer 32 A a33 $end
$var integer 32 B scale $end
$var integer 32 C c11 $end
$var integer 32 D c12 $end
$var integer 32 E c13 $end
$var integer 32 F c21 $end
$var integer 32 G c22 $end
$var integer 32 H c23 $end
$var integer 32 I c31 $end
$var integer 32 J c32 $end
$var integer 32 K c33 $end
$var reg 1 L valid $end
$var integer 32 M determinant $end
$upscope $end
$upscope $end
$enddefinitions $end
#0
0!
1"
b0 #
b0 $
b0 %
b0 &
b0 '
b0 (
b0 )
b0 *
b0 +
b1 ,
b0 -
b0 .
b0 /
b0 0
b0 1
b0 2
b0 3
b0 4
b0 5
06
07
18
b0 9
b0 :
b0 ;
b0 <
b0 =
b0 >
b0 ?
b0 @
b0 A
b1 B
b0 C
b0 D
b0 E
b0 F
b0 G
b0 H
b0 I
b0 J
b0 K
0L
b0 M
#5000000
1!
17
#10000000
0!
07
#15000000
1!
17
#20000000
0!
0"
b10011100010000 ,
07
08
b10011100010000 B
#25000000
1!
17
b1101 M
#30000000
0!
b10011100010000 #
b10011100010000 '
b10011100010000 +
07
b10011100010000 9
b10011100010000 =
b10011100010000 A
#35000000
1!
16
17
1L
b101111101011110000100001101 M
#40000000
0!
07
#45000000
1!
17
#50000000
0!
07
#55000000
1!
17
#60000000
0!
07
#65000000
1!
17
#70000000
0!
b100111000100000 #
b11111111111111111101100011110000 $
b11111111111111111101100011110000 &
b100111000100000 '
b11111111111111111101100011110000 (
b11111111111111111101100011110000 *
b100111000100000 +
07
b100111000100000 9
b11111111111111111101100011110000 :
b11111111111111111101100011110000 <
b100111000100000 =
b11111111111111111101100011110000 >
b11111111111111111101100011110000 @
b100111000100000 A
#75000000
1!
17
b10111110101111000010000001101 M
#80000000
0!
07
#85000000
1!
17
#90000000
0!
07
#95000000
1!
17
#100000000
0!
b1010 ,
07
b1010 B
#105000000
1!
17
#110000000
0!
b1010 #
b10100 $
b11110 %
b101000 &
b110010 '
b111100 (
b1000110 )
b1010000 *
b1011010 +
07
b1010 9
b10100 :
b11110 ;
b101000 <
b110010 =
b111100 >
b1000110 ?
b1010000 @
b1011010 A
#115000000
1!
17
b1000000001 M
#120000000
0!
07
#125000000
1!
17
#130000000
0!
07
#135000000
1!
17
#140000000
0!
07
#145000000
1!
17
#150000000
0!
b101000 #
b1000110 $
b10100 %
b11110 &
b111100 '
b1010 (
b10100 )
b110010 *
b1010 +
07
b101000 9
b1000110 :
b10100 ;
b11110 <
b111100 =
b1010 >
b10100 ?
b110010 @
b1010 A
#155000000
1!
17
b100101101101 M
