src/p4_state_space_3th_system/lib/math/3x3/matrix_inverse_3x3.component.vhd
library IEEE;
use IEEE.STD_LOGIC_1164.ALL;
use IEEE.NUMERIC_STD.ALL;

entity Matrix_Inverse_3x3 is
    Port (
        clk   : in  std_logic;
        reset : in  std_logic;

        SCALE         : in  integer;

        A11, A12, A13 : in  integer;
        A21, A22, A23 : in  integer;
        A31, A32, A33 : in  integer;

        C11, C12, C13 : out integer;
        C21, C22, C23 : out integer;
        C31, C32, C33 : out integer;

        valid         : out std_logic
    );
end entity Matrix_Inverse_3x3;

architecture Matrix_Inverse_3x3_RTL of Matrix_Inverse_3x3 is
    signal topC11, topC12, topC13, topC21, topC22, topC23, topC31, topC32, topC33 : signed(127 downto 0);
    signal bottomC11, bottomC12, bottomC13, bottomC21, bottomC22, bottomC23, bottomC31, bottomC32, bottomC33 : signed(127 downto 0);
    signal mC11, mC12, mC13, mC21, mC22, mC23, mC31, mC32, mC33 : signed(127 downto 0);
    signal determinant : signed(127 downto 0);
    signal det1 : signed(127 downto 0);
    signal det2 : signed(127 downto 0);
    signal det3 : signed(127 downto 0);
    signal det4 : signed(127 downto 0);
    signal det5 : signed(127 downto 0);
    signal det6 : signed(127 downto 0);

    -- Convert input integers to signed 64-bit values
    function to_signed32(value: integer) return signed is
    begin
        return to_signed(value, 32);
    end function;

    -- Custom function to convert signed value to integer
    function signed_to_integer(value: signed) return integer is
    begin
        return to_integer(value);
    end function;

begin
    process (clk, reset)
    begin
        if reset = '1' then
            -- Reset all output signals and internal signals
            C11 <= 0;
            C12 <= 0;
            C13 <= 0;
            C21 <= 0;
            C22 <= 0;
            C23 <= 0;
            C31 <= 0;
            C32 <= 0;
            C33 <= 0;

            -- Initialize all signals to a known value
            topC11 <= (others => '0');
            topC12 <= (others => '0');
            topC13 <= (others => '0');
            topC21 <= (others => '0');
            topC22 <= (others => '0');
            topC23 <= (others => '0');
            topC31 <= (others => '0');
            topC32 <= (others => '0');
            topC33 <= (others => '0');

            -- Initialize other signals similarly
            bottomC11 <= (others => '0');
            bottomC12 <= (others => '0');
            bottomC13 <= (others => '0');
            bottomC21 <= (others => '0');
            bottomC22 <= (others => '0');
            bottomC23 <= (others => '0');
            bottomC31 <= (others => '0');
            bottomC32 <= (others => '0');
            bottomC33 <= (others => '0');

            mC11 <= (others => '0');
            mC12 <= (others => '0');
            mC13 <= (others => '0');
            mC21 <= (others => '0');
            mC22 <= (others => '0');
            mC23 <= (others => '0');
            mC31 <= (others => '0');
            mC32 <= (others => '0');
            mC33 <= (others => '0');

            determinant <= (others => '0');
            det1 <= (others => '0');
            det2 <= (others => '0');
            det3 <= (others => '0');
            det4 <= (others => '0');
            det5 <= (others => '0');
            det6 <= (others => '0');

            valid <= '0';

        elsif rising_edge(clk) then
            -- Calculate the determinant of the 3x3 matrix

            det1 <= to_signed32(A11) * to_signed32(A22) * to_signed32(A33) * to_signed32(1) / ( SCALE * SCALE );
            det2 <= to_signed32(A12) * to_signed32(A23) * to_signed32(A31) * to_signed32(1) / ( SCALE * SCALE );
            det3 <= to_signed32(A13) * to_signed32(A21) * to_signed32(A32) * to_signed32(1) / ( SCALE * SCALE );
            det4 <= to_signed32(A13) * to_signed32(A22) * to_signed32(A31) * to_signed32(1) / ( SCALE * SCALE );
            det5 <= to_signed32(A12) * to_signed32(A21) * to_signed32(A33) * to_signed32(1) / ( SCALE * SCALE );
            det6 <= to_signed32(A11) * to_signed32(A23) * to_signed32(A32) * to_signed32(1) / ( SCALE * SCALE );

            determinant <=  det1 + det2 + det3 - det4 - det5 - det6 ;

            topC11 <= to_signed32(A22) * to_signed32(A33) * to_signed32(1) * to_signed32(1) / ( SCALE ) - to_signed32(A23) * to_signed32(A32) * to_signed32(1) * to_signed32(1) / ( SCALE );
            bottomC11 <= determinant;

            mC11 <= (bottomC11) / (topC11);


            --if determinant /= 0 then
            if false then
                -- Calculate the inverse matrix elements
                topC11 <= to_signed32(A22) * to_signed32(A33) * to_signed32(1) * to_signed32(1) - to_signed32(A23) * to_signed32(A32) * to_signed32(1) * to_signed32(1);
                topC12 <= to_signed32(A13) * to_signed32(A32) * to_signed32(1) * to_signed32(1) - to_signed32(A12) * to_signed32(A33) * to_signed32(1) * to_signed32(1);
                topC13 <= to_signed32(A12) * to_signed32(A23) * to_signed32(1) * to_signed32(1) - to_signed32(A13) * to_signed32(A22) * to_signed32(1) * to_signed32(1);
                topC21 <= to_signed32(A23) * to_signed32(A31) * to_signed32(1) * to_signed32(1) - to_signed32(A21) * to_signed32(A33) * to_signed32(1) * to_signed32(1);
                topC22 <= to_signed32(A11) * to_signed32(A33) * to_signed32(1) * to_signed32(1) - to_signed32(A13) * to_signed32(A31) * to_signed32(1) * to_signed32(1);
                topC23 <= to_signed32(A13) * to_signed32(A21) * to_signed32(1) * to_signed32(1) - to_signed32(A11) * to_signed32(A23) * to_signed32(1) * to_signed32(1);
                topC31 <= to_signed32(A21) * to_signed32(A32) * to_signed32(1) * to_signed32(1) - to_signed32(A22) * to_signed32(A31) * to_signed32(1) * to_signed32(1);
                topC32 <= to_signed32(A12) * to_signed32(A31) * to_signed32(1) * to_signed32(1) - to_signed32(A11) * to_signed32(A32) * to_signed32(1) * to_signed32(1);
                topC33 <= to_signed32(A11) * to_signed32(A22) * to_signed32(1) * to_signed32(1) - to_signed32(A12) * to_signed32(A21) * to_signed32(1) * to_signed32(1);

                bottomC11 <= determinant;
                bottomC12 <= determinant;
                bottomC13 <= determinant;
                bottomC21 <= determinant;
                bottomC22 <= determinant;
                bottomC23 <= determinant;
                bottomC31 <= determinant;
                bottomC32 <= determinant;
                bottomC33 <= determinant;

                mC11 <= topC11 / bottomC11;
                mC12 <= topC12 / bottomC12;
                mC13 <= topC13 / bottomC13;
                mC21 <= topC21 / bottomC21;
                mC22 <= topC22 / bottomC22;
                mC23 <= topC23 / bottomC23;
                mC31 <= topC31 / bottomC31;
                mC32 <= topC32 / bottomC32;
                mC33 <= topC33 / bottomC33;

                -- Convert back to 32-bit signed integer for output
                C11 <= signed_to_integer(resize(mC11, 32));
                C12 <= signed_to_integer(resize(mC12, 32));
                C13 <= signed_to_integer(resize(mC13, 32));
                C21 <= signed_to_integer(resize(mC21, 32));
                C22 <= signed_to_integer(resize(mC22, 32));
                C23 <= signed_to_integer(resize(mC23, 32));
                C31 <= signed_to_integer(resize(mC31, 32));
                C32 <= signed_to_integer(resize(mC32, 32));
                C33 <= signed_to_integer(resize(mC33, 32));

                valid <= '1'; -- Inverse is valid
            else
                -- If determinant is zero, inverse does not exist
                C11 <= signed_to_integer(resize(mC11, 32)); -- 1000000000
                C12 <= 0; -- 1 000 000
                C13 <= 0; -- 1 000 000 000;

                C21 <= 0; -- 500000
                C22 <= 0;
                C23 <= 0;
                C31 <= 0;
                C32 <= 0;
                C33 <= 0;
                valid <= '0'; -- Inverse is not valid
            end if;
        end if;
    end process;
end architecture Matrix_Inverse_3x3_RTL;

src/p4_state_space_3th_system/lib/math/3x3/matrix_inverse_3x3.testbench.vhd
library IEEE;
use IEEE.STD_LOGIC_1164.ALL;
use IEEE.NUMERIC_STD.ALL;

entity Matrix_Inverse_3x3_Testbench is
end entity Matrix_Inverse_3x3_Testbench;

architecture testbench of Matrix_Inverse_3x3_Testbench is

    -- Component declaration
    component Matrix_Inverse_3x3
        Port (
            clk   : in  std_logic;
            reset : in  std_logic;

            SCALE         : in integer;  -- Scaling factor

            A11, A12, A13 : in integer;
            A21, A22, A23 : in integer;
            A31, A32, A33 : in integer;

            C11, C12, C13 : out integer;
            C21, C22, C23 : out integer;
            C31, C32, C33 : out integer;
            valid         : out std_logic
        );
    end component;

    -- Signals declaration
    signal clk, reset                          : std_logic := '0';  -- Clock and reset signals
    signal A11, A12, A13, A21, A22, A23, A31, A32, A33 : integer := 0;  -- Matrix A elements
    signal SCALE                              : integer := 1;  -- Scaling factor
    signal C11, C12, C13, C21, C22, C23, C31, C32, C33 : integer := 0;  -- Output matrix elements
    signal valid                                       : std_logic := '0'; -- Valid signal

    -- Clock generation
    constant clk_period : time := 10 ns;

begin

    -- Clock process definition
    clk_process : process
    begin
        while now < 500 ns loop
            clk <= '0';
            wait for clk_period / 2;
            clk <= '1';
            wait for clk_period / 2;
        end loop;
    end process clk_process;

    -- Instantiate the Matrix_Inverse_3x3 module
    dut : Matrix_Inverse_3x3
        port map (
            clk => clk,
            reset => reset,
            A11 => A11, A12 => A12, A13 => A13,
            A21 => A21, A22 => A22, A23 => A23,
            A31 => A31, A32 => A32, A33 => A33,
            SCALE => SCALE,
            C11 => C11, C12 => C12, C13 => C13,
            C21 => C21, C22 => C22, C23 => C23,
            C31 => C31, C32 => C32, C33 => C33,
            valid => valid
        );

    -- Stimulus process
    stimulus: process
    begin
        -- Initialize reset
        reset <= '1';
        wait for 20 ns;
        reset <= '0';

        -- Test Case 1: Identity Matrix (should result in Identity Matrix)
        SCALE <= 10000;
        wait for 10 ns;
        A11 <= 1 * SCALE; A12 <= 0 * SCALE; A13 <= 0 * SCALE;
        A21 <= 0 * SCALE; A22 <= 1 * SCALE; A23 <= 0 * SCALE;
        A31 <= 0 * SCALE; A32 <= 0 * SCALE; A33 <= 1 * SCALE;

        wait for 30 ns;
        assert C11 = 1 * SCALE and C12 = 0 * SCALE and C13 = 0 * SCALE and
               C21 = 0 * SCALE and C22 = 1 * SCALE and C23 = 0 * SCALE and
               C31 = 0 * SCALE and C32 = 0 * SCALE and C33 = 1 * SCALE and
               valid = '1'
            report "Test Case 1 Failed: Identity Matrix. Expected (10000,0,0; 0,10000,0; 0,0,10000, valid=1), Got (" & 
               integer'image(C11) & "," & integer'image(C12) & "," & integer'image(C13) & "; " &
               integer'image(C21) & "," & integer'image(C22) & "," & integer'image(C23) & "; " &
               integer'image(C31) & "," & integer'image(C32) & "," & integer'image(C33) & ", valid=" & std_logic'image(valid) & ")"
            severity error;

        -- Test Case 2: Arbitrary invertible matrix
        SCALE <= 10000;
        wait for 10 ns;
        A11 <=  2 * SCALE; A12 <= -1 * SCALE; A13 <=  0 * SCALE;
        A21 <= -1 * SCALE; A22 <=  2 * SCALE; A23 <= -1 * SCALE;
        A31 <=  0 * SCALE; A32 <= -1 * SCALE; A33 <=  2 * SCALE;

        wait for 30 ns;

        assert C11 = 2 * SCALE and C12 = 1 * SCALE and C13 = 0 * SCALE and
               C21 = 1 * SCALE and C22 = 2 * SCALE and C23 = 1 * SCALE and
               C31 = 0 * SCALE and C32 = 1 * SCALE and C33 = 2 * SCALE and
               valid = '1'
            report "Test Case 2 Failed: Arbitrary invertible matrix. Expected (20000,10000,0; 10000,20000,10000; 0,10000,20000, valid=1), Got (" & 
                integer'image(C11) & "," & integer'image(C12) & "," & integer'image(C13) & "; " &
                integer'image(C21) & "," & integer'image(C22) & "," & integer'image(C23) & "; " &
                integer'image(C31) & "," & integer'image(C32) & "," & integer'image(C33) & ", valid=" & std_logic'image(valid) & ")"
            severity error;

        -- Test Case 3: Non-invertible matrix (determinant = 0)
        SCALE <= 10000;
        wait for 10 ns;
        A11 <= 1 * SCALE; A12 <= 2 * SCALE; A13 <= 3 * SCALE;
        A21 <= 4 * SCALE; A22 <= 5 * SCALE; A23 <= 6 * SCALE;
        A31 <= 7 * SCALE; A32 <= 8 * SCALE; A33 <= 9 * SCALE;

        wait for 30 ns;

        assert C11 = 0 * SCALE and C12 = 0 * SCALE and C13 = 0 * SCALE and
               C21 = 0 * SCALE and C22 = 0 * SCALE and C23 = 0 * SCALE and
               C31 = 0 * SCALE and C32 = 0 * SCALE and C33 = 0 * SCALE and
               valid = '0'
            report "Test Case 3 Failed: Non-invertible matrix. Expected (0,0,0; 0,0,0; 0,0,0, valid=0), Got (" & 
                integer'image(C11) & "," & integer'image(C12) & "," & integer'image(C13) & "; " &
                integer'image(C21) & "," & integer'image(C22) & "," & integer'image(C23) & "; " &
                integer'image(C31) & "," & integer'image(C32) & "," & integer'image(C33) & ", valid=" & std_logic'image(valid) & ")"
            severity error;

        -- Test Case 4: Invertible matrix
        wait for 10 ns;
        SCALE <= 10000;
        A11 <= 4 * SCALE; A12 <= 7 * SCALE; A13 <= 2 * SCALE;
        A21 <= 3 * SCALE; A22 <= 6 * SCALE; A23 <= 1 * SCALE;
        A31 <= 2 * SCALE; A32 <= 5 * SCALE; A33 <= 1 * SCALE;



        wait for 30 ns;

        assert C11 = -1 * SCALE and C12 = 1 * SCALE and C13 = 0 * SCALE and
               C21 = 2 * SCALE and C22 = -2 * SCALE and C23 = 1 * SCALE and
               C31 = 1 * SCALE and C32 = -1 * SCALE and C33 = 0 * SCALE and
               valid = '1'
            report "Test Case 4 Failed: Invertible matrix. Expected (-10000,10000,0; 20000,-20000,10000; 10000,-10000,0, valid=1), Got (" & 
                integer'image(C11) & "," & integer'image(C12) & "," & integer'image(C13) & "; " &
                integer'image(C21) & "," & integer'image(C22) & "," & integer'image(C23) & "; " &
                integer'image(C31) & "," & integer'image(C32) & "," & integer'image(C33) & ", valid=" & std_logic'image(valid) & ")"
            severity error;

        -- End the simulation
        wait;
    end process stimulus;

end architecture testbench;

src/p4_state_space_3th_system/test/waves/Matrix_Inverse_3x3_Testbench_wave.vcd
$date
  Fri Jun 21 11:42:08 2024
$end
$version
  GHDL v0
$end
$timescale
  1 fs
$end
$scope module standard $end
$upscope $end
$scope module std_logic_1164 $end
$upscope $end
$scope module numeric_std $end
$upscope $end
$scope module matrix_inverse_3x3_testbench $end
$var reg 1 ! clk $end
$var reg 1 " reset $end
$var integer 32 # a11 $end
$var integer 32 $ a12 $end
$var integer 32 % a13 $end
$var integer 32 & a21 $end
$var integer 32 ' a22 $end
$var integer 32 ( a23 $end
$var integer 32 ) a31 $end
$var integer 32 * a32 $end
$var integer 32 + a33 $end
$var integer 32 , scale $end
$var integer 32 - c11 $end
$var integer 32 . c12 $end
$var integer 32 / c13 $end
$var integer 32 0 c21 $end
$var integer 32 1 c22 $end
$var integer 32 2 c23 $end
$var integer 32 3 c31 $end
$var integer 32 4 c32 $end
$var integer 32 5 c33 $end
$var reg 1 6 valid $end
$scope module dut $end
$var reg 1 7 clk $end
$var reg 1 8 reset $end
$var integer 32 9 scale $end
$var integer 32 : a11 $end
$var integer 32 ; a12 $end
$var integer 32 < a13 $end
$var integer 32 = a21 $end
$var integer 32 > a22 $end
$var integer 32 ? a23 $end
$var integer 32 @ a31 $end
$var integer 32 A a32 $end
$var integer 32 B a33 $end
$var integer 32 C c11 $end
$var integer 32 D c12 $end
$var integer 32 E c13 $end
$var integer 32 F c21 $end
$var integer 32 G c22 $end
$var integer 32 H c23 $end
$var integer 32 I c31 $end
$var integer 32 J c32 $end
$var integer 32 K c33 $end
$var reg 1 L valid $end
$var reg 128 M topc11[127:0] $end
$var reg 128 N topc12[127:0] $end
$var reg 128 O topc13[127:0] $end
$var reg 128 P topc21[127:0] $end
$var reg 128 Q topc22[127:0] $end
$var reg 128 R topc23[127:0] $end
$var reg 128 S topc31[127:0] $end
$var reg 128 T topc32[127:0] $end
$var reg 128 U topc33[127:0] $end
$var reg 128 V bottomc11[127:0] $end
$var reg 128 W bottomc12[127:0] $end
$var reg 128 X bottomc13[127:0] $end
$var reg 128 Y bottomc21[127:0] $end
$var reg 128 Z bottomc22[127:0] $end
$var reg 128 [ bottomc23[127:0] $end
$var reg 128 \ bottomc31[127:0] $end
$var reg 128 ] bottomc32[127:0] $end
$var reg 128 ^ bottomc33[127:0] $end
$var reg 128 _ mc11[127:0] $end
$var reg 128 ` mc12[127:0] $end
$var reg 128 a mc13[127:0] $end
$var reg 128 b mc21[127:0] $end
$var reg 128 c mc22[127:0] $end
$var reg 128 d mc23[127:0] $end
$var reg 128 e mc31[127:0] $end
$var reg 128 f mc32[127:0] $end
$var reg 128 g mc33[127:0] $end
$var reg 128 h determinant[127:0] $end
$var reg 128 i det1[127:0] $end
$var reg 128 j det2[127:0] $end
$var reg 128 k det3[127:0] $end
$var reg 128 l det4[127:0] $end
$var reg 128 m det5[127:0] $end
$var reg 128 n det6[127:0] $end
$upscope $end
$upscope $end
$enddefinitions $end
#0
0!
1"
b0 #
b0 $
b0 %
b0 &
b0 '
b0 (
b0 )
b0 *
b0 +
b1 ,
b0 -
b0 .
b0 /
b0 0
b0 1
b0 2
b0 3
b0 4
b0 5
06
07
18
b1 9
b0 :
b0 ;
b0 <
b0 =
b0 >
b0 ?
b0 @
b0 A
b0 B
b0 C
b0 D
b0 E
b0 F
b0 G
b0 H
b0 I
b0 J
b0 K
0L
b00000000000000000000000000000000000000000000000000000000000000000000000000000000000000000000000000000000000000000000000000000000 M
b00000000000000000000000000000000000000000000000000000000000000000000000000000000000000000000000000000000000000000000000000000000 N
b00000000000000000000000000000000000000000000000000000000000000000000000000000000000000000000000000000000000000000000000000000000 O
b00000000000000000000000000000000000000000000000000000000000000000000000000000000000000000000000000000000000000000000000000000000 P
b00000000000000000000000000000000000000000000000000000000000000000000000000000000000000000000000000000000000000000000000000000000 Q
b00000000000000000000000000000000000000000000000000000000000000000000000000000000000000000000000000000000000000000000000000000000 R
b00000000000000000000000000000000000000000000000000000000000000000000000000000000000000000000000000000000000000000000000000000000 S
b00000000000000000000000000000000000000000000000000000000000000000000000000000000000000000000000000000000000000000000000000000000 T
b00000000000000000000000000000000000000000000000000000000000000000000000000000000000000000000000000000000000000000000000000000000 U
b00000000000000000000000000000000000000000000000000000000000000000000000000000000000000000000000000000000000000000000000000000000 V
b00000000000000000000000000000000000000000000000000000000000000000000000000000000000000000000000000000000000000000000000000000000 W
b00000000000000000000000000000000000000000000000000000000000000000000000000000000000000000000000000000000000000000000000000000000 X
b00000000000000000000000000000000000000000000000000000000000000000000000000000000000000000000000000000000000000000000000000000000 Y
b00000000000000000000000000000000000000000000000000000000000000000000000000000000000000000000000000000000000000000000000000000000 Z
b00000000000000000000000000000000000000000000000000000000000000000000000000000000000000000000000000000000000000000000000000000000 [
b00000000000000000000000000000000000000000000000000000000000000000000000000000000000000000000000000000000000000000000000000000000 \
b00000000000000000000000000000000000000000000000000000000000000000000000000000000000000000000000000000000000000000000000000000000 ]
b00000000000000000000000000000000000000000000000000000000000000000000000000000000000000000000000000000000000000000000000000000000 ^
b00000000000000000000000000000000000000000000000000000000000000000000000000000000000000000000000000000000000000000000000000000000 _
b00000000000000000000000000000000000000000000000000000000000000000000000000000000000000000000000000000000000000000000000000000000 `
b00000000000000000000000000000000000000000000000000000000000000000000000000000000000000000000000000000000000000000000000000000000 a
b00000000000000000000000000000000000000000000000000000000000000000000000000000000000000000000000000000000000000000000000000000000 b
b00000000000000000000000000000000000000000000000000000000000000000000000000000000000000000000000000000000000000000000000000000000 c
b00000000000000000000000000000000000000000000000000000000000000000000000000000000000000000000000000000000000000000000000000000000 d
b00000000000000000000000000000000000000000000000000000000000000000000000000000000000000000000000000000000000000000000000000000000 e
b00000000000000000000000000000000000000000000000000000000000000000000000000000000000000000000000000000000000000000000000000000000 f
b00000000000000000000000000000000000000000000000000000000000000000000000000000000000000000000000000000000000000000000000000000000 g
b00000000000000000000000000000000000000000000000000000000000000000000000000000000000000000000000000000000000000000000000000000000 h
b00000000000000000000000000000000000000000000000000000000000000000000000000000000000000000000000000000000000000000000000000000000 i
b00000000000000000000000000000000000000000000000000000000000000000000000000000000000000000000000000000000000000000000000000000000 j
b00000000000000000000000000000000000000000000000000000000000000000000000000000000000000000000000000000000000000000000000000000000 k
b00000000000000000000000000000000000000000000000000000000000000000000000000000000000000000000000000000000000000000000000000000000 l
b00000000000000000000000000000000000000000000000000000000000000000000000000000000000000000000000000000000000000000000000000000000 m
b00000000000000000000000000000000000000000000000000000000000000000000000000000000000000000000000000000000000000000000000000000000 n
#5000000
1!
17
#10000000
0!
07
#15000000
1!
17
#20000000
0!
0"
b1111101000 ,
07
08
b1111101000 9
#25000000
1!
17
#30000000
0!
b11111010000 #
b11111010000 '
b11111010000 +
07
b11111010000 :
b11111010000 >
b11111010000 B
#35000000
1!
17
b00000000000000000000000000000000000000000000000000000000000000000000000000000000000000000000000000000000000000000001111101000000 i
#40000000
0!
07
#45000000
1!
17
b00000000000000000000000000000000000000000000000000000000000000000000000000000000000000000000000000000000000000000001111101000000 h
#50000000
0!
07
#55000000
1!
16
17
1L
b00000000000000000000000000000000000000000000000000000000000000000000000000000000000000000000000000000000000000000000111110100000 M
b00000000000000000000000000000000000000000000000000000000000000000000000000000000000000000000000000000000000000000000111110100000 Q
b00000000000000000000000000000000000000000000000000000000000000000000000000000000000000000000000000000000000000000000111110100000 U
b00000000000000000000000000000000000000000000000000000000000000000000000000000000000000000000000000000000000000000000000000001000 V
b00000000000000000000000000000000000000000000000000000000000000000000000000000000000000000000000000000000000000000000000000001000 W
b00000000000000000000000000000000000000000000000000000000000000000000000000000000000000000000000000000000000000000000000000001000 X
b00000000000000000000000000000000000000000000000000000000000000000000000000000000000000000000000000000000000000000000000000001000 Y
b00000000000000000000000000000000000000000000000000000000000000000000000000000000000000000000000000000000000000000000000000001000 Z
b00000000000000000000000000000000000000000000000000000000000000000000000000000000000000000000000000000000000000000000000000001000 [
b00000000000000000000000000000000000000000000000000000000000000000000000000000000000000000000000000000000000000000000000000001000 \
b00000000000000000000000000000000000000000000000000000000000000000000000000000000000000000000000000000000000000000000000000001000 ]
b00000000000000000000000000000000000000000000000000000000000000000000000000000000000000000000000000000000000000000000000000001000 ^
b00000000000000000000000000000000000000000000000000000000000000000000000000000000000000000000000000000000000000000000000000000001 _
b00000000000000000000000000000000000000000000000000000000000000000000000000000000000000000000000000000000000000000000000000000001 `
b00000000000000000000000000000000000000000000000000000000000000000000000000000000000000000000000000000000000000000000000000000001 a
b00000000000000000000000000000000000000000000000000000000000000000000000000000000000000000000000000000000000000000000000000000001 b
b00000000000000000000000000000000000000000000000000000000000000000000000000000000000000000000000000000000000000000000000000000001 c
b00000000000000000000000000000000000000000000000000000000000000000000000000000000000000000000000000000000000000000000000000000001 d
b00000000000000000000000000000000000000000000000000000000000000000000000000000000000000000000000000000000000000000000000000000001 e
b00000000000000000000000000000000000000000000000000000000000000000000000000000000000000000000000000000000000000000000000000000001 f
b00000000000000000000000000000000000000000000000000000000000000000000000000000000000000000000000000000000000000000000000000000001 g
#60000000
0!
07
#65000000
1!
b1 -
b1 .
b1 /
b1 0
b1 1
b1 2
b1 3
b1 4
b1 5
17
b1 C
b1 D
b1 E
b1 F
b1 G
b1 H
b1 I
b1 J
b1 K
b00000000000000000000000000000000000000000000000000000000000000000000000000000000000000000000000000000000000000000000000110111100 _
b00000000000000000000000000000000000000000000000000000000000000000000000000000000000000000000000000000000000000000000000000000000 `
b00000000000000000000000000000000000000000000000000000000000000000000000000000000000000000000000000000000000000000000000000000000 a
b00000000000000000000000000000000000000000000000000000000000000000000000000000000000000000000000000000000000000000000000000000000 b
b00000000000000000000000000000000000000000000000000000000000000000000000000000000000000000000000000000000000000000000000110111100 c
b00000000000000000000000000000000000000000000000000000000000000000000000000000000000000000000000000000000000000000000000000000000 d
b00000000000000000000000000000000000000000000000000000000000000000000000000000000000000000000000000000000000000000000000000000000 e
b00000000000000000000000000000000000000000000000000000000000000000000000000000000000000000000000000000000000000000000000000000000 f
b00000000000000000000000000000000000000000000000000000000000000000000000000000000000000000000000000000000000000000000000110111100 g
#70000000
0!
07
#75000000
1!
b110111100 -
b0 .
b0 /
b0 0
b110111100 1
b0 2
b0 3
b0 4
b110111100 5
17
b110111100 C
b0 D
b0 E
b0 F
b110111100 G
b0 H
b0 I
b0 J
b110111100 K
