src/p4_state_space_3th_system/lib/math/3x3/matrix_vector_product_3x3.component.vhd
library IEEE;
use IEEE.STD_LOGIC_1164.ALL;
use IEEE.NUMERIC_STD.ALL;

entity MatrixVectorProduct_3x3 is
    Port (
        clk  : in  std_logic; -- Clock input
        rst  : in  std_logic; -- Reset input

        M11  : in  integer;   -- Input matrix A element (1,1)
        M12  : in  integer;   -- Input matrix A element (1,2)
        M13  : in  integer;   -- Input matrix A element (1,2)
        M21  : in  integer;   -- Input matrix A element (2,1)
        M22  : in  integer;   -- Input matrix A element (2,2)
        M23  : in  integer;   -- Input matrix A element (2,2)
        M31  : in  integer;   -- Input matrix A element (2,2)
        M32  : in  integer;   -- Input matrix A element (2,2)
        M33  : in  integer;   -- Input matrix A element (2,2)

        x1   : in  integer;   -- Input vector x element (1)
        x2   : in  integer;   -- Input vector x element (2)
        x3   : in  integer;   -- Input vector x element (2)

        y1   : out integer;   -- Output vector y element (1)
        y2   : out integer;   -- Output vector y element (1)
        y3   : out integer    -- Output vector y element (2)
    );
end entity MatrixVectorProduct_3x3;

architecture Behavioral_MatrixVectorProduct_3x3 of MatrixVectorProduct_3x3 is
begin
    process(clk, rst)
    begin
        if rst = '1' then
            y1 <= 0;
            y2 <= 0;
            y3 <= 0;
        elsif rising_edge(clk) then
            -- Perform matrix-vector multiplication
            y1 <= M11 * x1 + M12 * x2 + M13 * x3;
            y2 <= M21 * x1 + M22 * x2 + M23 * x3;
            y3 <= M31 * x1 + M32 * x2 + M33 * x3;
        end if;
    end process;
end Behavioral_MatrixVectorProduct_3x3;

src/p4_state_space_3th_system/lib/math/3x3/matrix_vector_product_3x3.testbench.vhd
library IEEE;
use IEEE.STD_LOGIC_1164.ALL;
use IEEE.NUMERIC_STD.ALL;

entity MatrixVectorProduct_3x3_Testbench is
end entity MatrixVectorProduct_3x3_Testbench;

architecture testbench of MatrixVectorProduct_3x3_Testbench is
    -- Constants for simulation parameters
    constant CLOCK_PERIOD : time := 10 ns;  -- Clock period (10 ns)

    -- Component declaration
    component MatrixVectorProduct_3x3
        Port (
            clk  : in  std_logic; -- Clock input
            rst  : in  std_logic; -- Reset input

            M11  : in  integer;   -- Input matrix A element (1,1)
            M12  : in  integer;   -- Input matrix A element (1,2)
            M13  : in  integer;   -- Input matrix A element (1,2)
            M21  : in  integer;   -- Input matrix A element (2,1)
            M22  : in  integer;   -- Input matrix A element (2,2)
            M23  : in  integer;   -- Input matrix A element (2,2)
            M31  : in  integer;   -- Input matrix A element (2,2)
            M32  : in  integer;   -- Input matrix A element (2,2)
            M33  : in  integer;   -- Input matrix A element (2,2)

            x1   : in  integer;   -- Input vector x element (1)
            x2   : in  integer;   -- Input vector x element (2)
            x3   : in  integer;   -- Input vector x element (2)

            y1   : out integer;   -- Output vector y element (1)
            y2   : out integer;   -- Output vector y element (1)
            y3   : out integer    -- Output vector y element (2)
        );
    end component;

    -- Signals declaration
    signal clk : std_logic := '0';     -- Clock signal
    signal rst : std_logic := '1';     -- Reset signal
    signal M11, M12, M13, M21, M22, M23, M31, M32, M33 : integer := 0;  -- Matrix elements
    signal x1, x2, x3 : integer := 0;              -- Vector elements
    signal y1, y2, y3 : integer := 0;              -- Output vector elements

begin

    -- Instantiate the MatrixVectorProduct_3x3 module
    dut : MatrixVectorProduct_3x3
        port map (
            clk => clk,
            rst => rst,
            M11 => M11,
            M12 => M12,
            M13 => M13,
            M21 => M21,
            M22 => M22,
            M23 => M23,
            M31 => M31,
            M32 => M32,
            M33 => M33,
            x1  => x1,
            x2  => x2,
            x3  => x3,
            y1  => y1,
            y2  => y2,
            y3  => y3
        );

    -- Clock process
    clk_process: process
    begin
        while now < 1000 ns loop  -- Run for 100 ns
            clk <= '0';
            wait for CLOCK_PERIOD / 2;
            clk <= '1';
            wait for CLOCK_PERIOD / 2;
        end loop;
        wait;
    end process clk_process;

    -- Stimulus process
    stimulus: process
    begin
        -- Reset
        rst <= '1';
        wait for 20 ns;
        rst <= '0';

       -- Test Case 1
        -- Identity Matrix (M = I), x = [1, 0, 0]
        wait for 10 ns;
        M11 <= 1; M12 <= 0; M13 <= 0;
        M21 <= 0; M22 <= 1; M23 <= 0;
        M31 <= 0; M32 <= 0; M33 <= 1;
        x1 <= 1; x2 <= 0; x3 <= 0;
        wait for 10 ns;
        assert y1 = 1 and y2 = 0 and y3 = 0
            report "Test Case 1 Failed: Identity Matrix, x = [1, 0, 0]"
            severity error;

        -- Test Case 2
        -- Arbitrary Matrix, x = [0, 1, 0]
        wait for 10 ns;
        M11 <= 1; M12 <= 2; M13 <= 3;
        M21 <= 4; M22 <= 5; M23 <= 6;
        M31 <= 7; M32 <= 8; M33 <= 9;
        x1 <= 0; x2 <= 1; x3 <= 0;
        wait for 10 ns;
        assert y1 = 2 and y2 = 5 and y3 = 8
            report "Test Case 2 Failed: Arbitrary Matrix, x = [0, 1, 0]"
            severity error;

        -- Test Case 3
        -- Zero Result Case
        wait for 10 ns;
        M11 <= 1; M12 <= 2; M13 <= 3;
        M21 <= 4; M22 <= 5; M23 <= 6;
        M31 <= 7; M32 <= 8; M33 <= 9;
        x1 <= 1; x2 <= 1; x3 <= 1;  -- Non-zero vector
        wait for 10 ns;
        assert y1 = 6 and y2 = 15 and y3 = 24
            report "Test Case 3 Failed: Non-zero vector and matrix, but zero result"
            severity error;

        -- Test Case 4
        -- Zero Result Case
        wait for 10 ns;
        M11 <= 1; M12 <= 1; M13 <= 1;
        M21 <= 1; M22 <= 1; M23 <= 1;
        M31 <= 1; M32 <= 1; M33 <= 1;
        x1 <= 1; x2 <= -2; x3 <= 1;  -- Non-zero vector
        wait for 10 ns;
        assert y1 = 0 and y2 = 0 and y3 = 0
            report "Test Case 4 Failed: Non-zero vector and matrix, but zero result"
            severity error;
        -- End the simulation
        wait;
    end process stimulus;

end architecture testbench;

src/p4_state_space_3th_system/test/waves/MatrixVectorProduct_3x3_Testbench_wave.vcd
$date
  Wed May 29 21:47:25 2024
$end
$version
  GHDL v0
$end
$timescale
  1 fs
$end
$scope module standard $end
$upscope $end
$scope module std_logic_1164 $end
$upscope $end
$scope module numeric_std $end
$upscope $end
$scope module matrixvectorproduct_3x3_testbench $end
$var reg 1 ! clk $end
$var reg 1 " rst $end
$var integer 32 # m11 $end
$var integer 32 $ m12 $end
$var integer 32 % m13 $end
$var integer 32 & m21 $end
$var integer 32 ' m22 $end
$var integer 32 ( m23 $end
$var integer 32 ) m31 $end
$var integer 32 * m32 $end
$var integer 32 + m33 $end
$var integer 32 , x1 $end
$var integer 32 - x2 $end
$var integer 32 . x3 $end
$var integer 32 / y1 $end
$var integer 32 0 y2 $end
$var integer 32 1 y3 $end
$scope module dut $end
$var reg 1 2 clk $end
$var reg 1 3 rst $end
$var integer 32 4 m11 $end
$var integer 32 5 m12 $end
$var integer 32 6 m13 $end
$var integer 32 7 m21 $end
$var integer 32 8 m22 $end
$var integer 32 9 m23 $end
$var integer 32 : m31 $end
$var integer 32 ; m32 $end
$var integer 32 < m33 $end
$var integer 32 = x1 $end
$var integer 32 > x2 $end
$var integer 32 ? x3 $end
$var integer 32 @ y1 $end
$var integer 32 A y2 $end
$var integer 32 B y3 $end
$upscope $end
$upscope $end
$enddefinitions $end
#0
0!
1"
b0 #
b0 $
b0 %
b0 &
b0 '
b0 (
b0 )
b0 *
b0 +
b0 ,
b0 -
b0 .
b0 /
b0 0
b0 1
02
13
b0 4
b0 5
b0 6
b0 7
b0 8
b0 9
b0 :
b0 ;
b0 <
b0 =
b0 >
b0 ?
b0 @
b0 A
b0 B
#5000000
1!
12
#10000000
0!
02
#15000000
1!
12
#20000000
0!
0"
02
03
#25000000
1!
12
#30000000
0!
b1 #
b1 '
b1 +
b1 ,
02
b1 4
b1 8
b1 <
b1 =
#35000000
1!
b1 /
12
b1 @
#40000000
0!
02
#45000000
1!
12
#50000000
0!
b10 $
b11 %
b100 &
b101 '
b110 (
b111 )
b1000 *
b1001 +
b0 ,
b1 -
02
b10 5
b11 6
b100 7
b101 8
b110 9
b111 :
b1000 ;
b1001 <
b0 =
b1 >
#55000000
1!
b10 /
b101 0
b1000 1
12
b10 @
b101 A
b1000 B
#60000000
0!
02
#65000000
1!
12
#70000000
0!
b1 ,
b1 .
02
b1 =
b1 ?
#75000000
1!
b110 /
b1111 0
b11000 1
12
b110 @
b1111 A
b11000 B
#80000000
0!
02
#85000000
1!
12
#90000000
0!
b1 $
b1 %
b1 &
b1 '
b1 (
b1 )
b1 *
b1 +
b11111111111111111111111111111110 -
02
b1 5
b1 6
b1 7
b1 8
b1 9
b1 :
b1 ;
b1 <
b11111111111111111111111111111110 >
#95000000
1!
b0 /
b0 0
b0 1
12
b0 @
b0 A
b0 B
