src/p4_state_space_3th_system/lib/math/3x3/matrix_inverse_3x3.component.vhd
library IEEE;
use IEEE.STD_LOGIC_1164.ALL;
use IEEE.NUMERIC_STD.ALL;

entity Matrix_Inverse_3x3 is
    Port (
        clk   : in  std_logic;
        reset : in  std_logic;
        A11, A12, A13 : in  integer;
        A21, A22, A23 : in  integer;
        A31, A32, A33 : in  integer;
        C11, C12, C13 : out integer;
        C21, C22, C23 : out integer;
        C31, C32, C33 : out integer;
        valid         : out std_logic
    );
end entity Matrix_Inverse_3x3;

architecture Matrix_Inverse_3x3_RTL of Matrix_Inverse_3x3 is
    signal determinant_factor_1 : integer;
    signal determinant_factor_2 : integer;
    signal determinant_factor_3 : integer;
    signal determinant : integer;
begin
    process (clk, reset)
    begin
        if reset = '1' then
            -- Reset all output signals and internal signals
            C11 <= 0;
            C12 <= 0;
            C13 <= 0;
            C21 <= 0;
            C22 <= 0;
            C23 <= 0;
            C31 <= 0;
            C32 <= 0;
            C33 <= 0;
            valid <= '0';
            determinant_factor_1 <= 0;
            determinant_factor_2 <= 0;
            determinant_factor_3 <= 0;
            determinant <= 0;
        elsif rising_edge(clk) then
            -- Calculate the determinant of the 3x3 matrix
            determinant_factor_1 <= A11 * (A22 * A33 - A23 * A32);
            determinant_factor_2 <= A12 * (A21 * A33 - A23 * A31);
            determinant_factor_3 <= A13 * (A21 * A32 - A22 * A31);
            determinant <= A11 * (A22 * A33 - A23 * A32) - A12 * (A21 * A33 - A23 * A31) + A13 * (A21 * A32 - A22 * A31);

            if determinant = 0 then
                -- If determinant is zero, inverse does not exist
                C11 <= 0;
                C12 <= 0;
                C13 <= 0;
                C21 <= 0;
                C22 <= 0;
                C23 <= 0;
                C31 <= 0;
                C32 <= 0;
                C33 <= 0;
                valid <= '0'; -- Inverse is not valid
            else
                -- Calculate the inverse matrix elements
                C11 <= determinant;-- (A22 * A33 - A23 * A32) / determinant;
                C12 <= (A22 * A33 - A23 * A32); --(A13 * A32 - A12 * A33) / determinant;
                C13 <= (A22 * A33 - A23 * A32) / determinant; --(A12 * A23 - A13 * A22) / determinant;

                C21 <= (A23 * A31 - A21 * A33) / determinant;
                C22 <= (A11 * A33 - A13 * A31) / determinant;
                C23 <= (A13 * A21 - A11 * A23) / determinant;

                C31 <= (A21 * A32 - A22 * A31) / determinant;
                C32 <= (A12 * A31 - A11 * A32) / determinant;
                C33 <= (A11 * A22 - A12 * A21) / determinant;

                valid <= '1'; -- Inverse is valid
            end if;
        end if;
    end process;
end architecture Matrix_Inverse_3x3_RTL;

src/p4_state_space_3th_system/lib/math/3x3/matrix_inverse_3x3.testbench.vhd
library IEEE;
use IEEE.STD_LOGIC_1164.ALL;
use IEEE.NUMERIC_STD.ALL;

entity Matrix_Inverse_3x3_Testbench is
end entity Matrix_Inverse_3x3_Testbench;

architecture testbench of Matrix_Inverse_3x3_Testbench is

    -- Component declaration
    component Matrix_Inverse_3x3
        Port (
            clk   : in  std_logic;
            reset : in  std_logic;
            A11, A12, A13 : in integer;
            A21, A22, A23 : in integer;
            A31, A32, A33 : in integer;
            C11, C12, C13 : out integer;
            C21, C22, C23 : out integer;
            C31, C32, C33 : out integer;
            valid         : out std_logic
        );
    end component;

    -- Signals declaration
    signal clk, reset                          : std_logic := '0';  -- Clock and reset signals
    signal A11, A12, A13, A21, A22, A23, A31, A32, A33 : integer := 0;  -- Matrix A elements
    signal C11, C12, C13, C21, C22, C23, C31, C32, C33 : integer := 0;  -- Output matrix elements
    signal valid                                       : std_logic := '0'; -- Valid signal

    signal alpha                                       : integer := 1;  -- Scaling factor

    -- Clock generation
    constant clk_period : time := 10 ns;

begin

    -- Clock process definition
    clk_process : process
    begin
        while now < 500 ns loop
            clk <= '0';
            wait for clk_period / 2;
            clk <= '1';
            wait for clk_period / 2;
        end loop;
    end process clk_process;


    -- Instantiate the Matrix_Inverse_3x3 module
    dut : Matrix_Inverse_3x3
        port map (
            clk => clk,
            reset => reset,
            A11 => A11, A12 => A12, A13 => A13,
            A21 => A21, A22 => A22, A23 => A23,
            A31 => A31, A32 => A32, A33 => A33,
            C11 => C11, C12 => C12, C13 => C13,
            C21 => C21, C22 => C22, C23 => C23,
            C31 => C31, C32 => C32, C33 => C33,
            valid => valid
        );

    -- Stimulus process
    stimulus: process
    begin
        -- Initialize reset
        reset <= '1';
        wait for 20 ns;
        reset <= '0';

        -- Test Case 1: Identity Matrix (should result in Identity Matrix)
        alpha <= 100;
        wait for 10 ns;
        A11 <= 1 * alpha; A12 <= 0 * alpha; A13 <= 0 * alpha;
        A21 <= 0 * alpha; A22 <= 1 * alpha; A23 <= 0 * alpha;
        A31 <= 0 * alpha; A32 <= 0 * alpha; A33 <= 1 * alpha;

        wait for 30 ns;
        assert C11 = 1 * alpha and C12 = 0 * alpha and C13 = 0 * alpha and
               C21 = 0 * alpha and C22 = 1 * alpha and C23 = 0 * alpha and
               C31 = 0 * alpha and C32 = 0 * alpha and C33 = 1 * alpha and
               valid = '1'
            report "Test Case 1 Failed: Identity Matrix. Expected (1,0,0; 0,1,0; 0,0,1, valid=1), Got (" & 
               integer'image(C11) & "," & integer'image(C12) & "," & integer'image(C13) & "; " &
               integer'image(C21) & "," & integer'image(C22) & "," & integer'image(C23) & "; " &
               integer'image(C31) & "," & integer'image(C32) & "," & integer'image(C33) & ", valid=" & std_logic'image(valid) & ")"
            severity error;

        -- Test Case 2: Arbitrary invertible matrix
        alpha <= 1;
        wait for 10 ns;
        A11 <=  2 * alpha; A12 <= -1 * alpha; A13 <=  0 * alpha;
        A21 <= -1 * alpha; A22 <=  2 * alpha; A23 <= -1 * alpha;
        A31 <=  0 * alpha; A32 <= -1 * alpha; A33 <=  2 * alpha;

        wait for 30 ns;

        assert C11 = 2 * alpha and C12 = 1 * alpha and C13 = 0 * alpha and
               C21 = 1 * alpha and C22 = 2 * alpha and C23 = 1 * alpha and
               C31 = 0 * alpha and C32 = 1 * alpha and C33 = 2 * alpha and
               valid = '1'
            report "Test Case 2 Failed: Arbitrary invertible matrix. Expected (2,1,0; 1,2,1; 0,1,2, valid=1), Got (" & 
                integer'image(C11) & "," & integer'image(C12) & "," & integer'image(C13) & "; " &
                integer'image(C21) & "," & integer'image(C22) & "," & integer'image(C23) & "; " &
                integer'image(C31) & "," & integer'image(C32) & "," & integer'image(C33) & ", valid=" & std_logic'image(valid) & ")"
            severity error;

        -- Test Case 3: Non-invertible matrix (determinant = 0)
        wait for 10 ns;
        A11 <= 1; A12 <= 2; A13 <= 3;
        A21 <= 4; A22 <= 5; A23 <= 6;
        A31 <= 7; A32 <= 8; A33 <= 9;

        wait for 30 ns;

        assert C11 = 0 and C12 = 0 and C13 = 0 and
               C21 = 0 and C22 = 0 and C23 = 0 and
               C31 = 0 and C32 = 0 and C33 = 0 and
               valid = '0'
            report "Test Case 3 Failed: Non-invertible matrix. Expected (0,0,0; 0,0,0; 0,0,0, valid=0), Got (" & 
                integer'image(C11) & "," & integer'image(C12) & "," & integer'image(C13) & "; " &
                integer'image(C21) & "," & integer'image(C22) & "," & integer'image(C23) & "; " &
                integer'image(C31) & "," & integer'image(C32) & "," & integer'image(C33) & ", valid=" & std_logic'image(valid) & ")"
            severity error;

        -- Test Case 4: Invertible matrix
        wait for 10 ns;
        A11 <= 4; A12 <= 7; A13 <= 2;
        A21 <= 3; A22 <= 6; A23 <= 1;
        A31 <= 2; A32 <= 5; A33 <= 1;

        wait for 30 ns;

        assert C11 = -1 and C12 = 1 and C13 = 0 and
               C21 = 2 and C22 = -2 and C23 = 1 and
               C31 = 1 and C32 = -1 and C33 = 0 and
               valid = '1'
            report "Test Case 4 Failed: Invertible matrix. Expected (-1,1,0; 2,-2,1; 1,-1,0, valid=1), Got (" & 
                integer'image(C11) & "," & integer'image(C12) & "," & integer'image(C13) & "; " &
                integer'image(C21) & "," & integer'image(C22) & "," & integer'image(C23) & "; " &
                integer'image(C31) & "," & integer'image(C32) & "," & integer'image(C33) & ", valid=" & std_logic'image(valid) & ")"
            severity error;

        -- End the simulation
        wait;
    end process stimulus;

end architecture testbench;

src/p4_state_space_3th_system/test/waves/Matrix_Inverse_3x3_Testbench_wave.vcd
$date
  Fri May 31 00:20:23 2024
$end
$version
  GHDL v0
$end
$timescale
  1 fs
$end
$scope module standard $end
$upscope $end
$scope module std_logic_1164 $end
$upscope $end
$scope module numeric_std $end
$upscope $end
$scope module matrix_inverse_3x3_testbench $end
$var reg 1 ! clk $end
$var reg 1 " reset $end
$var integer 32 # a11 $end
$var integer 32 $ a12 $end
$var integer 32 % a13 $end
$var integer 32 & a21 $end
$var integer 32 ' a22 $end
$var integer 32 ( a23 $end
$var integer 32 ) a31 $end
$var integer 32 * a32 $end
$var integer 32 + a33 $end
$var integer 32 , c11 $end
$var integer 32 - c12 $end
$var integer 32 . c13 $end
$var integer 32 / c21 $end
$var integer 32 0 c22 $end
$var integer 32 1 c23 $end
$var integer 32 2 c31 $end
$var integer 32 3 c32 $end
$var integer 32 4 c33 $end
$var reg 1 5 valid $end
$var integer 32 6 alpha $end
$scope module dut $end
$var reg 1 7 clk $end
$var reg 1 8 reset $end
$var integer 32 9 a11 $end
$var integer 32 : a12 $end
$var integer 32 ; a13 $end
$var integer 32 < a21 $end
$var integer 32 = a22 $end
$var integer 32 > a23 $end
$var integer 32 ? a31 $end
$var integer 32 @ a32 $end
$var integer 32 A a33 $end
$var integer 32 B c11 $end
$var integer 32 C c12 $end
$var integer 32 D c13 $end
$var integer 32 E c21 $end
$var integer 32 F c22 $end
$var integer 32 G c23 $end
$var integer 32 H c31 $end
$var integer 32 I c32 $end
$var integer 32 J c33 $end
$var reg 1 K valid $end
$var integer 32 L determinant_factor_1 $end
$var integer 32 M determinant_factor_2 $end
$var integer 32 N determinant_factor_3 $end
$var integer 32 O determinant $end
$upscope $end
$upscope $end
$enddefinitions $end
#0
0!
1"
b0 #
b0 $
b0 %
b0 &
b0 '
b0 (
b0 )
b0 *
b0 +
b0 ,
b0 -
b0 .
b0 /
b0 0
b0 1
b0 2
b0 3
b0 4
05
b1 6
07
18
b0 9
b0 :
b0 ;
b0 <
b0 =
b0 >
b0 ?
b0 @
b0 A
b0 B
b0 C
b0 D
b0 E
b0 F
b0 G
b0 H
b0 I
b0 J
0K
b0 L
b0 M
b0 N
b0 O
#5000000
1!
17
#10000000
0!
07
#15000000
1!
17
#20000000
0!
0"
b1100100 6
07
08
#25000000
1!
17
#30000000
0!
b1100100 #
b1100100 '
b1100100 +
07
b1100100 9
b1100100 =
b1100100 A
#35000000
1!
17
b11110100001001000000 L
b11110100001001000000 O
#40000000
0!
07
#45000000
1!
b11110100001001000000 ,
b10011100010000 -
15
17
b11110100001001000000 B
b10011100010000 C
1K
#50000000
0!
07
#55000000
1!
17
#60000000
0!
b1 6
07
#65000000
1!
17
#70000000
0!
b10 #
b11111111111111111111111111111111 $
b11111111111111111111111111111111 &
b10 '
b11111111111111111111111111111111 (
b11111111111111111111111111111111 *
b10 +
07
b10 9
b11111111111111111111111111111111 :
b11111111111111111111111111111111 <
b10 =
b11111111111111111111111111111111 >
b11111111111111111111111111111111 @
b10 A
#75000000
1!
b11 -
17
b11 C
b110 L
b10 M
b100 O
#80000000
0!
07
#85000000
1!
b100 ,
b1 0
17
b100 B
b1 F
#90000000
0!
07
#95000000
1!
17
#100000000
0!
07
#105000000
1!
17
#110000000
0!
b1 #
b10 $
b11 %
b100 &
b101 '
b110 (
b111 )
b1000 *
b1001 +
07
b1 9
b10 :
b11 ;
b100 <
b101 =
b110 >
b111 ?
b1000 @
b1001 A
#115000000
1!
b11111111111111111111111111111101 -
b1 /
b11111111111111111111111111111101 0
b1 1
b1 3
17
b11111111111111111111111111111101 C
b1 E
b11111111111111111111111111111101 F
b1 G
b1 I
b11111111111111111111111111111101 L
b11111111111111111111111111110100 M
b11111111111111111111111111110111 N
b0 O
#120000000
0!
07
#125000000
1!
b0 ,
b0 -
b0 /
b0 0
b0 1
b0 3
05
17
b0 B
b0 C
b0 E
b0 F
b0 G
b0 I
0K
#130000000
0!
07
#135000000
1!
17
#140000000
0!
07
#145000000
1!
17
#150000000
0!
b100 #
b111 $
b10 %
b11 &
b110 '
b1 (
b10 )
b101 *
b1 +
07
b100 9
b111 :
b10 ;
b11 <
b110 =
b1 >
b10 ?
b101 @
b1 A
#155000000
1!
17
b100 L
b111 M
b110 N
b11 O
#160000000
0!
07
#165000000
1!
b11 ,
b1 -
b1 2
b11111111111111111111111111111110 3
b1 4
15
17
b11 B
b1 C
b1 H
b11111111111111111111111111111110 I
b1 J
1K
#170000000
0!
07
#175000000
1!
17
#180000000
0!
07
#185000000
1!
17
#190000000
0!
07
#195000000
1!
17
#200000000
0!
07
#205000000
1!
17
#210000000
0!
07
#215000000
1!
17
#220000000
0!
07
#225000000
1!
17
#230000000
0!
07
#235000000
1!
17
#240000000
0!
07
#245000000
1!
17
#250000000
0!
07
#255000000
1!
17
#260000000
0!
07
#265000000
1!
17
#