src/p4_state_space_3th_system/lib/math/3x3/vector_integrator_3x1.component.vhd
library IEEE;
use IEEE.STD_LOGIC_1164.ALL;
use IEEE.NUMERIC_STD.ALL;

entity Vector_Integrator_3x1 is
    Port (
        clk : in std_logic;    -- Clock input
        rst : in std_logic;    -- Reset input
        x1  : in integer;      -- Input vector x element (1)
        x2  : in integer;      -- Input vector x element (2)
        x3  : in integer;      -- Input vector x element (3)
        int_x1 : out integer;  -- Output integral of x element (1)
        int_x2 : out integer;  -- Output integral of x element (2)
        int_x3 : out integer   -- Output integral of x element (3)
    );
end entity Vector_Integrator_3x1;

architecture Behavioral_Vector_Integrator_3x1 of Vector_Integrator_3x1 is
    signal sum_x1 : integer := 0;  -- Accumulated sum for x element (1)
    signal sum_x2 : integer := 0;  -- Accumulated sum for x element (2)
    signal sum_x3 : integer := 0;  -- Accumulated sum for x element (3)

    constant DT_TOP : integer := 1;
    constant DT_BOTTOM : integer := 100;

    constant MAX_VALUE : integer := 1000000; -- Define maximum saturation value
    constant MIN_VALUE : integer := -1000000; -- Define minimum saturation value

begin
    process(clk, rst)
    begin
        if rst = '1' then
            sum_x1 <= 0;
            sum_x2 <= 0;
            sum_x3 <= 0;
            int_x1 <= 0;
            int_x2 <= 0;
            int_x3 <= 0;
        elsif rising_edge(clk) then
            -- Perform integration (accumulation)
            sum_x1 <= sum_x1 + DT_TOP * (x1 / DT_BOTTOM);
            sum_x2 <= sum_x2 + DT_TOP * (x2 / DT_BOTTOM);
            sum_x3 <= sum_x3 + DT_TOP * (x3 / DT_BOTTOM);

            -- Apply saturation for x1
            if sum_x1 > MAX_VALUE then
                int_x1 <= MAX_VALUE;
            elsif sum_x1 < MIN_VALUE then
                int_x1 <= MIN_VALUE;
            else
                int_x1 <= sum_x1;
            end if;

            -- Apply saturation for x2
            if sum_x2 > MAX_VALUE then
                int_x2 <= MAX_VALUE;
            elsif sum_x2 < MIN_VALUE then
                int_x2 <= MIN_VALUE;
            else
                int_x2 <= sum_x2;
            end if;

            -- Apply saturation for x3
            if sum_x3 > MAX_VALUE then
                int_x3 <= MAX_VALUE;
            elsif sum_x3 < MIN_VALUE then
                int_x3 <= MIN_VALUE;
            else
                int_x3 <= sum_x3;
            end if;
        end if;
    end process;
end Behavioral_Vector_Integrator_3x1;

src/p4_state_space_3th_system/lib/math/3x3_nbits/vector_integrator_3x1.testbench.vhd
library IEEE;
use IEEE.STD_LOGIC_1164.ALL;
use IEEE.NUMERIC_STD.ALL;

entity Vector_Integrator_3x1_Testbench is
end entity Vector_Integrator_3x1_Testbench;


architecture testbench of Vector_Integrator_3x1_Testbench is
    -- Constants for simulation parameters
    constant CLOCK_PERIOD : time := 10 ns;  -- Clock period (10 ns)

    -- ANSI escape codes for colors
    constant ANSI_RESET : string := "\033[0m";
    constant ANSI_RED : string := "\033[31;1;4m";
    constant ANSI_GREEN : string := "\033[32;1;4m";
    constant ANSI_YELLOW : string := "\033[33m";
    constant ANSI_BLUE : string := "\033[34m";
    constant ANSI_MAGENTA : string := "\033[35m";
    constant ANSI_CYAN : string := "\033[36m";

    -- Component declaration
    component Vector_Integrator_3x1 is
        Port (
            clk : in std_logic;    -- Clock input
            rst : in std_logic;    -- Reset input
            x1  : in integer;      -- Input vector x element (1)
            x2  : in integer;      -- Input vector x element (2)
            x3  : in integer;      -- Input vector x element (3)
            int_x1 : out integer;  -- Output integral of x element (1)
            int_x2 : out integer;  -- Output integral of x element (2)
            int_x3 : out integer   -- Output integral of x element (3)
        );
    end component;

    -- Signals declaration
    signal clk : std_logic := '0';                 -- Clock signal
    signal rst : std_logic := '1';                 -- Reset signal
    signal x1, x2, x3 : integer := 0;              -- Input vectors
    signal int_x1, int_x2, int_x3 : integer;       -- Output vectors

    -- Signals for unit tests
    signal utest1_pass : std_logic := '0';         -- Unit test passed flag
    signal all_tests_passed : boolean := true;     -- Overall test status flag

begin
    -- Instantiate the Vector_Integrator_3x1 module
    dut : Vector_Integrator_3x1
        port map (
            clk => clk,
            rst => rst,
            x1 => x1,
            x2 => x2,
            x3 => x3,
            int_x1 => int_x1,
            int_x2 => int_x2,
            int_x3 => int_x3
        );

    -- Clock process
    clk_process: process
    begin
        while now < 500 ns loop  -- Run for 200 ns
            clk <= '0';
            wait for CLOCK_PERIOD / 2;
            clk <= '1';
            wait for CLOCK_PERIOD / 2;
        end loop;
        wait;
    end process clk_process;

    -- Stimulus process
    stimulus: process
    begin
        report " ";
        wait for 20 ns;  -- Wait for initial signal stabilization

        rst <= '1';
        wait for 20 ns;

        -----------------------------------------------
        -- Test Case 1
        -- x = [1, 2, 3]
        -- Should accumulate over time
        -----------------------------------------------

        rst <= '0';
        x1 <= 1;
        x2 <= 2;
        x3 <= 3;
        wait for 60 ns;  -- Wait for 5 cycles 

        if (int_x1 = 5 and int_x2 = 10 and int_x3 = 15) then
            utest1_pass <= '1';
            report "[v/] Test case 1 passed";
        else
            utest1_pass <= '0';
            report "[X] Test case 1 failed: int_x1 = " & integer'image(int_x1) & ", int_x2 = " & integer'image(int_x2) & ", int_x3 = " & integer'image(int_x3);
            all_tests_passed <= false;
        end if;

        wait for 50 ns;

        -----------------------------------------------
        -- Test Case 2
        -- Reset and check reset functionality
        -----------------------------------------------
        rst <= '1';
        wait for 20 ns;

        rst <= '0';
        x1 <= 0;
        x2 <= 0;
        x3 <= 0;

        if (int_x1 = 0 and int_x2 = 0 and int_x3 = 0) then
            utest1_pass <= '1';
            report "[v/] Test case 2 passed";
        else
            utest1_pass <= '0';
            report "[X] Test case 2 failed: int_x1 = " & integer'image(int_x1) & ", int_x2 = " & integer'image(int_x2) & ", int_x3 = " & integer'image(int_x3);
            all_tests_passed <= false;
        end if;

        wait for 50 ns;

        -----------------------------------------------
        -- Test Case 3
        -- x = [1000, -1000, 0]
        -- Check for correct accumulation and saturation
        -----------------------------------------------
        x1 <= 1000;
        x2 <= -1000;
        x3 <= 0;
        wait for 60 ns;  -- Wait for signal propagation

        if (int_x1 = 5000 and int_x2 = -5000 and int_x3 = 0) then
            utest1_pass <= '1';
            report "[v/] Test case 3 passed";
        else
            utest1_pass <= '0';
            report "[X] Test case 3 failed: int_x1 = " & integer'image(int_x1) & ", int_x2 = " & integer'image(int_x2) & ", int_x3 = " & integer'image(int_x3);
            all_tests_passed <= false;
        end if;

        wait for 50 ns;

        -----------------------------------------------
        -- Final message indicating if all tests passed
        -----------------------------------------------
        if all_tests_passed then
            report " . . . . . . . .  [v/] All test cases passed!";
        else
            report " x x x x x x x x ";
            report "[X] Some test cases failed!";
        end if;

        wait;
    end process stimulus;

end architecture testbench;

src/p4_state_space_3th_system/test/waves/vector_integrator_3x1_Testbench_wave.vcd
$date
  Mon May 27 17:16:50 2024
$end
$version
  GHDL v0
$end
$timescale
  1 fs
$end
$scope module standard $end
$upscope $end
$scope module std_logic_1164 $end
$upscope $end
$scope module numeric_std $end
$upscope $end
$scope module vector_integrator_3x1_testbench $end
$var reg 1 ! clk $end
$var reg 1 " rst $end
$var integer 32 # x1 $end
$var integer 32 $ x2 $end
$var integer 32 % x3 $end
$var integer 32 & int_x1 $end
$var integer 32 ' int_x2 $end
$var integer 32 ( int_x3 $end
$var reg 1 ) utest1_pass $end
$var reg 1 * all_tests_passed $end
$scope module dut $end
$var reg 1 + clk $end
$var reg 1 , rst $end
$var integer 32 - x1 $end
$var integer 32 . x2 $end
$var integer 32 / x3 $end
$var integer 32 0 int_x1 $end
$var integer 32 1 int_x2 $end
$var integer 32 2 int_x3 $end
$var integer 32 3 sum_x1 $end
$var integer 32 4 sum_x2 $end
$var integer 32 5 sum_x3 $end
$upscope $end
$upscope $end
$enddefinitions $end
#0
0!
1"
b0 #
b0 $
b0 %
b0 &
b0 '
b0 (
0)
1*
0+
1,
b0 -
b0 .
b0 /
b0 0
b0 1
b0 2
b0 3
b0 4
b0 5
#5000000
1!
1+
#10000000
0!
0+
#15000000
1!
1+
#20000000
0!
0+
#25000000
1!
1+
#30000000
0!
0+
#35000000
1!
1+
#40000000
0!
0"
b1 #
b10 $
b11 %
0+
0,
b1 -
b10 .
b11 /
#45000000
1!
1+
b1 3
b10 4
b11 5
#50000000
0!
0+
#55000000
1!
b1 &
b10 '
b11 (
1+
b1 0
b10 1
b11 2
b10 3
b100 4
b110 5
#60000000
0!
0+
#65000000
1!
b10 &
b100 '
b110 (
1+
b10 0
b100 1
b110 2
b11 3
b110 4
b1001 5
#70000000
0!
0+
#75000000
1!
b11 &
b110 '
b1001 (
1+
b11 0
b110 1
b1001 2
b100 3
b1000 4
b1100 5
#80000000
0!
0+
#85000000
1!
b100 &
b1000 '
b1100 (
1+
b100 0
b1000 1
b1100 2
b101 3
b1010 4
b1111 5
#90000000
0!
0+
#95000000
1!
b101 &
b1010 '
b1111 (
1+
b101 0
b1010 1
b1111 2
b110 3
b1100 4
b10010 5
#100000000
0!
1)
0+
#105000000
1!
b110 &
b1100 '
b10010 (
1+
b110 0
b1100 1
b10010 2
b111 3
b1110 4
b10101 5
#110000000
0!
0+
#115000000
1!
b111 &
b1110 '
b10101 (
1+
b111 0
b1110 1
b10101 2
b1000 3
b10000 4
b11000 5
#120000000
0!
0+
#125000000
1!
b1000 &
b10000 '
b11000 (
1+
b1000 0
b10000 1
b11000 2
b1001 3
b10010 4
b11011 5
#130000000
0!
0+
#135000000
1!
b1001 &
b10010 '
b11011 (
1+
b1001 0
b10010 1
b11011 2
b1010 3
b10100 4
b11110 5
#140000000
0!
0+
#145000000
1!
b1010 &
b10100 '
b11110 (
1+
b1010 0
b10100 1
b11110 2
b1011 3
b10110 4
b100001 5
#150000000
0!
1"
b0 &
b0 '
b0 (
0+
1,
b0 0
b0 1
b0 2
b0 3
b0 4
b0 5
#155000000
1!
1+
#160000000
0!
0+
#165000000
1!
1+
#170000000
0!
0"
b0 #
b0 $
b0 %
0+
0,
b0 -
b0 .
b0 /
#175000000
1!
1+
#180000000
0!
0+
#185000000
1!
1+
#190000000
0!
0+
#195000000
1!
1+
#200000000
0!
0+
#205000000
1!
1+
#210000000
0!
0+
#215000000
1!
1+
#220000000
0!
b1111101000 #
b11111111111111111111110000011000 $
0+
b1111101000 -
b11111111111111111111110000011000 .
#225000000
1!
1+
b1111101000 3
b11111111111111111111110000011000 4
#230000000
0!
0+
#235000000
1!
b1111101000 &
b11111111111111111111110000011000 '
1+
b1111101000 0
b11111111111111111111110000011000 1
b11111010000 3
b11111111111111111111100000110000 4
#240000000
0!
0+
#245000000
1!
b11111010000 &
b11111111111111111111100000110000 '
1+
b11111010000 0
b11111111111111111111100000110000 1
b101110111000 3
b11111111111111111111010001001000 4
#250000000
0!
0+
#255000000
1!
b101110111000 &
b11111111111111111111010001001000 '
1+
b101110111000 0
b11111111111111111111010001001000 1
b111110100000 3
b11111111111111111111000001100000 4
#260000000
0!
0+
#265000000
1!
b111110100000 &
b11111111111111111111000001100000 '
1+
b111110100000 0
b11111111111111111111000001100000 1
b1001110001000 3
b11111111111111111110110001111000 4
#270000000
0!
0+
#275000000
1!
b1001110001000 &
b11111111111111111110110001111000 '
1+
b1001110001000 0
b11111111111111111110110001111000 1
b1011101110000 3
b11111111111111111110100010010000 4
#280000000
0!
0+
#285000000
1!
b1011101110000 &
b11111111111111111110100010010000 '
1+
b1011101110000 0
b11111111111111111110100010010000 1
b1101101011000 3
b11111111111111111110010010101000 4
#290000000
0!
0+
#295000000
1!
b1101101011000 &
b11111111111111111110010010101000 '
1+
b1101101011000 0
b11111111111111111110010010101000 1
b1111101000000 3
b11111111111111111110000011000000 4
#300000000
0!
0+
#305000000
1!
b1111101000000 &
b11111111111111111110000011000000 '
1+
b1111101000000 0
b11111111111111111110000011000000 1
b10001100101000 3
b11111111111111111101110011011000 4
#310000000
0!
0+
#315000000
1!
b10001100101000 &
b11111111111111111101110011011000 '
1+
b10001100101000 0
b11111111111111111101110011011000 1
b10011100010000 3
b11111111111111111101100011110000 4
#320000000
0!
0+
#325000000
1!
b10011100010000 &
b11111111111111111101100011110000 '
1+
b10011100010000 0
b11111111111111111101100011110000 1
b10101011111000 3
b11111111111111111101010100001000 4
#330000000
0!
0+
#335000000
1!
b10101011111000 &
b11111111111111111101010100001000 '
1+
b10101011111000 0
b11111111111111111101010100001000 1
b10111011100000 3
b11111111111111111101000100100000 4
#340000000
0!
0+
#345000000
1!
b10111011100000 &
b11111111111111111101000100100000 '
1+
b10111011100000 0
b11111111111111111101000100100000 1
b11001011001000 3
b11111111111111111100110100111000 4
#350000000
0!
0+
#355000000
1!
b11001011001000 &
b11111111111111111100110100111000 '
1+
b11001011001000 0
b11111111111111111100110100111000 1
b11011010110000 3
b11111111111111111100100101010000 4
#360000000
0!
0+
#365000000
1!
b11011010110000 &
b11111111111111111100100101010000 '
1+
b11011010110000 0
b11111111111111111100100101010000 1
b11101010011000 3
b11111111111111111100010101101000 4
#370000000
0!
0+
#375000000
1!
b11101010011000 &
b11111111111111111100010101101000 '
1+
b11101010011000 0
b11111111111111111100010101101000 1
b11111010000000 3
b11111111111111111100000110000000 4
#380000000
0!
0+
#385000000
1!
b11111010000000 &
b11111111111111111100000110000000 '
1+
b11111010000000 0
b11111111111111111100000110000000 1
b100001001101000 3
b11111111111111111011110110011000 4
#390000000
0!
0+
#395000000
1!
b100001001101000 &
b11111111111111111011110110011000 '
1+
b100001001101000 0
b11111111111111111011110110011000 1
b100011001010000 3
b11111111111111111011100110110000 4
#400000000
0!
0+
#405000000
1!
b100011001010000 &
b11111111111111111011100110110000 '
1+
b100011001010000 0
b11111111111111111011100110110000 1
b100101000111000 3
b11111111111111111011010111001000 4
#410000000
0!
0+
#415000000
1!
b100101000111000 &
b11111111111111111011010111001000 '
1+
b100101000111000 0
b11111111111111111011010111001000 1
b100111000100000 3
b11111111111111111011000111100000 4
#420000000
0!
0+
#425000000
1!
b100111000100000 &
b11111111111111111011000111100000 '
1+
b100111000100000 0
b11111111111111111011000111100000 1
b101001000001000 3
b11111111111111111010110111111000 4
#430000000
0!
0+
#435000000
1!
b101001000001000 &
b11111111111111111010110111111000 '
1+
b101001000001000 0
b11111111111111111010110111111000 1
b101010111110000 3
b11111111111111111010101000010000 4
#440000000
0!
0+
#445000000
1!
b101010111110000 &
b11111111111111111010101000010000 '
1+
b101010111110000 0
b11111111111111111010101000010000 1
b101100111011000 3
b11111111111111111010011000101000 4
#450000000
0!
0+
#455000000
1!
b101100111011000 &
b11111111111111111010011000101000 '
1+
b101100111011000 0
b11111111111111111010011000101000 1
b101110111000000 3
b11111111111111111010001001000000 4
#460000000
0!
0+
#465000000
1!
b101110111000000 &
b11111111111111111010001001000000 '
1+
b101110111000000 0
b11111111111111111010001001000000 1
b110000110101000 3
b11111111111111111001111001011000 4
#470000000
0!
0+
#475000000
1!
b110000110101000 &
b11111111111111111001111001011000 '
1+
b110000110101000 0
b11111111111111111001111001011000 1
b110010110010000 3
b11111111111111111001101001110000 4
#480000000
0!
0+
#485000000
1!
b110010110010000 &
b11111111111111111001101001110000 '
1+
b110010110010000 0
b11111111111111111001101001110000 1
b110100101111000 3
b11111111111111111001011010001000 4
#490000000
0!
0+
#495000000
1!
b110100101111000 &
b11111111111111111001011010001000 '
1+
b110100101111000 0
b11111111111111111001011010001000 1
b110110101100000 3
b11111111111111111001001010100000 4
