src/p4_state_space_3th_system/lib/math/3x3/vector_derivator_3x1.component.vhd
library IEEE;
use IEEE.STD_LOGIC_1164.ALL;
use IEEE.NUMERIC_STD.ALL;

entity Vector_Derivator_3x1 is
    Port (
        clk : in std_logic;    -- Clock input
        rst : in std_logic;    -- Reset input
        x1  : in integer;      -- Current input vector x element (1)
        x2  : in integer;      -- Current input vector x element (2)
        x3  : in integer;      -- Current input vector x element (3)
        dx1 : out integer;     -- Output derivative dx/dt element (1)
        dx2 : out integer;     -- Output derivative dx/dt element (2)
        dx3 : out integer      -- Output derivative dx/dt element (3)
    );
end entity Vector_Derivator_3x1;

architecture Behavioral_Vector_Derivator_3x1 of Vector_Derivator_3x1 is

    constant DT_TOP : integer := 1;
    constant DT_BOTTOM : integer := 1;

    signal prev_x1 : integer := 0;  -- Previous value of x element (1)
    signal prev_x2 : integer := 0;  -- Previous value of x element (2)
    signal prev_x3 : integer := 0;  -- Previous value of x element (3)

begin
    process(clk, rst)
    begin
        if rst = '1' then
            prev_x1 <= 0;
            prev_x2 <= 0;
            prev_x3 <= 0;
            dx1 <= 0;
            dx2 <= 0;
            dx3 <= 0;
        elsif rising_edge(clk) then
            -- Compute the derivative (difference between current and previous values)
            dx1 <= (x1 - prev_x1); --(x1 - prev_x1) * DT_TOP / DT_BOTTOM;
            dx2 <= (x2 - prev_x2);--(x2 - prev_x2) * DT_TOP / DT_BOTTOM;
            dx3 <= (x3 - prev_x3);--(x3 - prev_x3) * DT_TOP / DT_BOTTOM;
            -- Store the current values for the next clock cycle
            prev_x1 <= x1;
            prev_x2 <= x2;
            prev_x3 <= x3;
        end if;
    end process;
end Behavioral_Vector_Derivator_3x1;

src/p4_state_space_3th_system/lib/math/3x3_nbits/vector_derivator_3x1.testbench.vhd
library IEEE;
use IEEE.STD_LOGIC_1164.ALL;
use IEEE.NUMERIC_STD.ALL;

entity Vector_Derivator_3x1_Testbench is
end entity Vector_Derivator_3x1_Testbench;

architecture testbench of Vector_Derivator_3x1_Testbench is
    -- Constants for simulation parameters
    constant CLOCK_PERIOD : time := 10 ns;  -- Clock period (10 ns)

    -- ANSI escape codes for colors
    constant ANSI_RESET : string := "\033[0m";
    constant ANSI_RED : string := "\033[31;1;4m";
    constant ANSI_GREEN : string := "\033[32;1;4m";
    constant ANSI_YELLOW : string := "\033[33m";
    constant ANSI_BLUE : string := "\033[34m";
    constant ANSI_MAGENTA : string := "\033[35m";
    constant ANSI_CYAN : string := "\033[36m";

    -- Component declaration
    component Vector_Derivator_3x1 is
        Port (
            clk : in std_logic;    -- Clock input
            rst : in std_logic;    -- Reset input
            x1  : in integer;      -- Current input vector x element (1)
            x2  : in integer;      -- Current input vector x element (2)
            x3  : in integer;      -- Current input vector x element (3)
            dx1 : out integer;     -- Output derivative dx/dt element (1)
            dx2 : out integer;     -- Output derivative dx/dt element (2)
            dx3 : out integer      -- Output derivative dx/dt element (3)
        );
    end component;

    -- Signals declaration
    signal clk : std_logic := '0';                 -- Clock signal
    signal rst : std_logic := '1';                 -- Reset signal
    signal x1, x2, x3 : integer := 0;              -- Input vectors
    signal dx1, dx2, dx3 : integer;                -- Output vectors

    -- Signals for unit tests
    signal t : integer := 0;          -- Unit test t

    signal utest1_pass : std_logic := '0';         -- Unit test passed flag
    signal all_tests_passed : boolean := true;     -- Overall test status flag

begin
    -- Instantiate the Vector_Derivator_3x1 module
    dut : Vector_Derivator_3x1
        port map (
            clk => clk,
            rst => rst,
            x1 => x1,
            x2 => x2,
            x3 => x3,
            dx1 => dx1,
            dx2 => dx2,
            dx3 => dx3
        );

    -- Clock process
    clk_process: process
    begin
        while now < 200 ns loop  -- Run for 200 ns
            clk <= '0';
            wait for CLOCK_PERIOD / 2;
            clk <= '1';
            wait for CLOCK_PERIOD / 2;
        end loop;
        wait;
    end process clk_process;

    -- Stimulus process
    stimulus: process
    begin

        report " ";
        wait for 20 ns;  -- Wait for initial signal stabilization

        rst <= '1';
        wait for 20 ns;
     
        -----------------------------------------------
        -- Test Case 1
        -- x = [1, 2, 3]
        -- Should calculate derivatives correctly
        -----------------------------------------------
        rst <= '0';
        x1 <= 10;
        x2 <= 20;
        x3 <= 30;

        wait for 10 ns;  -- Wait for clock edge
        if (dx1 = 10 and dx2 = 20 and dx3 = 30) then
            utest1_pass <= '1';
            report "[v/] Test case 1 passed";
        else
            utest1_pass <= '0';
            report "[X] Test case 1 failed: dx1 = " & integer'image(dx1) & ", dx2 = " & integer'image(dx2) & ", dx3 = " & integer'image(dx3);
            all_tests_passed <= false;
        end if;

        wait for 50 ns;

        -----------------------------------------------
        -- Test Case 2
        -- Reset and check reset functionality
        -----------------------------------------------
        rst <= '1';
        wait for 20 ns;
        rst <= '0';
        wait for 20 ns;

        if (dx1 = 0 and dx2 = 0 and dx3 = 0) then
            utest1_pass <= '1';
            report "[v/] Test case 2 passed";
        else
            utest1_pass <= '0';
            report "[X] Test case 2 failed: dx1 = " & integer'image(dx1) & ", dx2 = " & integer'image(dx2) & ", dx3 = " & integer'image(dx3);
            all_tests_passed <= false;
        end if;

        wait for 50 ns;


        -----------------------------------------------
        -- Final message indicating if all tests passed
        -----------------------------------------------
        if all_tests_passed then
            report " . . . . . . . .  [v/] All test cases passed!";
        else
            report " x x x x x x x x ";
            report "[X] Some test cases failed!";
        end if;


        wait;
    end process stimulus;

end architecture testbench;

src/p4_state_space_3th_system/test/waves/vector_derivator_3x1_Testbench_wave.vcd
$date
  Mon May 27 16:35:57 2024
$end
$version
  GHDL v0
$end
$timescale
  1 fs
$end
$scope module standard $end
$upscope $end
$scope module std_logic_1164 $end
$upscope $end
$scope module numeric_std $end
$upscope $end
$scope module vector_derivator_3x1_testbench $end
$var reg 1 ! clk $end
$var reg 1 " rst $end
$var integer 32 # x1 $end
$var integer 32 $ x2 $end
$var integer 32 % x3 $end
$var integer 32 & dx1 $end
$var integer 32 ' dx2 $end
$var integer 32 ( dx3 $end
$var integer 32 ) t $end
$var reg 1 * utest1_pass $end
$var reg 1 + all_tests_passed $end
$scope module dut $end
$var reg 1 , clk $end
$var reg 1 - rst $end
$var integer 32 . x1 $end
$var integer 32 / x2 $end
$var integer 32 0 x3 $end
$var integer 32 1 dx1 $end
$var integer 32 2 dx2 $end
$var integer 32 3 dx3 $end
$var integer 32 4 prev_x1 $end
$var integer 32 5 prev_x2 $end
$var integer 32 6 prev_x3 $end
$upscope $end
$upscope $end
$enddefinitions $end
#0
0!
1"
b0 #
b0 $
b0 %
b0 &
b0 '
b0 (
b0 )
0*
1+
0,
1-
b0 .
b0 /
b0 0
b0 1
b0 2
b0 3
b0 4
b0 5
b0 6
#5000000
1!
1,
#10000000
0!
0,
#15000000
1!
1,
#20000000
0!
0,
#25000000
1!
1,
#30000000
0!
0,
#35000000
1!
1,
#40000000
0!
0"
b1010 #
b10100 $
b11110 %
0,
0-
b1010 .
b10100 /
b11110 0
#45000000
1!
b1010 &
b10100 '
b11110 (
1,
b1010 1
b10100 2
b11110 3
b1010 4
b10100 5
b11110 6
#50000000
0!
1*
0,
#55000000
1!
b0 &
b0 '
b0 (
1,
b0 1
b0 2
b0 3
#60000000
0!
0,
#65000000
1!
1,
#70000000
0!
0,
#75000000
1!
1,
#80000000
0!
0,
#85000000
1!
1,
#90000000
0!
0,
#95000000
1!
1,
#100000000
0!
1"
0,
1-
b0 4
b0 5
b0 6
#105000000
1!
1,
#110000000
0!
0,
#115000000
1!
1,
#120000000
0!
0"
0,
0-
#125000000
1!
b1010 &
b10100 '
b11110 (
1,
b1010 1
b10100 2
b11110 3
b1010 4
b10100 5
b11110 6
#130000000
0!
0,
#135000000
1!
b0 &
b0 '
b0 (
1,
b0 1
b0 2
b0 3
