src/p4_state_space_2nd_system/etc/p1_2nd_system_step_response.vhd
library IEEE;
use IEEE.STD_LOGIC_1164.ALL;
use IEEE.NUMERIC_STD.ALL;


-- Declare the entity
entity p1_2nd_system_step_response is
    Port (
        clk   : in  std_logic;   -- Clock input
        rst   : in  std_logic;   -- Reset input
        u     : in  integer;     -- Input integer
        y     : out integer      -- Output scaled integer
    );
end p1_2nd_system_step_response;

-- Define the architecture
architecture Behavioral of p1_2nd_system_step_response is
    signal scaled_u : integer := 0;   -- Intermediate signal to store scaled value
    signal sy : integer := 0;   -- Intermediate signal to store scaled value
    signal dy : integer := 0;   -- Intermediate signal to store scaled value
    signal ddy : integer := 0;   -- Intermediate signal to store scaled value
    constant MAX_VALUE : integer := 4095;  -- Maximum value to saturate
    constant MIN_VALUE : integer := -4095;  -- Maximum value to saturate
begin
    -- Process for scaling the input
    process(clk, rst)
    begin
        -- If reset is asserted, reset the scaled output
        if rst = '1' then
            scaled_u <= 0;
            sy <= 0;
            dy <= 0;
            ddy <= 0;

        -- Else if rising edge of the clock, scale the input by 2
        elsif rising_edge(clk) then
            scaled_u <= u * 2;
            ddy <= (u - 1) * 500 / 1024 - dy * 50 / 1024 - sy * 50 / 1024;
            dy  <= dy + ddy;
            sy  <= dy + sy;

            if ddy > MAX_VALUE then
                ddy <= MAX_VALUE;
            end if;

            if ddy < MIN_VALUE then
                ddy <= MIN_VALUE;
            end if;

            if dy > MAX_VALUE then
                dy <= MAX_VALUE;
            end if;

            if dy < MIN_VALUE then
                dy <= MIN_VALUE;
            end if;

            if sy > MAX_VALUE then
                sy <= MAX_VALUE;
            end if;

            if sy < MIN_VALUE then
                sy <= MIN_VALUE;
            end if;

        end if;
    end process;

    -- Assign the scaled output to the output port
    y <= sy;
end Behavioral;

src/p1_2nd_system_step_response/p1_2nd_system_step_response_testbench.vhd
library IEEE;
use IEEE.STD_LOGIC_1164.ALL;
use IEEE.NUMERIC_STD.ALL;

entity p1_2nd_system_step_response_tb is
end p1_2nd_system_step_response_tb;

architecture testbench of p1_2nd_system_step_response_tb is
    -- Component declaration for the DUT (Design Under Test)
    component p1_2nd_system_step_response
        Port (
            clk   : in  std_logic;   -- Clock input
            rst   : in  std_logic;   -- Reset input
            u     : in  integer;     -- Input integer
            y     : out integer      -- Output scaled integer
        );
    end component;

    -- Test signals
    signal clk_tb   : std_logic := '0';   -- Test bench clock signal
    signal rst_tb   : std_logic := '0';   -- Test bench reset signal
    signal u_tb     : integer := 0;       -- Test bench input signal
    signal y_tb     : integer;            -- Test bench output signal

begin
    -- Instantiate the DUT
    dut : p1_2nd_system_step_response
        port map (
            clk => clk_tb,
            rst => rst_tb,
            u   => u_tb,
            y   => y_tb
        );

    -- Clock process
    clk_process : process
    begin
        while now < 1200 ns loop  -- Run for 1000 ns
            clk_tb <= not clk_tb;  -- Toggle clock every half period
            wait for 5 ns;         -- Wait for half period
        end loop;
        wait;  -- Stop simulation
    end process;

    -- Stimulus process
    stimulus : process
    begin
        rst_tb <= '1';   -- Assert reset
        wait for 10 ns;
        rst_tb <= '0';   -- Deassert reset
        wait for 10 ns;

        -- Test with different input values
        for i in 0 to 10 loop
            u_tb <= i;   -- Apply input value
            wait for 10 ns;
        end loop;

        wait;  -- Stop simulation
    end process;
end testbench;

src/p4_state_space_2nd_system/etc/p1_2nd_system_step_response_wave.vcd
$date
  Mon May  6 15:45:33 2024
$end
$version
  GHDL v0
$end
$timescale
  1 fs
$end
$scope module standard $end
$upscope $end
$scope module std_logic_1164 $end
$upscope $end
$scope module numeric_std $end
$upscope $end
$scope module p1_2nd_system_step_response_tb $end
$var reg 1 ! clk_tb $end
$var reg 1 " rst_tb $end
$var integer 32 # u_tb $end
$var integer 32 $ y_tb $end
$scope module dut $end
$var reg 1 % clk $end
$var reg 1 & rst $end
$var integer 32 ' u $end
$var integer 32 ( y $end
$var integer 32 ) scaled_u $end
$var integer 32 * sy $end
$var integer 32 + dy $end
$var integer 32 , ddy $end
$upscope $end
$upscope $end
$enddefinitions $end
#0
1!
1"
b0 #
b0 $
1%
1&
b0 '
b0 (
b0 )
b0 *
b0 +
b0 ,
#5000000
0!
0%
#10000000
1!
0"
1%
0&
#15000000
0!
0%
#20000000
1!
1%
#25000000
0!
0%
#30000000
1!
b1 #
1%
b1 '
b10 )
#35000000
0!
0%
#40000000
1!
b10 #
1%
b10 '
b100 )
#45000000
0!
0%
#50000000
1!
b11 #
1%
b11 '
b110 )
#55000000
0!
0%
#60000000
1!
b100 #
1%
b100 '
b1000 )
b1 ,
#65000000
0!
0%
#70000000
1!
b101 #
1%
b101 '
b1010 )
b1 +
#75000000
0!
0%
#80000000
1!
b110 #
b1 $
1%
b110 '
b1 (
b1100 )
b1 *
b10 +
b10 ,
#85000000
0!
0%
#90000000
1!
b111 #
b11 $
1%
b111 '
b11 (
b1110 )
b11 *
b100 +
#95000000
0!
0%
#100000000
1!
b1000 #
b111 $
1%
b1000 '
b111 (
b10000 )
b111 *
b110 +
b11 ,
#105000000
0!
0%
#110000000
1!
b1001 #
b1101 $
1%
b1001 '
b1101 (
b10010 )
b1101 *
b1001 +
#115000000
0!
0%
#120000000
1!
b1010 #
b10110 $
1%
b1010 '
b10110 (
b10100 )
b10110 *
b1100 +
b100 ,
#125000000
0!
0%
#130000000
1!
b100010 $
1%
b100010 (
b100010 *
b10000 +
b11 ,
#135000000
0!
0%
#140000000
1!
b110010 $
1%
b110010 (
b110010 *
b10011 +
#145000000
0!
0%
#150000000
1!
b1000101 $
1%
b1000101 (
b1000101 *
b10110 +
b10 ,
#155000000
0!
0%
#160000000
1!
b1011011 $
1%
b1011011 (
b1011011 *
b11000 +
b0 ,
#165000000
0!
0%
#170000000
1!
b1110011 $
1%
b1110011 (
b1110011 *
b11111111111111111111111111111111 ,
#175000000
0!
0%
#180000000
1!
b10001011 $
1%
b10001011 (
b10001011 *
b10111 +
b11111111111111111111111111111110 ,
#185000000
0!
0%
#190000000
1!
b10100010 $
1%
b10100010 (
b10100010 *
b10101 +
b11111111111111111111111111111101 ,
#195000000
0!
0%
#200000000
1!
b10110111 $
1%
b10110111 (
b10110111 *
b10010 +
b11111111111111111111111111111100 ,
#205000000
0!
0%
#210000000
1!
b11001001 $
1%
b11001001 (
b11001001 *
b1110 +
#215000000
0!
0%
#220000000
1!
b11010111 $
1%
b11010111 (
b11010111 *
b1010 +
b11111111111111111111111111111011 ,
#225000000
0!
0%
#230000000
1!
b11100001 $
1%
b11100001 (
b11100001 *
b101 +
b11111111111111111111111111111010 ,
#235000000
0!
0%
#240000000
1!
b11100110 $
1%
b11100110 (
b11100110 *
b11111111111111111111111111111111 +
#245000000
0!
0%
#250000000
1!
b11100101 $
1%
b11100101 (
b11100101 *
b11111111111111111111111111111001 +
b11111111111111111111111111111001 ,
#255000000
0!
0%
#260000000
1!
b11011110 $
1%
b11011110 (
b11011110 *
b11111111111111111111111111110010 +
#265000000
0!
0%
#270000000
1!
b11010000 $
1%
b11010000 (
b11010000 *
b11111111111111111111111111101011 +
b11111111111111111111111111111010 ,
#275000000
0!
0%
#280000000
1!
b10111011 $
1%
b10111011 (
b10111011 *
b11111111111111111111111111100101 +
b11111111111111111111111111111011 ,
#285000000
0!
0%
#290000000
1!
b10100000 $
1%
b10100000 (
b10100000 *
b11111111111111111111111111100000 +
b11111111111111111111111111111100 ,
#295000000
0!
0%
#300000000
1!
b10000000 $
1%
b10000000 (
b10000000 *
b11111111111111111111111111011100 +
b11111111111111111111111111111110 ,
#305000000
0!
0%
#310000000
1!
b1011100 $
1%
b1011100 (
b1011100 *
b11111111111111111111111111011010 +
b11111111111111111111111111111111 ,
#315000000
0!
0%
#320000000
1!
b110110 $
1%
b110110 (
b110110 *
b11111111111111111111111111011001 +
b1 ,
#325000000
0!
0%
#330000000
1!
b1111 $
1%
b1111 (
b1111 *
b11111111111111111111111111011010 +
b11 ,
#335000000
0!
0%
#340000000
1!
b11111111111111111111111111101001 $
1%
b11111111111111111111111111101001 (
b11111111111111111111111111101001 *
b11111111111111111111111111011101 +
b101 ,
#345000000
0!
0%
#350000000
1!
b11111111111111111111111111000110 $
1%
b11111111111111111111111111000110 (
b11111111111111111111111111000110 *
b11111111111111111111111111100010 +
b110 ,
#355000000
0!
0%
#360000000
1!
b11111111111111111111111110101000 $
1%
b11111111111111111111111110101000 (
b11111111111111111111111110101000 *
b11111111111111111111111111101000 +
b111 ,
#365000000
0!
0%
#370000000
1!
b11111111111111111111111110010000 $
1%
b11111111111111111111111110010000 (
b11111111111111111111111110010000 *
b11111111111111111111111111101111 +
b1001 ,
#375000000
0!
0%
#380000000
1!
b11111111111111111111111101111111 $
1%
b11111111111111111111111101111111 (
b11111111111111111111111101111111 *
b11111111111111111111111111111000 +
#385000000
0!
0%
#390000000
1!
b11111111111111111111111101110111 $
1%
b11111111111111111111111101110111 (
b11111111111111111111111101110111 *
b1 +
b1010 ,
#395000000
0!
0%
#400000000
1!
b11111111111111111111111101111000 $
1%
b11111111111111111111111101111000 (
b11111111111111111111111101111000 *
b1011 +
#405000000
0!
0%
#410000000
1!
b11111111111111111111111110000011 $
1%
b11111111111111111111111110000011 (
b11111111111111111111111110000011 *
b10101 +
#415000000
0!
0%
#420000000
1!
b11111111111111111111111110011000 $
1%
b11111111111111111111111110011000 (
b11111111111111111111111110011000 *
b11111 +
b1001 ,
#425000000
0!
0%
#430000000
1!
b11111111111111111111111110110111 $
1%
b11111111111111111111111110110111 (
b11111111111111111111111110110111 *
b101000 +
b1000 ,
#435000000
0!
0%
#440000000
1!
b11111111111111111111111111011111 $
1%
b11111111111111111111111111011111 (
b11111111111111111111111111011111 *
b110000 +
b110 ,
#445000000
0!
0%
#450000000
1!
b1111 $
1%
b1111 (
b1111 *
b110110 +
b11 ,
#455000000
0!
0%
#460000000
1!
b1000101 $
1%
b1000101 (
b1000101 *
b111001 +
b10 ,
#465000000
0!
0%
#470000000
1!
b1111110 $
1%
b1111110 (
b1111110 *
b111011 +
b11111111111111111111111111111111 ,
#475000000
0!
0%
#480000000
1!
b10111001 $
1%
b10111001 (
b10111001 *
b111010 +
b11111111111111111111111111111100 ,
#485000000
0!
0%
#490000000
1!
b11110011 $
1%
b11110011 (
b11110011 *
b110110 +
b11111111111111111111111111111001 ,
#495000000
0!
0%
#500000000
1!
b100101001 $
1%
b100101001 (
b100101001 *
b101111 +
b11111111111111111111111111110111 ,
#505000000
0!
0%
#510000000
1!
b101011000 $
1%
b101011000 (
b101011000 *
b100110 +
b11111111111111111111111111110100 ,
#515000000
0!
0%
#520000000
1!
b101111110 $
1%
b101111110 (
b101111110 *
b11010 +
b11111111111111111111111111110011 ,
#525000000
0!
0%
#530000000
1!
b110011000 $
1%
b110011000 (
b110011000 *
b1101 +
b11111111111111111111111111110001 ,
#535000000
0!
0%
#540000000
1!
b110100101 $
1%
b110100101 (
b110100101 *
b11111111111111111111111111111110 +
#545000000
0!
0%
#550000000
1!
b110100011 $
1%
b110100011 (
b110100011 *
b11111111111111111111111111101111 +
b11111111111111111111111111110000 ,
#555000000
0!
0%
#560000000
1!
b110010010 $
1%
b110010010 (
b110010010 *
b11111111111111111111111111011111 +
#565000000
0!
0%
#570000000
1!
b101110001 $
1%
b101110001 (
b101110001 *
b11111111111111111111111111001111 +
b11111111111111111111111111110010 ,
#575000000
0!
0%
#580000000
1!
b101000000 $
1%
b101000000 (
b101000000 *
b11111111111111111111111111000001 +
b11111111111111111111111111110100 ,
#585000000
0!
0%
#590000000
1!
b100000001 $
1%
b100000001 (
b100000001 *
b11111111111111111111111110110101 +
b11111111111111111111111111111000 ,
#595000000
0!
0%
#600000000
1!
b10110110 $
1%
b10110110 (
b10110110 *
b11111111111111111111111110101101 +
b11111111111111111111111111111011 ,
#605000000
0!
0%
#610000000
1!
b1100011 $
1%
b1100011 (
b1100011 *
b11111111111111111111111110101000 +
b0 ,
#615000000
0!
0%
#620000000
1!
b1011 $
1%
b1011 (
b1011 *
b100 ,
#625000000
0!
0%
#630000000
1!
b11111111111111111111111110110011 $
1%
b11111111111111111111111110110011 (
b11111111111111111111111110110011 *
b11111111111111111111111110101100 +
b1000 ,
#635000000
0!
0%
#640000000
1!
b11111111111111111111111101011111 $
1%
b11111111111111111111111101011111 (
b11111111111111111111111101011111 *
b11111111111111111111111110110100 +
b1011 ,
#645000000
0!
0%
#650000000
1!
b11111111111111111111111100010011 $
1%
b11111111111111111111111100010011 (
b11111111111111111111111100010011 *
b11111111111111111111111110111111 +
b1110 ,
#655000000
0!
0%
#660000000
1!
b11111111111111111111111011010010 $
1%
b11111111111111111111111011010010 (
b11111111111111111111111011010010 *
b11111111111111111111111111001101 +
b10010 ,
#665000000
0!
0%
#670000000
1!
b11111111111111111111111010011111 $
1%
b11111111111111111111111010011111 (
b11111111111111111111111010011111 *
b11111111111111111111111111011111 +
b10100 ,
#675000000
0!
0%
#680000000
1!
b11111111111111111111111001111110 $
1%
b11111111111111111111111001111110 (
b11111111111111111111111001111110 *
b11111111111111111111111111110011 +
b10110 ,
#685000000
0!
0%
#690000000
1!
b11111111111111111111111001110001 $
1%
b11111111111111111111111001110001 (
b11111111111111111111111001110001 *
b1001 +
#695000000
0!
0%
#700000000
1!
b11111111111111111111111001111010 $
1%
b11111111111111111111111001111010 (
b11111111111111111111111001111010 *
b11111 +
b10111 ,
#705000000
0!
0%
#710000000
1!
b11111111111111111111111010011001 $
1%
b11111111111111111111111010011001 (
b11111111111111111111111010011001 *
b110110 +
b10110 ,
#715000000
0!
0%
#720000000
1!
b11111111111111111111111011001111 $
1%
b11111111111111111111111011001111 (
b11111111111111111111111011001111 *
b1001100 +
b10011 ,
#725000000
0!
0%
#730000000
1!
b11111111111111111111111100011011 $
1%
b11111111111111111111111100011011 (
b11111111111111111111111100011011 *
b1011111 +
b1111 ,
#735000000
0!
0%
#740000000
1!
b11111111111111111111111101111010 $
1%
b11111111111111111111111101111010 (
b11111111111111111111111101111010 *
b1101110 +
b1011 ,
#745000000
0!
0%
#750000000
1!
b11111111111111111111111111101000 $
1%
b11111111111111111111111111101000 (
b11111111111111111111111111101000 *
b1111001 +
b101 ,
#755000000
0!
0%
#760000000
1!
b1100001 $
1%
b1100001 (
b1100001 *
b1111110 +
b0 ,
#765000000
0!
0%
#770000000
1!
b11011111 $
1%
b11011111 (
b11011111 *
b11111111111111111111111111111010 ,
#775000000
0!
0%
#780000000
1!
b101011101 $
1%
b101011101 (
b101011101 *
b1111000 +
b11111111111111111111111111110100 ,
#785000000
0!
0%
#790000000
1!
b111010101 $
1%
b111010101 (
b111010101 *
b1101100 +
b11111111111111111111111111101110 ,
#795000000
0!
0%
#800000000
1!
b1001000001 $
1%
b1001000001 (
b1001000001 *
b1011010 +
b11111111111111111111111111101001 ,
#805000000
0!
0%
#810000000
1!
b1010011011 $
1%
b1010011011 (
b1010011011 *
b1000011 +
b11111111111111111111111111100100 ,
#815000000
0!
0%
#820000000
1!
b1011011110 $
1%
b1011011110 (
b1011011110 *
b100111 +
b11111111111111111111111111100001 ,
#825000000
0!
0%
#830000000
1!
b1100000101 $
1%
b1100000101 (
b1100000101 *
b1000 +
b11111111111111111111111111100000 ,
#835000000
0!
0%
#840000000
1!
b1100001101 $
1%
b1100001101 (
b1100001101 *
b11111111111111111111111111101000 +
b11111111111111111111111111011111 ,
#845000000
0!
0%
#850000000
1!
b1011110101 $
1%
b1011110101 (
b1011110101 *
b11111111111111111111111111000111 +
#855000000
0!
0%
#860000000
1!
b1010111100 $
1%
b1010111100 (
b1010111100 *
b11111111111111111111111110100110 +
b11111111111111111111111111100010 ,
#865000000
0!
0%
#870000000
1!
b1001100010 $
1%
b1001100010 (
b1001100010 *
b11111111111111111111111110001000 +
b11111111111111111111111111100110 ,
#875000000
0!
0%
#880000000
1!
b111101010 $
1%
b111101010 (
b111101010 *
b11111111111111111111111101101110 +
b11111111111111111111111111101100 ,
#885000000
0!
0%
#890000000
1!
b101011000 $
1%
b101011000 (
b101011000 *
b11111111111111111111111101011010 +
b11111111111111111111111111110100 ,
#895000000
0!
0%
#900000000
1!
b10110010 $
1%
b10110010 (
b10110010 *
b11111111111111111111111101001110 +
b11111111111111111111111111111100 ,
#905000000
0!
0%
#910000000
1!
b0 $
1%
b0 (
b0 *
b11111111111111111111111101001010 +
b100 ,
#915000000
0!
0%
#920000000
1!
b11111111111111111111111101001010 $
1%
b11111111111111111111111101001010 (
b11111111111111111111111101001010 *
b11111111111111111111111101001110 +
b1100 ,
#925000000
0!
0%
#930000000
1!
b11111111111111111111111010011000 $
1%
b11111111111111111111111010011000 (
b11111111111111111111111010011000 *
b11111111111111111111111101011010 +
b10100 ,
#935000000
0!
0%
#940000000
1!
b11111111111111111111110111110010 $
1%
b11111111111111111111110111110010 (
b11111111111111111111110111110010 *
b11111111111111111111111101101110 +
b11101 ,
#945000000
0!
0%
#950000000
1!
b11111111111111111111110101100000 $
1%
b11111111111111111111110101100000 (
b11111111111111111111110101100000 *
b11111111111111111111111110001011 +
b100100 ,
#955000000
0!
0%
#960000000
1!
b11111111111111111111110011101011 $
1%
b11111111111111111111110011101011 (
b11111111111111111111110011101011 *
b11111111111111111111111110101111 +
b101001 ,
#965000000
0!
0%
#970000000
1!
b11111111111111111111110010011010 $
1%
b11111111111111111111110010011010 (
b11111111111111111111110010011010 *
b11111111111111111111111111011000 +
b101101 ,
#975000000
0!
0%
#980000000
1!
b11111111111111111111110001110010 $
1%
b11111111111111111111110001110010 (
b11111111111111111111110001110010 *
b101 +
b101111 ,
#985000000
0!
0%
#990000000
1!
b11111111111111111111110001110111 $
1%
b11111111111111111111110001110111 (
b11111111111111111111110001110111 *
b110100 +
b110000 ,
#995000000
0!
0%
#1000000000
1!
b11111111111111111111110010101011 $
1%
b11111111111111111111110010101011 (
b11111111111111111111110010101011 *
b1100100 +
b101110 ,
#1005000000
0!
0%
#1010000000
1!
b11111111111111111111110100001111 $
1%
b11111111111111111111110100001111 (
b11111111111111111111110100001111 *
b10010010 +
b101001 ,
#1015000000
0!
0%
#1020000000
1!
b11111111111111111111110110100001 $
1%
b11111111111111111111110110100001 (
b11111111111111111111110110100001 *
b10111011 +
b100001 ,
#1025000000
0!
0%
#1030000000
1!
b11111111111111111111111001011100 $
1%
b11111111111111111111111001011100 (
b11111111111111111111111001011100 *
b11011100 +
b11000 ,
#1035000000
0!
0%
#1040000000
1!
b11111111111111111111111100111000 $
1%
b11111111111111111111111100111000 (
b11111111111111111111111100111000 *
b11110100 +
b1110 ,
#1045000000
0!
0%
#1050000000
1!
b101100 $
1%
b101100 (
b101100 *
b100000010 +
b10 ,
#1055000000
0!
0%
#1060000000
1!
b100101110 $
1%
b100101110 (
b100101110 *
b100000100 +
b11111111111111111111111111110110 ,
#1065000000
0!
0%
#1070000000
1!
b1000110010 $
1%
b1000110010 (
b1000110010 *
b11111010 +
b11111111111111111111111111101010 ,
#1075000000
0!
0%
#1080000000
1!
b1100101100 $
1%
b1100101100 (
b1100101100 *
b11100100 +
b11111111111111111111111111011101 ,
#1085000000
0!
0%
#1090000000
1!
b10000010000 $
1%
b10000010000 (
b10000010000 *
b11000001 +
b11111111111111111111111111010010 ,
#1095000000
0!
0%
#1100000000
1!
b10011010001 $
1%
b10011010001 (
b10011010001 *
b10010011 +
b11111111111111111111111111001001 ,
#1105000000
0!
0%
#1110000000
1!
b10101100100 $
1%
b10101100100 (
b10101100100 *
b1011100 +
b11111111111111111111111111000001 ,
#1115000000
0!
0%
#1120000000
1!
b10111000000 $
1%
b10111000000 (
b10111000000 *
b11101 +
b11111111111111111111111110111101 ,
#1125000000
0!
0%
#1130000000
1!
b10111011101 $
1%
b10111011101 (
b10111011101 *
b11111111111111111111111111011010 +
b11111111111111111111111110111100 ,
#1135000000
0!
0%
#1140000000
1!
b10110110111 $
1%
b10110110111 (
b10110110111 *
b11111111111111111111111110010110 +
#1145000000
0!
0%
#1150000000
1!
b10101001101 $
1%
b10101001101 (
b10101001101 *
b11111111111111111111111101010010 +
b11111111111111111111111111000010 ,
#1155000000
0!
0%
#1160000000
1!
b10010011111 $
1%
b10010011111 (
b10010011111 *
b11111111111111111111111100010100 +
b11111111111111111111111111001010 ,
#1165000000
0!
0%
#1170000000
1!
b1110110011 $
1%
b1110110011 (
b1110110011 *
b11111111111111111111111011011110 +
b11111111111111111111111111010110 ,
#1175000000
0!
0%
#1180000000
1!
b1010010001 $
1%
b1010010001 (
b1010010001 *
b11111111111111111111111010110100 +
b11111111111111111111111111100100 ,
#1185000000
0!
0%
#1190000000
1!
b101000101 $
1%
b101000101 (
b101000101 *
b11111111111111111111111010011000 +
b11111111111111111111111111110100 ,
