src/p4_state_space_n_system/lib/filters/filter_low_pass.vhd
library IEEE;
use IEEE.STD_LOGIC_1164.ALL;
use IEEE.NUMERIC_STD.ALL;

entity FilterLowPass is
    Port (
        clk   : in  std_logic;
        rst   : in  std_logic;
        x     : in  integer;
        y     : out integer
    );
end entity FilterLowPass;

architecture FilterLowPassRTL of FilterLowPass is
    -- Internal signal for storing the previous output value
    signal s_y : integer := 0;
    signal s_y_prev : integer := 0;

    -- Filter coefficients (adjust these based on your desired cutoff frequency)
    constant ALPHA : integer := 10;  -- Adjust this value for desired filtering effect

begin
    process(clk, rst)
    begin
        if rst = '1' then
            -- Reset the internal state and output when the reset signal is asserted
            s_y <= 0;
            s_y_prev <= 0;
        elsif rising_edge(clk) then
            -- Update the output using the first-order low-pass filter equation
            s_y <= s_y_prev + (x - s_y_prev) / ALPHA;
            -- Store the current output value for the next iteration
            s_y_prev <= s_y;
        end if;

        y <= s_y_prev;
    end process;
end FilterLowPassRTL;

src/p2_random_noise_generator/lib/noise.vhd
library IEEE;
use IEEE.STD_LOGIC_1164.ALL;
use IEEE.NUMERIC_STD.ALL;

entity Noise is
    Port (
        clk : in  std_logic;                     -- Clock input
        rst : in  std_logic;                     -- Reset input
        x   : in  integer;                       -- Input signal
        y   : out integer                        -- Output signal with noise
    );
end entity Noise;

architecture Behavioral of Noise is

    constant a : integer := 1;
    constant b : integer := 1;
    constant c : integer := 1;
    constant d : integer := 1;

    constant LFSR_WIDTH : integer := 16;
    signal s_lfsr_y : integer := 0;             -- Noise signal
    signal s_lfsr_count : integer := 0;          -- LFSR count
    signal s_lfsr_reg : std_logic_vector(31 downto 0) := (others => '0');   -- LFSR register
    signal s_lfsr_reg2 : std_logic_vector(31 downto 0) := (others => '0');  -- LFSR register
    signal s_lfsr_reg3 : std_logic_vector(31 downto 0) := (others => '0');  -- LFSR register
    signal s_lfsr_reg4 : std_logic_vector(31 downto 0) := (others => '0');  -- LFSR register
    signal lfsr_tap : std_logic;

begin
    process(clk, rst)
    begin
        if rst = '1' then
            s_lfsr_y <= 0;                          -- Reset noise signal
            s_lfsr_count <= 0;                      -- Reset LFSR count
            s_lfsr_reg <= (others => '0');          -- Reset LFSR register
            s_lfsr_reg2 <= (others => '0');         -- Reset LFSR register
            s_lfsr_reg3 <= (others => '0');         -- Reset LFSR register
            s_lfsr_reg4 <= (others => '0');         -- Reset LFSR register
            y <= 0;                                 -- Reset output
        elsif rising_edge(clk) then
            -- Increment counters
            -- Increment counters
            if s_lfsr_count < 16 then
                s_lfsr_reg <= std_logic_vector(unsigned(s_lfsr_reg) + 1);
            end if;
            if s_lfsr_count < 8 then
                s_lfsr_reg2 <= std_logic_vector(unsigned(s_lfsr_reg2) + 1);
            end if;
            if s_lfsr_count < 4 then
                s_lfsr_reg3 <= std_logic_vector(unsigned(s_lfsr_reg3) + 1);
            end if;
            if s_lfsr_count < 2 then
                s_lfsr_reg4 <= std_logic_vector(unsigned(s_lfsr_reg4) + 1);
            end if;


            -- Update noise signal
            s_lfsr_y <= a * to_integer(unsigned(s_lfsr_reg)) + b * to_integer(unsigned(s_lfsr_reg2)) + c * to_integer(unsigned(s_lfsr_reg3)) + d * to_integer(unsigned(s_lfsr_reg4));

            -- Output signal with noise
            y <=  x;

            -- Increment LFSR count
            if s_lfsr_count = 19 then
                s_lfsr_count <= 0;
            else
                s_lfsr_count <= s_lfsr_count + 1;
            end if;
        end if;
    end process;
end Behavioral;

src/p1_2nd_system_step_response/lib/saturation.vhd
library IEEE;
use IEEE.STD_LOGIC_1164.ALL;
use IEEE.NUMERIC_STD.ALL;

-- Include the saturation module
-- Change the path to match the location of your Saturation.vhdl file
entity Saturation is
    Port (
        x       : in  integer;
        max_val : in  integer;
        min_val : in  integer;
        y       : out integer
    );
end entity Saturation;

architecture SaturationRTL of Saturation is
begin
    process(x, max_val, min_val)
    begin
        if x > max_val then
            y <= max_val;
        elsif x < min_val then
            y <= min_val;
        else
            y <= x;
        end if;
    end process;
end SaturationRTL;

src/p2_random_noise_generator/src/main.vhd
library IEEE;
use IEEE.STD_LOGIC_1164.ALL;
use IEEE.NUMERIC_STD.ALL;



entity Main is
    Port (
        clk     : in  std_logic;
        rst     : in  std_logic;
        u       : in  integer;
        y       : out integer;
        y_noise : out integer
    );
end Main;

architecture Behavioral of Main is

    signal s_y : integer := 0;
    signal s_dy : integer := 0;
    signal s_ddy : integer := 0;

    constant SCALE_VALUE : integer := 8192;
    constant SCALE_DT : integer := 100;

    constant MAX_VALUE : integer := 65536;
    constant MIN_VALUE : integer := -65536;

    constant K : integer := 1 * SCALE_VALUE;

    constant b2 : integer := 1 * SCALE_VALUE;
    constant b1 : integer := 2 * SCALE_VALUE;
    constant b0 : integer := 10 * SCALE_VALUE;

    constant a0 : integer := 10 * SCALE_VALUE;

    component Saturation is
        Port (
            x       : in  integer;
            max_val : in  integer;
            min_val : in  integer;
            y       : out integer
        );
    end component;


    component Noise is
        Port (
            clk   : in  std_logic;
            rst   : in  std_logic;
            x     : in  integer;
            y     : out integer
        );
    end component;

    component FilterLowPass is
        Port (
            clk   : in  std_logic;
            rst   : in  std_logic;
            x     : in  integer;
            y     : out integer
        );
    end component;

    signal s_sat_in : integer;
    signal s_sat_out : integer;
    signal s_sat_noise_out : integer;
    signal s_sat_noise_filtered_out : integer;

begin
    process(clk, rst)
    begin
        if rst = '1' then
            s_y <= 0;
            s_dy <= 0;
            s_ddy <= 0;
            s_sat_in <= 0;
        elsif rising_edge(clk) then
            s_ddy <= (u) * (a0 / b2) - s_dy * (b1 / b2) - s_y * (b0 / b2);
            s_dy  <= s_dy + s_ddy / SCALE_DT;
            s_y   <= s_y + s_dy / SCALE_DT;

            s_sat_in <= s_y;
        end if;
    end process;

    saturation_inst : Saturation
    port map (
        max_val => MAX_VALUE,
        min_val => MIN_VALUE,
        x       => s_sat_in,
        y       => s_sat_out
    );

    noise_inst : Noise
    port map (
        clk => clk,
        rst => rst,
        x => s_sat_out,
        y => s_sat_noise_out
    );

    filter_low_pass_inst : FilterLowPass
    port map (
        clk => clk,
        rst => rst,
        x => s_sat_noise_out,
        y => s_sat_noise_filtered_out
    );

    y <= s_sat_noise_filtered_out;
    y_noise <= s_sat_noise_out;

end Behavioral;

src/p3_feedback_loop_pid_controller/test/main_testbench.vhd
library IEEE;
use IEEE.STD_LOGIC_1164.ALL;
use IEEE.NUMERIC_STD.ALL;

entity Main_tb is
end Main_tb;

architecture testbench of Main_tb is
    -- Component declaration for the DUT (Design Under Test)
    component Main
        Port (
            clk   : in  std_logic;   -- Clock input
            rst   : in  std_logic;   -- Reset input
            u     : in  integer;     -- Input integer
            y     : out integer;      -- Output scaled integer
            y_noise     : out integer      -- Output scaled integer
        );
    end component;

    -- Test signals
    signal clk_tb   : std_logic := '0';   -- Test bench clock signal
    signal rst_tb   : std_logic := '0';   -- Test bench reset signal
    signal u_tb     : integer := 0;       -- Test bench input signal
    signal y_tb     : integer;            -- Test bench output signal
    signal y_noise_tb     : integer;            -- Test bench output signal

begin
    -- Instantiate the DUT
    dut : Main
        port map (
            clk => clk_tb,
            rst => rst_tb,
            u   => u_tb,
            y   => y_tb,
            y_noise   => y_noise_tb
        );

    -- Clock process
    clk_process : process
    begin
        while now < 10000 ns loop  -- Run for 1000 ns
            clk_tb <= not clk_tb;  -- Toggle clock every half period
            wait for 5 ns;         -- Wait for half period
        end loop;
        wait;  -- Stop simulation
    end process;

    -- Stimulus process
    stimulus : process
    begin
        u_tb <= 0;
        rst_tb <= '1';   -- Assert reset

        wait for 20 ns;
        u_tb <= 0;
        rst_tb <= '0';   -- Deassert reset

        wait for 20 ns;  -- u(t) = 0
        u_tb <= 0;

        wait for 20 ns;   -- u(t) = 1
        u_tb <= 8192;

        wait;  -- Stop simulation
    end process;
end testbench;

src/p2_random_noise_generator/test/main_wave.vcd
$date
  Fri May 10 20:04:02 2024
$end
$version
  GHDL v0
$end
$timescale
  1 fs
$end
$scope module standard $end
$upscope $end
$scope module std_logic_1164 $end
$upscope $end
$scope module numeric_std $end
$upscope $end
$scope module main_tb $end
$var reg 1 ! clk_tb $end
$var reg 1 " rst_tb $end
$var integer 32 # u_tb $end
$var integer 32 $ y_tb $end
$scope module dut $end
$var reg 1 % clk $end
$var reg 1 & rst $end
$var integer 32 ' u $end
$var integer 32 ( y $end
$var integer 32 ) s_y $end
$var integer 32 * s_dy $end
$var integer 32 + s_ddy $end
$var integer 32 , s_sat_in $end
$var integer 32 - s_sat_out $end
$var integer 32 . s_sat_noise_out $end
$scope module saturation_inst $end
$var integer 32 / x $end
$var integer 32 0 max_val $end
$var integer 32 1 min_val $end
$var integer 32 2 y $end
$upscope $end
$scope module noise_inst $end
$var reg 1 3 clk $end
$var reg 1 4 rst $end
$var integer 32 5 x $end
$var integer 32 6 y $end
$var integer 32 7 s_lfsr_y $end
$var integer 32 8 s_lfsr_count $end
$var reg 32 9 s_lfsr_reg[31:0] $end
$var reg 32 : s_lfsr_reg2[31:0] $end
$var reg 32 ; s_lfsr_reg3[31:0] $end
$var reg 32 < s_lfsr_reg4[31:0] $end
$var reg 1 = lfsr_tap $end
$upscope $end
$upscope $end
$upscope $end
$enddefinitions $end
#0
1!
1"
b0 #
b0 $
1%
1&
b0 '
b0 (
b0 )
b0 *
b0 +
b0 ,
b0 -
b0 .
b0 /
b10000000000000000 0
b11111111111111110000000000000000 1
b0 2
13
14
b0 5
b0 6
b0 7
b0 8
b00000000000000000000000000000000 9
b00000000000000000000000000000000 :
b00000000000000000000000000000000 ;
b00000000000000000000000000000000 <
U=
#5000000
0!
0%
03
#10000000
1!
1%
13
#15000000
0!
0%
03
#20000000
1!
0"
1%
0&
13
04
b1 8
b00000000000000000000000000000001 9
b00000000000000000000000000000001 :
b00000000000000000000000000000001 ;
b00000000000000000000000000000001 <
#25000000
0!
0%
03
#30000000
1!
1%
13
b100 7
b10 8
b00000000000000000000000000000010 9
b00000000000000000000000000000010 :
b00000000000000000000000000000010 ;
b00000000000000000000000000000010 <
#35000000
0!
0%
03
#40000000
1!
1%
13
b1000 7
b11 8
b00000000000000000000000000000011 9
b00000000000000000000000000000011 :
b00000000000000000000000000000011 ;
#45000000
0!
0%
03
#50000000
1!
1%
13
b1011 7
b100 8
b00000000000000000000000000000100 9
b00000000000000000000000000000100 :
b00000000000000000000000000000100 ;
#55000000
0!
0%
03
#60000000
1!
b10000000000000 #
1%
b10000000000000 '
b10100000000000000 +
13
b1110 7
b101 8
b00000000000000000000000000000101 9
b00000000000000000000000000000101 :
#65000000
0!
0%
03
#70000000
1!
1%
b1100110011 *
13
b10000 7
b110 8
b00000000000000000000000000000110 9
b00000000000000000000000000000110 :
#75000000
0!
0%
03
#80000000
1!
1%
b1000 )
b11001100110 *
b10011100110011010 +
13
b10010 7
b111 8
b00000000000000000000000000000111 9
b00000000000000000000000000000111 :
#85000000
0!
0%
03
#90000000
1!
1%
b11000 )
b100110001000 *
b10011001011100100 +
b1000 ,
b1000 -
b1000 /
b1000 2
13
b1000 5
b10100 7
b1000 8
b00000000000000000000000000001000 9
b00000000000000000000000000001000 :
#95000000
0!
0%
03
#100000000
1!
b1000 $
1%
b1000 (
b110000 )
b110010011001 *
b10010110000000000 +
b11000 ,
b11000 -
b1000 .
b11000 /
b11000 2
13
b11000 5
b1000 6
b10110 7
b1001 8
b00000000000000000000000000001001 9
#105000000
0!
0%
03
#110000000
1!
b11000 $
1%
b11000 (
b1010000 )
b111110011001 *
b10010010011101110 +
b110000 ,
b110000 -
b11000 .
b110000 /
b110000 2
13
b110000 5
b11000 6
b10111 7
b1010 8
b00000000000000000000000000001010 9
#115000000
0!
0%
03
#120000000
1!
b110000 $
1%
b110000 (
b1110111 )
b1001010000110 *
b10001110110101110 +
b1010000 ,
b1010000 -
b110000 .
b1010000 /
b1010000 2
13
b1010000 5
b110000 6
b11000 7
b1011 8
b00000000000000000000000000001011 9
#125000000
0!
0%
03
#130000000
1!
b1010000 $
1%
b1010000 (
b10100110 )
b1010101100001 *
b10001011001001110 +
b1110111 ,
b1110111 -
b1010000 .
b1110111 /
b1110111 2
13
b1110111 5
b1010000 6
b11001 7
b1100 8
b00000000000000000000000000001100 9
#135000000
0!
0%
03
#140000000
1!
b1110111 $
1%
b1110111 (
b11011100 )
b1100000101001 *
b10000111011000010 +
b10100110 ,
b10100110 -
b1110111 .
b10100110 /
b10100110 2
13
b10100110 5
b1110111 6
b11010 7
b1101 8
b00000000000000000000000000001101 9
#145000000
0!
0%
03
#150000000
1!
b10100110 $
1%
b10100110 (
b100011001 )
b1101011011110 *
b10000011100010110 +
b11011100 ,
b11011100 -
b10100110 .
b11011100 /
b11011100 2
13
b11011100 5
b10100110 6
b11011 7
b1110 8
b00000000000000000000000000001110 9
#155000000
0!
0%
03
#160000000
1!
b11011100 $
1%
b11011100 (
b101011101 )
b1110101111111 *
b1111111101001010 +
b100011001 ,
b100011001 -
b11011100 .
b100011001 /
b100011001 2
13
b100011001 5
b11011100 6
b11100 7
b1111 8
b00000000000000000000000000001111 9
#165000000
0!
0%
03
#170000000
1!
b100011001 $
1%
b100011001 (
b110101000 )
b10000000001100 *
b1111011101100000 +
b101011101 ,
b101011101 -
b100011001 .
b101011101 /
b101011101 2
13
b101011101 5
b100011001 6
b11101 7
b10000 8
b00000000000000000000000000010000 9
#175000000
0!
0%
03
#180000000
1!
b101011101 $
1%
b101011101 (
b111111010 )
b10001010000101 *
b1110111101011000 +
b110101000 ,
b110101000 -
b101011101 .
b110101000 /
b110101000 2
13
b110101000 5
b101011101 6
b11110 7
b10001 8
#185000000
0!
0%
03
#190000000
1!
b110101000 $
1%
b110101000 (
b1001010010 )
b10010011101001 *
b1110011100110010 +
b111111010 ,
b111111010 -
b110101000 .
b111111010 /
b111111010 2
13
b111111010 5
b110101000 6
b10010 8
#195000000
0!
0%
03
#200000000
1!
b111111010 $
1%
b111111010 (
b1010110000 )
b10011100111000 *
b1101111011111010 +
b1001010010 ,
b1001010010 -
b111111010 .
b1001010010 /
b1001010010 2
13
b1001010010 5
b111111010 6
b10011 8
#205000000
0!
0%
03
#210000000
1!
b1001010010 $
1%
b1001010010 (
b1100010100 )
b10100101110010 *
b1101011010110000 +
b1010110000 ,
b1010110000 -
b1001010010 .
b1010110000 /
b1010110000 2
13
b1010110000 5
b1001010010 6
b0 8
#215000000
0!
0%
03
#220000000
1!
b1010110000 $
1%
b1010110000 (
b1101111110 )
b10101110010111 *
b1100111001010100 +
b1100010100 ,
b1100010100 -
b1010110000 .
b1100010100 /
b1100010100 2
13
b1100010100 5
b1010110000 6
b1 8
b00000000000000000000000000010001 9
b00000000000000000000000000001001 :
b00000000000000000000000000000101 ;
b00000000000000000000000000000011 <
#225000000
0!
0%
03
#230000000
1!
b1100010100 $
1%
b1100010100 (
b1111101101 )
b10110110100111 *
b1100010111100110 +
b1101111110 ,
b1101111110 -
b1100010100 .
b1101111110 /
b1101111110 2
13
b1101111110 5
b1100010100 6
b100010 7
b10 8
b00000000000000000000000000010010 9
b00000000000000000000000000001010 :
b00000000000000000000000000000110 ;
b00000000000000000000000000000100 <
#235000000
0!
0%
03
#240000000
1!
b1101111110 $
1%
b1101111110 (
b10001100001 )
b10111110100001 *
b1011110101110000 +
b1111101101 ,
b1111101101 -
b1101111110 .
b1111101101 /
b1111101101 2
13
b1111101101 5
b1101111110 6
b100110 7
b11 8
b00000000000000000000000000010011 9
b00000000000000000000000000001011 :
b00000000000000000000000000000111 ;
#245000000
0!
0%
03
#250000000
1!
b1111101101 $
1%
b1111101101 (
b10011011010 )
b11000110000101 *
b1011010011110100 +
b10001100001 ,
b10001100001 -
b1111101101 .
b10001100001 /
b10001100001 2
13
b10001100001 5
b1111101101 6
b101001 7
b100 8
b00000000000000000000000000010100 9
b00000000000000000000000000001100 :
b00000000000000000000000000001000 ;
#255000000
0!
0%
03
#260000000
1!
b10001100001 $
1%
b10001100001 (
b10101011000 )
b11001101010100 *
b1010110001110010 +
b10011011010 ,
b10011011010 -
b10001100001 .
b10011011010 /
b10011011010 2
13
b10011011010 5
b10001100001 6
b101100 7
b101 8
b00000000000000000000000000010101 9
b00000000000000000000000000001101 :
#265000000
0!
0%
03
#270000000
1!
b10011011010 $
1%
b10011011010 (
b10111011011 )
b11010100001101 *
b1010001111101000 +
b10101011000 ,
b10101011000 -
b10011011010 .
b10101011000 /
b10101011000 2
13
b10101011000 5
b10011011010 6
b101110 7
b110 8
b00000000000000000000000000010110 9
b00000000000000000000000000001110 :
#275000000
0!
0%
03
#280000000
1!
b10101011000 $
1%
b10101011000 (
b11001100010 )
b11011010110000 *
b1001101101011000 +
b10111011011 ,
b10111011011 -
b10101011000 .
b10111011011 /
b10111011011 2
13
b10111011011 5
b10101011000 6
b110000 7
b111 8
b00000000000000000000000000010111 9
b00000000000000000000000000001111 :
#285000000
0!
0%
03
#290000000
1!
b10111011011 $
1%
b10111011011 (
b11011101110 )
b11100000111101 *
b1001001011001100 +
b11001100010 ,
b11001100010 -
b10111011011 .
b11001100010 /
b11001100010 2
13
b11001100010 5
b10111011011 6
b110010 7
b1000 8
b00000000000000000000000000011000 9
b00000000000000000000000000010000 :
#295000000
0!
0%
03
#300000000
1!
b11001100010 $
1%
b11001100010 (
b11101111101 )
b11100110110100 *
b1000101000111010 +
b11011101110 ,
b11011101110 -
b11001100010 .
b11011101110 /
b11011101110 2
13
b11011101110 5
b11001100010 6
b110100 7
b1001 8
b00000000000000000000000000011001 9
#305000000
0!
0%
03
#310000000
1!
b11011101110 $
1%
b11011101110 (
b100000010000 )
b11101100010101 *
b1000000110110110 +
b11101111101 ,
b11101111101 -
b11011101110 .
b11101111101 /
b11101111101 2
13
b11101111101 5
b11011101110 6
b110101 7
b1010 8
b00000000000000000000000000011010 9
#315000000
0!
0%
03
#320000000
1!
b11101111101 $
1%
b11101111101 (
b100010100111 )
b11110001100001 *
b111100100110110 +
b100000010000 ,
b100000010000 -
b11101111101 .
b100000010000 /
b100000010000 2
13
b100000010000 5
b11101111101 6
b110110 7
b1011 8
b00000000000000000000000000011011 9
#325000000
0!
0%
03
#330000000
1!
b100000010000 $
1%
b100000010000 (
b100101000001 )
b11110110010111 *
b111000010111000 +
b100010100111 ,
b100010100111 -
b100000010000 .
b100010100111 /
b100010100111 2
13
b100010100111 5
b100000010000 6
b110111 7
b1100 8
b00000000000000000000000000011100 9
#335000000
0!
0%
03
#340000000
1!
b100010100111 $
1%
b100010100111 (
b100111011110 )
b11111010110111 *
b110100001001000 +
b100101000001 ,
b100101000001 -
b100010100111 .
b100101000001 /
b100101000001 2
13
b100101000001 5
b100010100111 6
b111000 7
b1101 8
b00000000000000000000000000011101 9
#345000000
0!
0%
03
#350000000
1!
b100101000001 $
1%
b100101000001 (
b101001111110 )
b11111111000001 *
b101111111100110 +
b100111011110 ,
b100111011110 -
b100101000001 .
b100111011110 /
b100111011110 2
13
b100111011110 5
b100101000001 6
b111001 7
b1110 8
b00000000000000000000000000011110 9
#355000000
0!
0%
03
#360000000
1!
b100111011110 $
1%
b100111011110 (
b101100100001 )
b100000010110110 *
b101011110010010 +
b101001111110 ,
b101001111110 -
b100111011110 .
b101001111110 /
b101001111110 2
13
b101001111110 5
b100111011110 6
b111010 7
b1111 8
b00000000000000000000000000011111 9
#365000000
0!
0%
03
#370000000
1!
b101001111110 $
1%
b101001111110 (
b101111000110 )
b100000110010110 *
b100111101001010 +
b101100100001 ,
b101100100001 -
b101001111110 .
b101100100001 /
b101100100001 2
13
b101100100001 5
b101001111110 6
b111011 7
b10000 8
b00000000000000000000000000100000 9
#375000000
0!
0%
03
#380000000
1!
b101100100001 $
1%
b101100100001 (
b110001101101 )
b100001001100000 *
b100011100011000 +
b101111000110 ,
b101111000110 -
b101100100001 .
b101111000110 /
b101111000110 2
13
b101111000110 5
b101100100001 6
b111100 7
b10001 8
#385000000
0!
0%
03
#390000000
1!
b101111000110 $
1%
b101111000110 (
b110100010110 )
b100001100010110 *
b11111011111110 +
b110001101101 ,
b110001101101 -
b101111000110 .
b110001101101 /
b110001101101 2
13
b110001101101 5
b101111000110 6
b10010 8
#395000000
0!
0%
03
#400000000
1!
b110001101101 $
1%
b110001101101 (
b110111000001 )
b100001110110111 *
b11011011111000 +
b110100010110 ,
b110100010110 -
b110001101101 .
b110100010110 /
b110100010110 2
13
b110100010110 5
b110001101101 6
b10011 8
#405000000
0!
0%
03
#410000000
1!
b110100010110 $
1%
b110100010110 (
b111001101110 )
b100010001000011 *
b10111100001000 +
b110111000001 ,
b110111000001 -
b110100010110 .
b110111000001 /
b110111000001 2
13
b110111000001 5
b110100010110 6
b0 8
#415000000
0!
0%
03
#420000000
1!
b110111000001 $
1%
b110111000001 (
b111100011100 )
b100010010111011 *
b10011100101110 +
b111001101110 ,
b111001101110 -
b110111000001 .
b111001101110 /
b111001101110 2
13
b111001101110 5
b110111000001 6
b1 8
b00000000000000000000000000100001 9
b00000000000000000000000000010001 :
b00000000000000000000000000001001 ;
b00000000000000000000000000000101 <
#425000000
0!
0%
03
#430000000
1!
b111001101110 $
1%
b111001101110 (
b111111001011 )
b100010100011111 *
b1111101110010 +
b111100011100 ,
b111100011100 -
b111001101110 .
b111100011100 /
b111100011100 2
13
b111100011100 5
b111001101110 6
b1000000 7
b10 8
b00000000000000000000000000100010 9
b00000000000000000000000000010010 :
b00000000000000000000000000001010 ;
b00000000000000000000000000000110 <
#435000000
0!
0%
03
#440000000
1!
b111100011100 $
1%
b111100011100 (
b1000001111011 )
b100010101101111 *
b1011111010100 +
b111111001011 ,
b111111001011 -
b111100011100 .
b111111001011 /
b111111001011 2
13
b111111001011 5
b111100011100 6
b1000100 7
b11 8
b00000000000000000000000000100011 9
b00000000000000000000000000010011 :
b00000000000000000000000000001011 ;
#445000000
0!
0%
03
#450000000
1!
b111111001011 $
1%
b111111001011 (
b1000100101100 )
b100010110101100 *
b1000001010100 +
b1000001111011 ,
b1000001111011 -
b111111001011 .
b1000001111011 /
b1000001111011 2
13
b1000001111011 5
b111111001011 6
b1000111 7
b100 8
b00000000000000000000000000100100 9
b00000000000000000000000000010100 :
b00000000000000000000000000001100 ;
#455000000
0!
0%
03
#460000000
1!
b1000001111011 $
1%
b1000001111011 (
b1000111011110 )
b100010111010101 *
b100011110000 +
b1000100101100 ,
b1000100101100 -
b1000001111011 .
b1000100101100 /
b1000100101100 2
13
b1000100101100 5
b1000001111011 6
b1001010 7
b101 8
b00000000000000000000000000100101 9
b00000000000000000000000000010101 :
#465000000
0!
0%
03
#470000000
1!
b1000100101100 $
1%
b1000100101100 (
b1001010010000 )
b100010111101011 *
b110101010 +
b1000111011110 ,
b1000111011110 -
b1000100101100 .
b1000111011110 /
b1000111011110 2
13
b1000111011110 5
b1000100101100 6
b1001100 7
b110 8
b00000000000000000000000000100110 9
b00000000000000000000000000010110 :
#475000000
0!
0%
03
#480000000
1!
b1000111011110 $
1%
b1000111011110 (
b1001101000010 )
b100010111101111 *
b11111111111111111111101010001010 +
b1001010010000 ,
b1001010010000 -
b1000111011110 .
b1001010010000 /
b1001010010000 2
13
b1001010010000 5
b1000111011110 6
b1001110 7
b111 8
b00000000000000000000000000100111 9
b00000000000000000000000000010111 :
#485000000
0!
0%
03
#490000000
1!
b1001010010000 $
1%
b1001010010000 (
b1001111110101 )
b100010111100010 *
b11111111111111111111001110001110 +
b1001101000010 ,
b1001101000010 -
b1001010010000 .
b1001101000010 /
b1001101000010 2
13
b1001101000010 5
b1001010010000 6
b1010000 7
b1000 8
b00000000000000000000000000101000 9
b00000000000000000000000000011000 :
#495000000
0!
0%
03
#500000000
1!
b1001101000010 $
1%
b1001101000010 (
b1010010100111 )
b100010111000011 *
b11111111111111111110110010101010 +
b1001111110101 ,
b1001111110101 -
b1001101000010 .
b1001111110101 /
b1001111110101 2
13
b1001111110101 5
b1001101000010 6
b1010010 7
b1001 8
b00000000000000000000000000101001 9
#505000000
0!
0%
03
#510000000
1!
b1001111110101 $
1%
b1001111110101 (
b1010101011001 )
b100010110010010 *
b11111111111111111110010111110100 +
b1010010100111 ,
b1010010100111 -
b1001111110101 .
b1010010100111 /
b1010010100111 2
13
b1010010100111 5
b1001111110101 6
b1010011 7
b1010 8
b00000000000000000000000000101010 9
#515000000
0!
0%
03
#520000000
1!
b1010010100111 $
1%
b1010010100111 (
b1011000001011 )
b100010101010000 *
b11111111111111111101111101100010 +
b1010101011001 ,
b1010101011001 -
b1010010100111 .
b1010101011001 /
b1010101011001 2
13
b1010101011001 5
b1010010100111 6
b1010100 7
b1011 8
b00000000000000000000000000101011 9
#525000000
0!
0%
03
#530000000
1!
b1010101011001 $
1%
b1010101011001 (
b1011010111100 )
b100010011111101 *
b11111111111111111101100011110010 +
b1011000001011 ,
b1011000001011 -
b1010101011001 .
b1011000001011 /
b1011000001011 2
13
b1011000001011 5
b1010101011001 6
b1010101 7
b1100 8
b00000000000000000000000000101100 9
#535000000
0!
0%
03
#540000000
1!
b1011000001011 $
1%
b1011000001011 (
b1011101101100 )
b100010010011010 *
b11111111111111111101001010101110 +
b1011010111100 ,
b1011010111100 -
b1011000001011 .
b1011010111100 /
b1011010111100 2
13
b1011010111100 5
b1011000001011 6
b1010110 7
b1101 8
b00000000000000000000000000101101 9
#545000000
0!
0%
03
#550000000
1!
b1011010111100 $
1%
b1011010111100 (
b1100000011011 )
b100010000100110 *
b11111111111111111100110010010100 +
b1011101101100 ,
b1011101101100 -
b1011010111100 .
b1011101101100 /
b1011101101100 2
13
b1011101101100 5
b1011010111100 6
b1010111 7
b1110 8
b00000000000000000000000000101110 9
#555000000
0!
0%
03
#560000000
1!
b1011101101100 $
1%
b1011101101100 (
b1100011001001 )
b100001110100011 *
b11111111111111111100011010100110 +
b1100000011011 ,
b1100000011011 -
b1011101101100 .
b1100000011011 /
b1100000011011 2
13
b1100000011011 5
b1011101101100 6
b1011000 7
b1111 8
b00000000000000000000000000101111 9
#565000000
0!
0%
03
#570000000
1!
b1100000011011 $
1%
b1100000011011 (
b1100101110110 )
b100001100010001 *
b11111111111111111100000011100000 +
b1100011001001 ,
b1100011001001 -
b1100000011011 .
b1100011001001 /
b1100011001001 2
13
b1100011001001 5
b1100000011011 6
b1011001 7
b10000 8
b00000000000000000000000000110000 9
#575000000
0!
0%
03
#580000000
1!
b1100011001001 $
1%
b1100011001001 (
b1101000100001 )
b100001001110000 *
b11111111111111111011101101000010 +
b1100101110110 ,
b1100101110110 -
b1100011001001 .
b1100101110110 /
b1100101110110 2
13
b1100101110110 5
b1100011001001 6
b1011010 7
b10001 8
#585000000
0!
0%
03
#590000000
1!
b1100101110110 $
1%
b1100101110110 (
b1101011001011 )
b100000111000001 *
b11111111111111111011010111010110 +
b1101000100001 ,
b1101000100001 -
b1100101110110 .
b1101000100001 /
b1101000100001 2
13
b1101000100001 5
b1100101110110 6
b10010 8
#595000000
0!
0%
03
#600000000
1!
b1101000100001 $
1%
b1101000100001 (
b1101101110011 )
b100000100000100 *
b11111111111111111011000010010000 +
b1101011001011 ,
b1101011001011 -
b1101000100001 .
b1101011001011 /
b1101011001011 2
13
b1101011001011 5
b1101000100001 6
b10011 8
#605000000
0!
0%
03
#610000000
1!
b1101011001011 $
1%
b1101011001011 (
b1110000011001 )
b100000000111001 *
b11111111111111111010101101111010 +
b1101101110011 ,
b1101101110011 -
b1101011001011 .
b1101101110011 /
b1101101110011 2
13
b1101101110011 5
b1101011001011 6
b0 8
#615000000
0!
0%
03
#620000000
1!
b1101101110011 $
1%
b1101101110011 (
b1110010111101 )
b11111101100001 *
b11111111111111111010011010010100 +
b1110000011001 ,
b1110000011001 -
b1101101110011 .
b1110000011001 /
b1110000011001 2
13
b1110000011001 5
b1101101110011 6
b1 8
b00000000000000000000000000110001 9
b00000000000000000000000000011001 :
b00000000000000000000000000001101 ;
b00000000000000000000000000000111 <
#625000000
0!
0%
03
#630000000
1!
b1110000011001 $
1%
b1110000011001 (
b1110101011111 )
b11111001111101 *
b11111111111111111010000111011100 +
b1110010111101 ,
b1110010111101 -
b1110000011001 .
b1110010111101 /
b1110010111101 2
13
b1110010111101 5
b1110000011001 6
b1011110 7
b10 8
b00000000000000000000000000110010 9
b00000000000000000000000000011010 :
b00000000000000000000000000001110 ;
b00000000000000000000000000001000 <
#635000000
0!
0%
03
#640000000
1!
b1110010111101 $
1%
b1110010111101 (
b1110111111110 )
b11110110001100 *
b11111111111111111001110101010000 +
b1110101011111 ,
b1110101011111 -
b1110010111101 .
b1110101011111 /
b1110101011111 2
13
b1110101011111 5
b1110010111101 6
b1100010 7
b11 8
b00000000000000000000000000110011 9
b00000000000000000000000000011011 :
b00000000000000000000000000001111 ;
#645000000
0!
0%
03
#650000000
1!
b1110101011111 $
1%
b1110101011111 (
b1111010011011 )
b11110010010000 *
b11111111111111111001100011111100 +
b1110111111110 ,
b1110111111110 -
b1110101011111 .
b1110111111110 /
b1110111111110 2
13
b1110111111110 5
b1110101011111 6
b1100101 7
b100 8
b00000000000000000000000000110100 9
b00000000000000000000000000011100 :
b00000000000000000000000000010000 ;
#655000000
0!
0%
03
#660000000
1!
b1110111111110 $
1%
b1110111111110 (
b1111100110110 )
b11101110001001 *
b11111111111111111001010011010010 +
b1111010011011 ,
b1111010011011 -
b1110111111110 .
b1111010011011 /
b1111010011011 2
13
b1111010011011 5
b1110111111110 6
b1101000 7
b101 8
b00000000000000000000000000110101 9
b00000000000000000000000000011101 :
#665000000
0!
0%
03
