src/p4_state_space_n_system/lib/filters/filter_low_pass.vhd
library IEEE;
use IEEE.STD_LOGIC_1164.ALL;
use IEEE.NUMERIC_STD.ALL;

entity FilterLowPass is
    Port (
        clk   : in  std_logic;
        rst   : in  std_logic;
        x     : in  integer;
        y     : out integer
    );
end entity FilterLowPass;

architecture FilterLowPassRTL of FilterLowPass is
    -- Internal signal for storing the previous output value
    signal s_y : integer := 0;
    signal s_y_prev : integer := 0;

    -- Filter coefficients (adjust these based on your desired cutoff frequency)
    constant ALPHA : integer := 10;  -- Adjust this value for desired filtering effect

begin
    process(clk, rst)
    begin
        if rst = '1' then
            -- Reset the internal state and output when the reset signal is asserted
            s_y <= 0;
            s_y_prev <= 0;
        elsif rising_edge(clk) then
            -- Update the output using the first-order low-pass filter equation
            s_y <= s_y_prev + (x - s_y_prev) / ALPHA;
            -- Store the current output value for the next iteration
            s_y_prev <= s_y;
        end if;

        y <= s_y_prev;
    end process;
end FilterLowPassRTL;

src/p2_random_noise_generator/lib/noise.vhd
library IEEE;
use IEEE.STD_LOGIC_1164.ALL;
use IEEE.NUMERIC_STD.ALL;

entity Noise is
    Port (
        clk : in  std_logic;         -- Clock input
        rst : in  std_logic;         -- Reset input
        x   : in  integer;           -- Input signal
        y   : out integer            -- Output signal with noise
    );
end entity Noise;

architecture Behavioral of Noise is

    constant A : integer := 2;
    constant B : integer := 4;
    constant C : integer := 8;
    constant D : integer := 16;
    constant E : integer := 32;
    constant F : integer := 64;

    constant P0 : integer := 128;
    constant P1 : integer := 64;
    constant P2 : integer := 32;
    constant P3 : integer := 16;
    constant P4 : integer := 8;
    constant P5 : integer := 4;

    constant DIVIDER : integer := 1;  -- Integer division factor

    signal s_lfsr_y : integer := 0;             -- Noise signal
    signal s_lfsr_count1 : integer := 0;        -- LFSR count
    signal s_lfsr_count2 : integer := 0;        -- LFSR count
    signal s_lfsr_count3 : integer := 0;        -- LFSR count
    signal s_lfsr_count4 : integer := 0;        -- LFSR count
    signal s_lfsr_count5 : integer := 0;        -- LFSR count
    signal s_lfsr_count6 : integer := 0;        -- LFSR count

begin
    process(clk, rst)
    begin
        if rst = '1' then
            s_lfsr_y <= 0;              -- Reset noise signal
            s_lfsr_count1 <= 0;
            s_lfsr_count2 <= 0;
            s_lfsr_count3 <= 0;
            s_lfsr_count4 <= 0;
            s_lfsr_count5 <= 0;
            s_lfsr_count6 <= 0;
            y <= 0;                     -- Reset output
        elsif rising_edge(clk) then

            -- Increment counters
            if s_lfsr_count1 < A then
                s_lfsr_count1 <= s_lfsr_count1 + 1;
            else
                s_lfsr_count1 <= 0;
            end if;

            if s_lfsr_count2 < B then
                s_lfsr_count2 <= s_lfsr_count2 + 1;
            else
                s_lfsr_count2 <= 0;
            end if;

            if s_lfsr_count3 < C then
                s_lfsr_count3 <= s_lfsr_count3 + 1;
            else
                s_lfsr_count3 <= 0;
            end if;

            if s_lfsr_count4 < D then
                s_lfsr_count4 <= s_lfsr_count4 + 1;
            else
                s_lfsr_count4 <= 0;
            end if;

            if s_lfsr_count5 < E then
                s_lfsr_count5 <= s_lfsr_count5 + 1;
            else
                s_lfsr_count5 <= 0;
            end if;

            if s_lfsr_count6 < F then
                s_lfsr_count6 <= s_lfsr_count6 + 1;
            else
                s_lfsr_count6 <= 0;
            end if;

            s_lfsr_y <= P0 * (s_lfsr_count1 - A/2) +
                        P1 * (s_lfsr_count2 - B/2) +
                        P2 * (s_lfsr_count3 - C/2) +
                        P3 * (s_lfsr_count4 - D/2) +
                        P4 * (s_lfsr_count5 - E/2) +
                        P5 * (s_lfsr_count6 - F/2);

            -- Output signal with noise
            y <= x + s_lfsr_y;

        end if;
    end process;

end Behavioral;

src/p1_2nd_system_step_response/lib/saturation.vhd
library IEEE;
use IEEE.STD_LOGIC_1164.ALL;
use IEEE.NUMERIC_STD.ALL;

-- Include the saturation module
-- Change the path to match the location of your Saturation.vhdl file
entity Saturation is
    Port (
        x       : in  integer;
        max_val : in  integer;
        min_val : in  integer;
        y       : out integer
    );
end entity Saturation;

architecture SaturationRTL of Saturation is
begin
    process(x, max_val, min_val)
    begin
        if x > max_val then
            y <= max_val;
        elsif x < min_val then
            y <= min_val;
        else
            y <= x;
        end if;
    end process;
end SaturationRTL;

src/p2_random_noise_generator/src/main.vhd
library IEEE;
use IEEE.STD_LOGIC_1164.ALL;
use IEEE.NUMERIC_STD.ALL;



entity Main is
    Port (
        clk     : in  std_logic;
        rst     : in  std_logic;
        u       : in  integer;
        y       : out integer;
        y_noise : out integer
    );
end Main;

architecture Behavioral of Main is

    signal s_y : integer := 0;
    signal s_dy : integer := 0;
    signal s_ddy : integer := 0;

    constant SCALE_VALUE : integer := 8192;
    constant SCALE_DT : integer := 100;

    constant MAX_VALUE : integer := 65536;
    constant MIN_VALUE : integer := -65536;

    constant K : integer := 1 * SCALE_VALUE;

    constant b2 : integer := 1 * SCALE_VALUE;
    constant b1 : integer := 2 * SCALE_VALUE;
    constant b0 : integer := 10 * SCALE_VALUE;

    constant a0 : integer := 10 * SCALE_VALUE;

    component Saturation is
        Port (
            x       : in  integer;
            max_val : in  integer;
            min_val : in  integer;
            y       : out integer
        );
    end component;


    component Noise is
        Port (
            clk   : in  std_logic;
            rst   : in  std_logic;
            x     : in  integer;
            y     : out integer
        );
    end component;

    component FilterLowPass is
        Port (
            clk   : in  std_logic;
            rst   : in  std_logic;
            x     : in  integer;
            y     : out integer
        );
    end component;

    signal s_sat_in : integer;
    signal s_sat_out : integer;
    signal s_sat_noise_out : integer;
    signal s_sat_noise_filtered_out : integer;

begin
    process(clk, rst)
    begin
        if rst = '1' then
            s_y <= 0;
            s_dy <= 0;
            s_ddy <= 0;
            s_sat_in <= 0;
        elsif rising_edge(clk) then
            s_ddy <= (u) * (a0 / b2) - s_dy * (b1 / b2) - s_y * (b0 / b2);
            s_dy  <= s_dy + s_ddy / SCALE_DT;
            s_y   <= s_y + s_dy / SCALE_DT;

            s_sat_in <= s_y;
        end if;
    end process;

    saturation_inst : Saturation
    port map (
        max_val => MAX_VALUE,
        min_val => MIN_VALUE,
        x       => s_sat_in,
        y       => s_sat_out
    );

    noise_inst : Noise
    port map (
        clk => clk,
        rst => rst,
        x => s_sat_out,
        y => s_sat_noise_out
    );

    filter_low_pass_inst : FilterLowPass
    port map (
        clk => clk,
        rst => rst,
        x => s_sat_noise_out,
        y => s_sat_noise_filtered_out
    );

    y <= s_sat_noise_filtered_out;
    y_noise <= s_sat_noise_out;

end Behavioral;

src/p3_feedback_loop_pid_controller/test/main_testbench.vhd
library IEEE;
use IEEE.STD_LOGIC_1164.ALL;
use IEEE.NUMERIC_STD.ALL;

entity Main_tb is
end Main_tb;

architecture testbench of Main_tb is
    -- Component declaration for the DUT (Design Under Test)
    component Main
        Port (
            clk   : in  std_logic;   -- Clock input
            rst   : in  std_logic;   -- Reset input
            u     : in  integer;     -- Input integer
            y     : out integer;      -- Output scaled integer
            y_noise     : out integer      -- Output scaled integer
        );
    end component;

    -- Test signals
    signal clk_tb   : std_logic := '0';   -- Test bench clock signal
    signal rst_tb   : std_logic := '0';   -- Test bench reset signal
    signal u_tb     : integer := 0;       -- Test bench input signal
    signal y_tb     : integer;            -- Test bench output signal
    signal y_noise_tb     : integer;            -- Test bench output signal

begin
    -- Instantiate the DUT
    dut : Main
        port map (
            clk => clk_tb,
            rst => rst_tb,
            u   => u_tb,
            y   => y_tb,
            y_noise   => y_noise_tb
        );

    -- Clock process
    clk_process : process
    begin
        while now < 10000 ns loop  -- Run for 1000 ns
            clk_tb <= not clk_tb;  -- Toggle clock every half period
            wait for 5 ns;         -- Wait for half period
        end loop;
        wait;  -- Stop simulation
    end process;

    -- Stimulus process
    stimulus : process
    begin
        u_tb <= 0;
        rst_tb <= '1';   -- Assert reset

        wait for 20 ns;
        u_tb <= 0;
        rst_tb <= '0';   -- Deassert reset

        wait for 20 ns;  -- u(t) = 0
        u_tb <= 0;

        wait for 20 ns;   -- u(t) = 1
        u_tb <= 8192;

        wait;  -- Stop simulation
    end process;
end testbench;

src/p2_random_noise_generator/test/main_wave.vcd
$date
  Tue May 14 18:22:38 2024
$end
$version
  GHDL v0
$end
$timescale
  1 fs
$end
$scope module standard $end
$upscope $end
$scope module std_logic_1164 $end
$upscope $end
$scope module numeric_std $end
$upscope $end
$scope module main_tb $end
$var reg 1 ! clk_tb $end
$var reg 1 " rst_tb $end
$var integer 32 # u_tb $end
$var integer 32 $ y_tb $end
$var integer 32 % y_noise_tb $end
$scope module dut $end
$var reg 1 & clk $end
$var reg 1 ' rst $end
$var integer 32 ( u $end
$var integer 32 ) y $end
$var integer 32 * y_noise $end
$var integer 32 + s_y $end
$var integer 32 , s_dy $end
$var integer 32 - s_ddy $end
$var integer 32 . s_sat_in $end
$var integer 32 / s_sat_out $end
$var integer 32 0 s_sat_noise_out $end
$var integer 32 1 s_sat_noise_filtered_out $end
$scope module saturation_inst $end
$var integer 32 2 x $end
$var integer 32 3 max_val $end
$var integer 32 4 min_val $end
$var integer 32 5 y $end
$upscope $end
$scope module noise_inst $end
$var reg 1 6 clk $end
$var reg 1 7 rst $end
$var integer 32 8 x $end
$var integer 32 9 y $end
$var integer 32 : s_lfsr_y $end
$var integer 32 ; s_lfsr_count1 $end
$var integer 32 < s_lfsr_count2 $end
$var integer 32 = s_lfsr_count3 $end
$var integer 32 > s_lfsr_count4 $end
$var integer 32 ? s_lfsr_count5 $end
$var integer 32 @ s_lfsr_count6 $end
$upscope $end
$scope module filter_low_pass_inst $end
$var reg 1 A clk $end
$var reg 1 B rst $end
$var integer 32 C x $end
$var integer 32 D y $end
$var integer 32 E s_y $end
$var integer 32 F s_y_prev $end
$upscope $end
$upscope $end
$upscope $end
$enddefinitions $end
#0
1!
1"
b0 #
b0 $
b0 %
1&
1'
b0 (
b0 )
b0 *
b0 +
b0 ,
b0 -
b0 .
b0 /
b0 0
b0 1
b0 2
b10000000000000000 3
b11111111111111110000000000000000 4
b0 5
16
17
b0 8
b0 9
b0 :
b0 ;
b0 <
b0 =
b0 >
b0 ?
b0 @
1A
1B
b0 C
b0 D
b0 E
b0 F
#5000000
0!
0&
06
0A
#10000000
1!
1&
16
1A
#15000000
0!
0&
06
0A
#20000000
1!
0"
1&
0'
16
07
b11111111111111111111110100000000 :
b1 ;
b1 <
b1 =
b1 >
b1 ?
b1 @
1A
0B
#25000000
0!
0&
06
0A
#30000000
1!
b11111111111111111111110100000000 %
1&
b11111111111111111111110100000000 *
b11111111111111111111110100000000 0
16
b11111111111111111111110100000000 9
b11111111111111111111110111111100 :
b10 ;
b10 <
b10 =
b10 >
b10 ?
b10 @
1A
b11111111111111111111110100000000 C
#35000000
0!
0&
06
0A
#40000000
1!
b11111111111111111111110111111100 %
1&
b11111111111111111111110111111100 *
b11111111111111111111110111111100 0
16
b11111111111111111111110111111100 9
b11111111111111111111111011111000 :
b0 ;
b11 <
b11 =
b11 >
b11 ?
b11 @
1A
b11111111111111111111110111111100 C
b11111111111111111111111110110100 E
#45000000
0!
0&
06
0A
#50000000
1!
b11111111111111111111111011111000 %
1&
b11111111111111111111111011111000 *
b11111111111111111111111011111000 0
16
b11111111111111111111111011111000 9
b11111111111111111111111001110100 :
b1 ;
b100 <
b100 =
b100 >
b100 ?
b100 @
1A
b11111111111111111111111011111000 C
b11111111111111111111111111001101 E
b11111111111111111111111110110100 F
#55000000
0!
b11111111111111111111111110110100 $
0&
b11111111111111111111111110110100 )
b11111111111111111111111110110100 1
06
0A
b11111111111111111111111110110100 D
#60000000
1!
b10000000000000 #
b11111111111111111111111001110100 %
1&
b10000000000000 (
b11111111111111111111111001110100 *
b10100000000000000 -
b11111111111111111111111001110100 0
16
b11111111111111111111111001110100 9
b11111111111111111111111101110000 :
b10 ;
b0 <
b101 =
b101 >
b101 ?
b101 @
1A
b11111111111111111111111001110100 C
b11111111111111111111111110100010 E
b11111111111111111111111111001101 F
#65000000
0!
b11111111111111111111111111001101 $
0&
b11111111111111111111111111001101 )
b11111111111111111111111111001101 1
06
0A
b11111111111111111111111111001101 D
#70000000
1!
b11111111111111111111111101110000 %
1&
b11111111111111111111111101110000 *
b1100110011 ,
b11111111111111111111111101110000 0
16
b11111111111111111111111101110000 9
b11111111111111111111111100101100 :
b0 ;
b1 <
b110 =
b110 >
b110 ?
b110 @
1A
b11111111111111111111111101110000 C
b11111111111111111111111110101011 E
b11111111111111111111111110100010 F
#75000000
0!
b11111111111111111111111110100010 $
0&
b11111111111111111111111110100010 )
b11111111111111111111111110100010 1
06
0A
b11111111111111111111111110100010 D
#80000000
1!
b11111111111111111111111100101100 %
1&
b11111111111111111111111100101100 *
b1000 +
b11001100110 ,
b10011100110011010 -
b11111111111111111111111100101100 0
16
b11111111111111111111111100101100 9
b11111111111111111111111010101000 :
b1 ;
b10 <
b111 =
b111 >
b111 ?
b111 @
1A
b11111111111111111111111100101100 C
b11111111111111111111111110011101 E
b11111111111111111111111110101011 F
#85000000
0!
b11111111111111111111111110101011 $
0&
b11111111111111111111111110101011 )
b11111111111111111111111110101011 1
06
0A
b11111111111111111111111110101011 D
#90000000
1!
b11111111111111111111111010101000 %
1&
b11111111111111111111111010101000 *
b11000 +
b100110001000 ,
b10011001011100100 -
b1000 .
b1000 /
b11111111111111111111111010101000 0
b1000 2
b1000 5
16
b1000 8
b11111111111111111111111010101000 9
b11111111111111111111111110100100 :
b10 ;
b11 <
b1000 =
b1000 >
b1000 ?
b1000 @
1A
b11111111111111111111111010101000 C
b11111111111111111111111110011111 E
b11111111111111111111111110011101 F
#95000000
0!
b11111111111111111111111110011101 $
0&
b11111111111111111111111110011101 )
b11111111111111111111111110011101 1
06
0A
b11111111111111111111111110011101 D
#100000000
1!
b11111111111111111111111110101100 %
1&
b11111111111111111111111110101100 *
b110000 +
b110010011001 ,
b10010110000000000 -
b11000 .
b11000 /
b11111111111111111111111110101100 0
b11000 2
b11000 5
16
b11000 8
b11111111111111111111111110101100 9
b10100000 :
b0 ;
b100 <
b0 =
b1001 >
b1001 ?
b1001 @
1A
b11111111111111111111111110101100 C
b11111111111111111111111110000101 E
b11111111111111111111111110011111 F
#105000000
0!
b11111111111111111111111110011111 $
0&
b11111111111111111111111110011111 )
b11111111111111111111111110011111 1
06
0A
b11111111111111111111111110011111 D
#110000000
1!
b10111000 %
1&
b10111000 *
b1010000 +
b111110011001 ,
b10010010011101110 -
b110000 .
b110000 /
b10111000 0
b110000 2
b110000 5
16
b110000 8
b10111000 9
b11111111111111111111111011111100 :
b1 ;
b0 <
b1 =
b1010 >
b1010 ?
b1010 @
1A
b10111000 C
b11111111111111111111111110100000 E
b11111111111111111111111110000101 F
#115000000
0!
b11111111111111111111111110000101 $
0&
b11111111111111111111111110000101 )
b11111111111111111111111110000101 1
06
0A
b11111111111111111111111110000101 D
#120000000
1!
b11111111111111111111111100101100 %
1&
b11111111111111111111111100101100 *
b1110111 +
b1001010000110 ,
b10001110110101110 -
b1010000 .
b1010000 /
b11111111111111111111111100101100 0
b1010000 2
b1010000 5
16
b1010000 8
b11111111111111111111111100101100 9
b11111111111111111111111010111000 :
b10 ;
b1 <
b10 =
b1011 >
b1011 ?
b1011 @
1A
b11111111111111111111111100101100 C
b11111111111111111111111110100011 E
b11111111111111111111111110100000 F
#125000000
0!
b11111111111111111111111110100000 $
0&
b11111111111111111111111110100000 )
b11111111111111111111111110100000 1
06
0A
b11111111111111111111111110100000 D
#130000000
1!
b11111111111111111111111100001000 %
1&
b11111111111111111111111100001000 *
b10100110 +
b1010101100001 ,
b10001011001001110 -
b1110111 .
b1110111 /
b11111111111111111111111100001000 0
b1110111 2
b1110111 5
16
b1110111 8
b11111111111111111111111100001000 9
b11111111111111111111111110110100 :
b0 ;
b10 <
b11 =
b1100 >
b1100 ?
b1100 @
1A
b11111111111111111111111100001000 C
b11111111111111111111111110010101 E
b11111111111111111111111110100011 F
#135000000
0!
b11111111111111111111111110100011 $
0&
b11111111111111111111111110100011 )
b11111111111111111111111110100011 1
06
0A
b11111111111111111111111110100011 D
#140000000
1!
b101011 %
1&
b101011 *
b11011100 +
b1100000101001 ,
b10000111011000010 -
b10100110 .
b10100110 /
b101011 0
b10100110 2
b10100110 5
16
b10100110 8
b101011 9
b11111111111111111111111100110000 :
b1 ;
b11 <
b100 =
b1101 >
b1101 ?
b1101 @
1A
b101011 C
b11111111111111111111111110010100 E
b11111111111111111111111110010101 F
#145000000
0!
b11111111111111111111111110010101 $
0&
b11111111111111111111111110010101 )
b11111111111111111111111110010101 1
06
0A
b11111111111111111111111110010101 D
#150000000
1!
b11111111111111111111111111010110 %
1&
b11111111111111111111111111010110 *
b100011001 +
b1101011011110 ,
b10000011100010110 -
b11011100 .
b11011100 /
b11111111111111111111111111010110 0
b11011100 2
b11011100 5
16
b11011100 8
b11111111111111111111111111010110 9
b101100 :
b10 ;
b100 <
b101 =
b1110 >
b1110 ?
b1110 @
1A
b11111111111111111111111111010110 C
b11111111111111111111111110100100 E
b11111111111111111111111110010100 F
#155000000
0!
b11111111111111111111111110010100 $
0&
b11111111111111111111111110010100 )
b11111111111111111111111110010100 1
06
0A
b11111111111111111111111110010100 D
#160000000
1!
b100001000 %
1&
b100001000 *
b101011101 +
b1110101111111 ,
b1111111101001010 -
b100011001 .
b100011001 /
b100001000 0
b100011001 2
b100011001 5
16
b100011001 8
b100001000 9
b100101000 :
b0 ;
b0 <
b110 =
b1111 >
b1111 ?
b1111 @
1A
b100001000 C
b11111111111111111111111110011010 E
b11111111111111111111111110100100 F
#165000000
0!
b11111111111111111111111110100100 $
0&
b11111111111111111111111110100100 )
b11111111111111111111111110100100 1
06
0A
b11111111111111111111111110100100 D
#170000000
1!
b1001000001 %
1&
b1001000001 *
b110101000 +
b10000000001100 ,
b1111011101100000 -
b101011101 .
b101011101 /
b1001000001 0
b101011101 2
b101011101 5
16
b101011101 8
b1001000001 9
b11111111111111111111111101100100 :
b1 ;
b1 <
b111 =
b10000 >
b10000 ?
b10000 @
1A
b1001000001 C
b11111111111111111111111111000111 E
b11111111111111111111111110011010 F
#175000000
0!
b11111111111111111111111110011010 $
0&
b11111111111111111111111110011010 )
b11111111111111111111111110011010 1
06
0A
b11111111111111111111111110011010 D
#180000000
1!
b11000001 %
1&
b11000001 *
b111111010 +
b10001010000101 ,
b1110111101011000 -
b110101000 .
b110101000 /
b11000001 0
b110101000 2
b110101000 5
16
b110101000 8
b11000001 9
b1100000 :
b10 ;
b10 <
b1000 =
b0 >
b10001 ?
b10001 @
1A
b11000001 C
b11111111111111111111111111011101 E
b11111111111111111111111111000111 F
#185000000
0!
b11111111111111111111111111000111 $
0&
b11111111111111111111111111000111 )
b11111111111111111111111111000111 1
06
0A
b11111111111111111111111111000111 D
#190000000
1!
b1000001000 %
1&
b1000001000 *
b1001010010 +
b10010011101001 ,
b1110011100110010 -
b111111010 .
b111111010 /
b1000001000 0
b111111010 2
b111111010 5
16
b111111010 8
b1000001000 9
b1001100 :
b0 ;
b11 <
b0 =
b1 >
b10010 ?
b10010 @
1A
b1000001000 C
b11111111111111111111111111100000 E
b11111111111111111111111111011101 F
#195000000
0!
b11111111111111111111111111011101 $
0&
b11111111111111111111111111011101 )
b11111111111111111111111111011101 1
06
0A
b11111111111111111111111111011101 D
#200000000
1!
b1001000110 %
1&
b1001000110 *
b1010110000 +
b10011100111000 ,
b1101111011111010 -
b1001010010 .
b1001010010 /
b1001000110 0
b1001010010 2
b1001010010 5
16
b1001010010 8
b1001000110 9
b11111111111111111111111010101000 :
b1 ;
b100 <
b1 =
b10 >
b10011 ?
b10011 @
1A
b1001000110 C
b10100 E
b11111111111111111111111111100000 F
#205000000
0!
b11111111111111111111111111100000 $
0&
b11111111111111111111111111100000 )
b11111111111111111111111111100000 1
06
0A
b11111111111111111111111111100000 D
#210000000
1!
b11111010 %
1&
b11111010 *
b1100010100 +
b10100101110010 ,
b1101011010110000 -
b1010110000 .
b1010110000 /
b11111010 0
b1010110000 2
b1010110000 5
16
b1010110000 8
b11111010 9
b11111111111111111111111110100100 :
b10 ;
b0 <
b10 =
b11 >
b10100 ?
b10100 @
1A
b11111010 C
b11101 E
b10100 F
#215000000
0!
b10100 $
0&
b10100 )
b10100 1
06
0A
b10100 D
#220000000
1!
b1001010100 %
1&
b1001010100 *
b1101111110 +
b10101110010111 ,
b1100111001010100 -
b1100010100 .
b1100010100 /
b1001010100 0
b1100010100 2
b1100010100 5
16
b1100010100 8
b1001010100 9
b11111111111111111111111101100000 :
b0 ;
b1 <
b11 =
b100 >
b10101 ?
b10101 @
1A
b1001010100 C
b101011 E
b11101 F
#225000000
0!
b11101 $
0&
b11101 )
b11101 1
06
0A
b11101 D
#230000000
1!
b1001110100 %
1&
b1001110100 *
b1111101101 +
b10110110100111 ,
b1100010111100110 -
b1101111110 .
b1101111110 /
b1001110100 0
b1101111110 2
b1101111110 5
16
b1101111110 8
b1001110100 9
b11111111111111111111111011011100 :
b1 ;
b10 <
b100 =
b101 >
b10110 ?
b10110 @
1A
b1001110100 C
b1010101 E
b101011 F
#235000000
0!
b101011 $
0&
b101011 )
b101011 1
06
0A
b101011 D
#240000000
1!
b1001011010 %
1&
b1001011010 *
b10001100001 +
b10111110100001 ,
b1011110101110000 -
b1111101101 .
b1111101101 /
b1001011010 0
b1111101101 2
b1111101101 5
16
b1111101101 8
b1001011010 9
b11111111111111111111111111011000 :
b10 ;
b11 <
b101 =
b110 >
b10111 ?
b10111 @
1A
b1001011010 C
b1100101 E
b1010101 F
#245000000
0!
b1010101 $
0&
b1010101 )
b1010101 1
06
0A
b1010101 D
#250000000
1!
b1111000101 %
1&
b1111000101 *
b10011011010 +
b11000110000101 ,
b1011010011110100 -
b10001100001 .
b10001100001 /
b1111000101 0
b10001100001 2
b10001100001 5
16
b10001100001 8
b1111000101 9
b11010100 :
b0 ;
b100 <
b110 =
b111 >
b11000 ?
b11000 @
1A
b1111000101 C
b10001000 E
b1100101 F
#255000000
0!
b1100101 $
0&
b1100101 )
b1100101 1
06
0A
b1100101 D
#260000000
1!
b10100110101 %
1&
b10100110101 *
b10101011000 +
b11001101010100 ,
b1010110001110010 -
b10011011010 .
b10011011010 /
b10100110101 0
b10011011010 2
b10011011010 5
16
b10011011010 8
b10100110101 9
b1010000 :
b1 ;
b0 <
b111 =
b1000 >
b11001 ?
b11001 @
1A
b10100110101 C
b10111011 E
b10001000 F
#265000000
0!
b10001000 $
0&
b10001000 )
b10001000 1
06
0A
b10001000 D
#270000000
1!
b10100101010 %
1&
b10100101010 *
b10111011011 +
b11010100001101 ,
b1010001111101000 -
b10101011000 .
b10101011000 /
b10100101010 0
b10101011000 2
b10101011000 5
16
b10101011000 8
b10100101010 9
b1100 :
b10 ;
b1 <
b1000 =
b1001 >
b11010 ?
b11010 @
1A
b10100101010 C
b11111111 E
b10111011 F
#275000000
0!
b10111011 $
0&
b10111011 )
b10111011 1
06
0A
b10111011 D
#280000000
1!
b10101100100 %
1&
b10101100100 *
b11001100010 +
b11011010110000 ,
b1001101101011000 -
b10111011011 .
b10111011011 /
b10101100100 0
b10111011011 2
b10111011011 5
16
b10111011011 8
b10101100100 9
b100001000 :
b0 ;
b10 <
b0 =
b1010 >
b11011 ?
b11011 @
1A
b10101100100 C
b100101100 E
b11111111 F
#285000000
0!
b11111111 $
0&
b11111111 )
b11111111 1
06
0A
b11111111 D
#290000000
1!
b11011100011 %
1&
b11011100011 *
b11011101110 +
b11100000111101 ,
b1001001011001100 -
b11001100010 .
b11001100010 /
b11011100011 0
b11001100010 2
b11001100010 5
16
b11001100010 8
b11011100011 9
b11111111111111111111111101100100 :
b1 ;
b11 <
b1 =
b1011 >
b11100 ?
b11100 @
1A
b11011100011 C
b101101111 E
b100101100 F
#295000000
0!
b100101100 $
0&
b100101100 )
b100101100 1
06
0A
b100101100 D
#300000000
1!
b10111000110 %
1&
b10111000110 *
b11101111101 +
b11100110110100 ,
b1000101000111010 -
b11011101110 .
b11011101110 /
b10111000110 0
b11011101110 2
b11011101110 5
16
b11011101110 8
b10111000110 9
b1100000 :
b10 ;
b100 <
b10 =
b1100 >
b11101 ?
b11101 @
1A
b10111000110 C
b110111110 E
b101101111 F
#305000000
0!
b101101111 $
0&
b101101111 )
b101101111 1
06
0A
b101101111 D
#310000000
1!
b11101001110 %
1&
b11101001110 *
b100000010000 +
b11101100010101 ,
b1000000110110110 -
b11101111101 .
b11101111101 /
b11101001110 0
b11101111101 2
b11101111101 5
16
b11101111101 8
b11101001110 9
b101011100 :
b0 ;
b0 <
b11 =
b1101 >
b11110 ?
b11110 @
1A
b11101001110 C
b111011110 E
b110111110 F
#315000000
0!
b110111110 $
0&
b110111110 )
b110111110 1
06
0A
b110111110 D
#320000000
1!
b100011011001 %
1&
b100011011001 *
b100010100111 +
b11110001100001 ,
b111100100110110 -
b100000010000 .
b100000010000 /
b100011011001 0
b100000010000 2
b100000010000 5
16
b100000010000 8
b100011011001 9
b11111111111111111111111110011000 :
b1 ;
b1 <
b100 =
b1110 >
b11111 ?
b11111 @
1A
b100011011001 C
b1001001100 E
b111011110 F
#325000000
0!
b111011110 $
0&
b111011110 )
b111011110 1
06
0A
b111011110 D
#330000000
1!
b11110101000 %
1&
b11110101000 *
b100101000001 +
b11110110010111 ,
b111000010111000 -
b100010100111 .
b100010100111 /
b11110101000 0
b100010100111 2
b100010100111 5
16
b100010100111 8
b11110101000 9
b10010100 :
b10 ;
b10 <
b101 =
b1111 >
b100000 ?
b100000 @
1A
b11110101000 C
b1010010000 E
b1001001100 F
#335000000
0!
b1001001100 $
0&
b1001001100 )
b1001001100 1
06
0A
b1001001100 D
#340000000
1!
b100100111011 %
1&
b100100111011 *
b100111011110 +
b11111010110111 ,
b110100001001000 -
b100101000001 .
b100101000001 /
b100100111011 0
b100101000001 2
b100101000001 5
16
b100101000001 8
b100100111011 9
b110010000 :
b0 ;
b11 <
b110 =
b10000 >
b0 ?
b100001 @
1A
b100100111011 C
b1011010101 E
b1010010000 F
#345000000
0!
b1010010000 $
0&
b1010010000 )
b1010010000 1
06
0A
b1010010000 D
#350000000
1!
b101011010001 %
1&
b101011010001 *
b101001111110 +
b11111111000001 ,
b101111111100110 -
b100111011110 .
b100111011110 /
b101011010001 0
b100111011110 2
b100111011110 5
16
b100111011110 8
b101011010001 9
b100 :
b1 ;
b100 <
b111 =
b0 >
b1 ?
b100010 @
1A
b101011010001 C
b1100111010 E
b1011010101 F
#355000000
0!
b1011010101 $
0&
b1011010101 )
b1011010101 1
06
0A
b1011010101 D
#360000000
1!
b100111100010 %
1&
b100111100010 *
b101100100001 +
b100000010110110 ,
b101011110010010 -
b101001111110 .
b101001111110 /
b100111100010 0
b101001111110 2
b101001111110 5
16
b101001111110 8
b100111100010 9
b11111111111111111111111111110000 :
b10 ;
b0 <
b1000 =
b1 >
b10 ?
b100011 @
1A
b100111100010 C
b1110100001 E
b1100111010 F
#365000000
0!
b1100111010 $
0&
b1100111010 )
b1100111010 1
06
0A
b1100111010 D
#370000000
1!
b101001101110 %
1&
b101001101110 *
b101111000110 +
b100000110010110 ,
b100111101001010 -
b101100100001 .
b101100100001 /
b101001101110 0
b101100100001 2
b101100100001 5
16
b101100100001 8
b101001101110 9
b11111111111111111111111110101100 :
b0 ;
b1 <
b0 =
b10 >
b11 ?
b100100 @
1A
b101001101110 C
b1111100100 E
b1110100001 F
#375000000
0!
b1110100001 $
0&
b1110100001 )
b1110100001 1
06
0A
b1110100001 D
#380000000
1!
b101011001101 %
1&
b101011001101 *
b110001101101 +
b100001001100000 ,
b100011100011000 -
b101111000110 .
b101111000110 /
b101011001101 0
b101111000110 2
b101111000110 5
16
b101111000110 8
b101011001101 9
b11111111111111111111111000001000 :
b1 ;
b10 <
b1 =
b11 >
b100 ?
b100101 @
1A
b101011001101 C
b10001001111 E
b1111100100 F
#385000000
0!
b1111100100 $
0&
b1111100100 )
b1111100100 1
06
0A
b1111100100 D
#390000000
1!
b100111001110 %
1&
b100111001110 *
b110100010110 +
b100001100010110 ,
b11111011111110 -
b110001101101 .
b110001101101 /
b100111001110 0
b110001101101 2
b110001101101 5
16
b110001101101 8
b100111001110 9
b11111111111111111111111100000100 :
b10 ;
b11 <
b10 =
b100 >
b101 ?
b100110 @
1A
b100111001110 C
b10010010100 E
b10001001111 F
#395000000
0!
b10001001111 $
0&
b10001001111 )
b10001001111 1
06
0A
b10001001111 D
#400000000
1!
b101101110001 %
1&
b101101110001 *
b110111000001 +
b100001110110111 ,
b11011011111000 -
b110100010110 .
b110100010110 /
b101101110001 0
b110100010110 2
b110100010110 5
16
b110100010110 8
b101101110001 9
b0 :
b0 ;
b100 <
b11 =
b101 >
b110 ?
b100111 @
1A
b101101110001 C
b10011011011 E
b10010010100 F
#405000000
0!
b10010010100 $
0&
b10010010100 )
b10010010100 1
06
0A
b10010010100 D
#410000000
1!
b110100010110 %
1&
b110100010110 *
b111001101110 +
b100010001000011 ,
b10111100001000 -
b110111000001 .
b110111000001 /
b110100010110 0
b110111000001 2
b110111000001 5
16
b110111000001 8
b110100010110 9
b11111111111111111111111101111100 :
b1 ;
b0 <
b100 =
b110 >
b111 ?
b101000 @
1A
b110100010110 C
b10101000011 E
b10011011011 F
#415000000
0!
b10011011011 $
0&
b10011011011 )
b10011011011 1
06
0A
b10011011011 D
#420000000
1!
b110100111101 %
1&
b110100111101 *
b111100011100 +
b100010010111011 ,
b10011100101110 -
b111001101110 .
b111001101110 /
b110100111101 0
b111001101110 2
b111001101110 5
16
b111001101110 8
b110100111101 9
b11111111111111111111111100111000 :
b10 ;
b1 <
b101 =
b111 >
b1000 ?
b101001 @
1A
b110100111101 C
b10110101101 E
b10101000011 F
