src/p1_2nd_module_design/src/main_integer.vhd
library IEEE;
use IEEE.STD_LOGIC_1164.ALL;
use IEEE.NUMERIC_STD.ALL;


-- Declare the entity
entity Main is
    Port (
        clk   : in  std_logic;   -- Clock input
        rst   : in  std_logic;   -- Reset input
        u     : in  integer;     -- Input integer
        y     : out integer      -- Output scaled integer
    );
end Main;

-- Define the architecture
architecture Behavioral of Main is

    signal s_y : integer := 0;   -- Intermediate signal to store scaled value
    signal s_dy : integer := 0;   -- Intermediate signal to store scaled value
    signal s_ddy : integer := 0;   -- Intermediate signal to store scaled value

    constant SCALE_VALUE : integer := 8192; -- Scaled Value to Represent 1
    constant SCALE_DT : integer := 100; -- Scaled Value to Represent 1

    constant MAX_VALUE : integer := 65536;  -- Maximum value to saturate
    constant MIN_VALUE : integer := -65536;  -- Maximum value to saturate

    constant b2 : integer := 1 * SCALE_VALUE;
    constant b1 : integer := 2 * SCALE_VALUE;
    constant b0 : integer := 10 * SCALE_VALUE;

    constant a0 : integer := 4 * SCALE_VALUE;

begin
    -- Process for scaling the input
    process(clk, rst)
    begin
        -- If reset is asserted, reset the scaled output
        if rst = '1' then
            s_y <= 0;
            s_dy <= 0;
            s_ddy <= 0;

        -- Else if rising edge of the clock
        elsif rising_edge(clk) then
            s_ddy <= (u) * (a0 / b2) - s_dy * (b1 / b2) - s_y * (b0 / b2);
            s_dy  <= s_dy + s_ddy / SCALE_DT;
            s_y  <= s_y + s_dy / SCALE_DT;

        -- Saturate the result if it goes beyond the maximum or minimum value
        if s_y > MAX_VALUE then
            s_y <= MAX_VALUE;
        elsif s_y < MIN_VALUE then
            s_y <= MIN_VALUE;
        end if;

        end if;
    end process;

    -- Assign the scaled output to the output port
    y <= s_y;
end Behavioral;

src/p1_2nd_module_design/test/main_testbench.vhd
library IEEE;
use IEEE.STD_LOGIC_1164.ALL;
use IEEE.NUMERIC_STD.ALL;

entity Main_tb is
end Main_tb;

architecture testbench of Main_tb is
    -- Component declaration for the DUT (Design Under Test)
    component Main
        Port (
            clk   : in  std_logic;   -- Clock input
            rst   : in  std_logic;   -- Reset input
            u     : in  integer;     -- Input integer
            y     : out integer      -- Output scaled integer
        );
    end component;

    -- Test signals
    signal clk_tb   : std_logic := '0';   -- Test bench clock signal
    signal rst_tb   : std_logic := '0';   -- Test bench reset signal
    signal u_tb     : integer := 0;       -- Test bench input signal
    signal y_tb     : integer;            -- Test bench output signal

begin
    -- Instantiate the DUT
    dut : Main
        port map (
            clk => clk_tb,
            rst => rst_tb,
            u   => u_tb,
            y   => y_tb
        );

    -- Clock process
    clk_process : process
    begin
        while now < 6200 ns loop  -- Run for 1000 ns
            clk_tb <= not clk_tb;  -- Toggle clock every half period
            wait for 5 ns;         -- Wait for half period
        end loop;
        wait;  -- Stop simulation
    end process;

    -- Stimulus process
    stimulus : process
    begin
        u_tb <= 0;
        rst_tb <= '1';   -- Assert reset

        wait for 20 ns;
        u_tb <= 0;
        rst_tb <= '0';   -- Deassert reset

        wait for 20 ns;  -- u(t) = 0
        u_tb <= 0;

        wait for 20 ns;   -- u(t) = 1
        u_tb <= 8192;

        wait;  -- Stop simulation
    end process;
end testbench;

src/p1_2nd_module_design/test/main_wave.vcd
$date
  Wed May  8 19:20:36 2024
$end
$version
  GHDL v0
$end
$timescale
  1 fs
$end
$scope module standard $end
$upscope $end
$scope module std_logic_1164 $end
$upscope $end
$scope module numeric_std $end
$upscope $end
$scope module main_tb $end
$var reg 1 ! clk_tb $end
$var reg 1 " rst_tb $end
$var integer 32 # u_tb $end
$var integer 32 $ y_tb $end
$scope module dut $end
$var reg 1 % clk $end
$var reg 1 & rst $end
$var integer 32 ' u $end
$var integer 32 ( y $end
$var integer 32 ) s_y $end
$var integer 32 * s_dy $end
$var integer 32 + s_ddy $end
$upscope $end
$upscope $end
$enddefinitions $end
#0
1!
1"
b0 #
b0 $
1%
1&
b0 '
b0 (
b0 )
b0 *
b0 +
#5000000
0!
0%
#10000000
1!
1%
#15000000
0!
0%
#20000000
1!
0"
1%
0&
#25000000
0!
0%
#30000000
1!
1%
#35000000
0!
0%
#40000000
1!
1%
#45000000
0!
0%
#50000000
1!
1%
#55000000
0!
0%
#60000000
1!
b10000000000000 #
1%
b10000000000000 '
b1000000000000000 +
#65000000
0!
0%
#70000000
1!
1%
b101000111 *
#75000000
0!
0%
#80000000
1!
b11 $
1%
b11 (
b11 )
b1010001110 *
b111111010111001 +
#85000000
0!
0%
#90000000
1!
b1001 $
1%
b1001 (
b1001 )
b1111010010 *
b111110101010100 +
#95000000
0!
0%
#100000000
1!
b10010 $
1%
b10010 (
b10010 )
b10100010010 *
b111101111010100 +
#105000000
0!
0%
#110000000
1!
b11110 $
1%
b11110 (
b11110 )
b11001001111 *
b111101000111010 +
#115000000
0!
0%
#120000000
1!
b101110 $
1%
b101110 (
b101110 )
b11110000111 *
b111100010000101 +
#125000000
0!
0%
#130000000
1!
b1000001 $
1%
b1000001 (
b1000001 )
b100010111011 *
b111011010101101 +
#135000000
0!
0%
#140000000
1!
b1010111 $
1%
b1010111 (
b1010111 )
b100111101010 *
b111010010111011 +
#145000000
0!
0%
#150000000
1!
b1110000 $
1%
b1110000 (
b1110000 )
b101100010100 *
b111001010110000 +
#155000000
0!
0%
#160000000
1!
b10001100 $
1%
b10001100 (
b10001100 )
b110000111001 *
b111000010001100 +
#165000000
0!
0%
#170000000
1!
b10101011 $
1%
b10101011 (
b10101011 )
b110101011001 *
b110111001001111 +
#175000000
0!
0%
#180000000
1!
b11001101 $
1%
b11001101 (
b11001101 )
b111001110011 *
b110101111111001 +
#185000000
0!
0%
#190000000
1!
b11110001 $
1%
b11110001 (
b11110001 )
b111110000111 *
b110100110001011 +
#195000000
0!
0%
#200000000
1!
b100011000 $
1%
b100011000 (
b100011000 )
b1000010010101 *
b110011100001111 +
#205000000
0!
0%
#210000000
1!
b101000010 $
1%
b101000010 (
b101000010 )
b1000110011100 *
b110010001111011 +
#215000000
0!
0%
#220000000
1!
b101101111 $
1%
b101101111 (
b101101111 )
b1001010011101 *
b110000111010000 +
#225000000
0!
0%
#230000000
1!
b110011110 $
1%
b110011110 (
b110011110 )
b1001110010111 *
b101111100001101 +
#235000000
0!
0%
#240000000
1!
b111010000 $
1%
b111010000 (
b111010000 )
b1010010001010 *
b101110000111101 +
#245000000
0!
0%
#250000000
1!
b1000000100 $
1%
b1000000100 (
b1000000100 )
b1010101110110 *
b101100101010110 +
#255000000
0!
0%
#260000000
1!
b1000111010 $
1%
b1000111010 (
b1000111010 )
b1011001011010 *
b101011001100010 +
#265000000
0!
0%
#270000000
1!
b1001110011 $
1%
b1001110011 (
b1001110011 )
b1011100110111 *
b101001101100010 +
#275000000
0!
0%
#280000000
1!
b1010101110 $
1%
b1010101110 (
b1010101110 )
b1100000001100 *
b101000001001011 +
#285000000
0!
0%
#290000000
1!
b1011101011 $
1%
b1011101011 (
b1011101011 )
b1100011011001 *
b100110100101000 +
#295000000
0!
0%
#300000000
1!
b1100101010 $
1%
b1100101010 (
b1100101010 )
b1100110011110 *
b100100111111001 +
#305000000
0!
0%
#310000000
1!
b1101101011 $
1%
b1101101011 (
b1101101011 )
b1101001011011 *
b100011010111110 +
#315000000
0!
0%
#320000000
1!
b1110101110 $
1%
b1110101110 (
b1110101110 )
b1101100010000 *
b100001101110111 +
#325000000
0!
0%
#330000000
1!
b1111110011 $
1%
b1111110011 (
b1111110011 )
b1101110111100 *
b100000000100100 +
#335000000
0!
0%
#340000000
1!
b10000111010 $
1%
b10000111010 (
b10000111010 )
b1110001100000 *
b11110011000110 +
#345000000
0!
0%
#350000000
1!
b10010000010 $
1%
b10010000010 (
b10010000010 )
b1110011111011 *
b11100101011100 +
#355000000
0!
0%
#360000000
1!
b10011001100 $
1%
b10011001100 (
b10011001100 )
b1110110001101 *
b11010111110001 +
#365000000
0!
0%
#370000000
1!
b10100010111 $
1%
b10100010111 (
b10100010111 )
b1111000010111 *
b11001001111011 +
#375000000
0!
0%
#380000000
1!
b10101100100 $
1%
b10101100100 (
b10101100100 )
b1111010011000 *
b10111100000011 +
#385000000
0!
0%
#390000000
1!
b10110110010 $
1%
b10110110010 (
b10110110010 )
b1111100010000 *
b10101110000000 +
#395000000
0!
0%
#400000000
1!
b11000000001 $
1%
b11000000001 (
b11000000001 )
b1111101111111 *
b10011111111100 +
#405000000
0!
0%
#410000000
1!
b11001010001 $
1%
b11001010001 (
b11001010001 )
b1111111100101 *
b10010001110111 +
#415000000
0!
0%
#420000000
1!
b11010100010 $
1%
b11010100010 (
b11010100010 )
b10000001000010 *
b10000011110001 +
#425000000
0!
0%
#430000000
1!
b11011110100 $
1%
b11011110100 (
b11011110100 )
b10000010010110 *
b1110101101010 +
#435000000
0!
0%
#440000000
1!
b11101000111 $
1%
b11101000111 (
b11101000111 )
b10000011100001 *
b1100111100010 +
#445000000
0!
0%
#450000000
1!
b11110011011 $
1%
b11110011011 (
b11110011011 )
b10000100100011 *
b1011001011001 +
#455000000
0!
0%
#460000000
1!
b11111101111 $
1%
b11111101111 (
b11111101111 )
b10000101011100 *
b1001011001111 +
#465000000
0!
0%
#470000000
1!
b100001000100 $
1%
b100001000100 (
b100001000100 )
b10000110001100 *
b111101001110 +
#475000000
0!
0%
#480000000
1!
b100010011001 $
1%
b100010011001 (
b100010011001 )
b10000110110011 *
b101111001100 +
#485000000
0!
0%
#490000000
1!
b100011101111 $
1%
b100011101111 (
b100011101111 )
b10000111010001 *
b100001010011 +
#495000000
0!
0%
#500000000
1!
b100101000101 $
1%
b100101000101 (
b100101000101 )
b10000111100110 *
b10011011001 +
#505000000
0!
0%
#510000000
1!
b100110011011 $
1%
b100110011011 (
b100110011011 )
b10000111110010 *
b101101000 +
#515000000
0!
0%
#520000000
1!
b100111110001 $
1%
b100111110001 (
b100111110001 )
b10000111110101 *
b11111111111111111111111000000000 +
#525000000
0!
0%
#530000000
1!
b101001000111 $
1%
b101001000111 (
b101001000111 )
b10000111110000 *
b11111111111111111111101010100001 +
#535000000
0!
0%
#540000000
1!
b101010011101 $
1%
b101010011101 (
b101010011101 )
b10000111100011 *
b11111111111111111111011101001010 +
#545000000
0!
0%
#550000000
1!
b101011110011 $
1%
b101011110011 (
b101011110011 )
b10000111001101 *
b11111111111111111111001111111011 +
#555000000
0!
0%
#560000000
1!
b101101001001 $
1%
b101101001001 (
b101101001001 )
b10000110101111 *
b11111111111111111111000010110101 +
#565000000
0!
0%
#570000000
1!
b101110011111 $
1%
b101110011111 (
b101110011111 )
b10000110001000 *
b11111111111111111110110101110111 +
#575000000
0!
0%
#580000000
1!
b101111110100 $
1%
b101111110100 (
b101111110100 )
b10000101011001 *
b11111111111111111110101001000010 +
#585000000
0!
0%
#590000000
1!
b110001001001 $
1%
b110001001001 (
b110001001001 )
b10000100100010 *
b11111111111111111110011100011111 +
#595000000
0!
0%
#600000000
1!
b110010011101 $
1%
b110010011101 (
b110010011101 )
b10000011100011 *
b11111111111111111110010000000100 +
#605000000
0!
0%
#610000000
1!
b110011110001 $
1%
b110011110001 (
b110011110001 )
b10000010011100 *
b11111111111111111110000011111011 +
#615000000
0!
0%
#620000000
1!
b110101000100 $
1%
b110101000100 (
b110101000100 )
b10000001001101 *
b11111111111111111101110111111010 +
#625000000
0!
0%
#630000000
1!
b110110010110 $
1%
b110110010110 (
b110110010110 )
b1111111110110 *
b11111111111111111101101100001011 +
#635000000
0!
0%
#640000000
1!
b110111100111 $
1%
b110111100111 (
b110111100111 )
b1111110011000 *
b11111111111111111101100000101110 +
#645000000
0!
0%
#650000000
1!
b111000110111 $
1%
b111000110111 (
b111000110111 )
b1111100110011 *
b11111111111111111101010101100010 +
#655000000
0!
0%
#660000000
1!
b111010000110 $
1%
b111010000110 (
b111010000110 )
b1111011000110 *
b11111111111111111101001010100111 +
#665000000
0!
0%
#670000000
1!
b111011010100 $
1%
b111011010100 (
b111011010100 )
b1111001010010 *
b11111111111111111100111111111110 +
#675000000
0!
0%
#680000000
1!
b111100100001 $
1%
b111100100001 (
b111100100001 )
b1110111011000 *
b11111111111111111100110101100110 +
#685000000
0!
0%
#690000000
1!
b111101101101 $
1%
b111101101101 (
b111101101101 )
b1110101010111 *
b11111111111111111100101011011110 +
#695000000
0!
0%
#700000000
1!
b111110111000 $
1%
b111110111000 (
b111110111000 )
b1110011001111 *
b11111111111111111100100001100111 +
#705000000
0!
0%
#710000000
1!
b1000000000001 $
1%
b1000000000001 (
b1000000000001 )
b1110001000001 *
b11111111111111111100011000000001 +
#715000000
0!
0%
#720000000
1!
b1000001001001 $
1%
b1000001001001 (
b1000001001001 )
b1101110101101 *
b11111111111111111100001110110101 +
#725000000
0!
0%
#730000000
1!
b1000010001111 $
1%
b1000010001111 (
b1000010001111 )
b1101100010011 *
b11111111111111111100000101111001 +
#735000000
0!
0%
#740000000
1!
b1000011010100 $
1%
b1000011010100 (
b1000011010100 )
b1101001110011 *
b11111111111111111011111101010111 +
#745000000
0!
0%
#750000000
1!
b1000100010111 $
1%
b1000100010111 (
b1000100010111 )
b1100111001110 *
b11111111111111111011110101000101 +
#755000000
0!
0%
#760000000
1!
b1000101011001 $
1%
b1000101011001 (
b1000101011001 )
b1100100100100 *
b11111111111111111011101101001100 +
#765000000
0!
0%
#770000000
1!
b1000110011001 $
1%
b1000110011001 (
b1000110011001 )
b1100001110101 *
b11111111111111111011100101100010 +
#775000000
0!
0%
#780000000
1!
b1000111010111 $
1%
b1000111010111 (
b1000111010111 )
b1011111000001 *
b11111111111111111011011110010001 +
#785000000
0!
0%
#790000000
1!
b1001000010011 $
1%
b1001000010011 (
b1001000010011 )
b1011100001000 *
b11111111111111111011010111011001 +
#795000000
0!
0%
#800000000
1!
b1001001001101 $
1%
b1001001001101 (
b1001001001101 )
b1011001001011 *
b11111111111111111011010000111010 +
#805000000
0!
0%
#810000000
1!
b1001010000110 $
1%
b1001010000110 (
b1001010000110 )
b1010110001010 *
b11111111111111111011001010110011 +
#815000000
0!
0%
#820000000
1!
b1001010111101 $
1%
b1001010111101 (
b1001010111101 )
b1010011000101 *
b11111111111111111011000100111010 +
#825000000
0!
0%
#830000000
1!
b1001011110010 $
1%
b1001011110010 (
b1001011110010 )
b1001111111100 *
b11111111111111111010111111011001 +
#835000000
0!
0%
#840000000
1!
b1001100100101 $
1%
b1001100100101 (
b1001100100101 )
b1001100101111 *
b11111111111111111010111010010000 +
#845000000
0!
0%
#850000000
1!
b1001101010110 $
1%
b1001101010110 (
b1001101010110 )
b1001001011111 *
b11111111111111111010110101011111 +
#855000000
0!
0%
#860000000
1!
b1001110000101 $
1%
b1001110000101 (
b1001110000101 )
b1000110001100 *
b11111111111111111010110001000101 +
#865000000
0!
0%
#870000000
1!
b1001110110001 $
1%
b1001110110001 (
b1001110110001 )
b1000010110110 *
b11111111111111111010101101000010 +
#875000000
0!
0%
#880000000
1!
b1001111011011 $
1%
b1001111011011 (
b1001111011011 )
b111111011110 *
b11111111111111111010101001100000 +
#885000000
0!
0%
#890000000
1!
b1010000000011 $
1%
b1010000000011 (
b1010000000011 )
b111100000011 *
b11111111111111111010100110010100 +
#895000000
0!
0%
#900000000
1!
b1010000101001 $
1%
b1010000101001 (
b1010000101001 )
b111000100110 *
b11111111111111111010100011011111 +
#905000000
0!
0%
#910000000
1!
b1010001001101 $
1%
b1010001001101 (
b1010001001101 )
b110101000111 *
b11111111111111111010100001000000 +
#915000000
0!
0%
#920000000
1!
b1010001101110 $
1%
b1010001101110 (
b1010001101110 )
b110001100111 *
b11111111111111111010011110110111 +
#925000000
0!
0%
#930000000
1!
b1010010001101 $
1%
b1010010001101 (
b1010010001101 )
b101110000101 *
b11111111111111111010011101001101 +
#935000000
0!
0%
#940000000
1!
b1010010101010 $
1%
b1010010101010 (
b1010010101010 )
b101010100010 *
b11111111111111111010011011111001 +
#945000000
0!
0%
#950000000
1!
b1010011000101 $
1%
b1010011000101 (
b1010011000101 )
b100110111111 *
b11111111111111111010011010111010 +
#955000000
0!
0%
#960000000
1!
b1010011011101 $
1%
b1010011011101 (
b1010011011101 )
b100011011011 *
b11111111111111111010011010001111 +
#965000000
0!
0%
#970000000
1!
b1010011110011 $
1%
b1010011110011 (
b1010011110011 )
b11111110111 *
b11111111111111111010011010000011 +
#975000000
0!
0%
#980000000
1!
b1010100000111 $
1%
b1010100000111 (
b1010100000111 )
b11100010010 *
b11111111111111111010011010001011 +
#985000000
0!
0%
#990000000
1!
b1010100011001 $
1%
b1010100011001 (
b1010100011001 )
b11000101101 *
b11111111111111111010011010101000 +
#995000000
0!
0%
#1000000000
1!
b1010100101000 $
1%
b1010100101000 (
b1010100101000 )
b10101001001 *
b11111111111111111010011011011001 +
#1005000000
0!
0%
#1010000000
1!
b1010100110101 $
1%
b1010100110101 (
b1010100110101 )
b10001100101 *
b11111111111111111010011100100111 +
#1015000000
0!
0%
#1020000000
1!
b1010101000000 $
1%
b1010101000000 (
b1010101000000 )
b1110000010 *
b11111111111111111010011110001001 +
#1025000000
0!
0%
#1030000000
1!
b1010101001000 $
1%
b1010101001000 (
b1010101001000 )
b1010100000 *
b11111111111111111010011111111110 +
#1035000000
0!
0%
#1040000000
1!
b1010101001110 $
1%
b1010101001110 (
b1010101001110 )
b110111111 *
b11111111111111111010100010010000 +
#1045000000
0!
0%
#1050000000
1!
b1010101010010 $
1%
b1010101010010 (
b1010101010010 )
b11100000 *
b11111111111111111010100100110101 +
#1055000000
0!
0%
#1060000000
1!
b1010101010100 $
1%
b1010101010100 (
b1010101010100 )
b10 *
b11111111111111111010100111101100 +
#1065000000
0!
0%
#1070000000
1!
1%
b11111111111111111111111100100110 *
b11111111111111111010101010110110 +
#1075000000
0!
0%
#1080000000
1!
b1010101010010 $
1%
b1010101010010 (
b1010101010010 )
b11111111111111111111111001001100 *
b11111111111111111010101110010010 +
#1085000000
0!
0%
#1090000000
1!
b1010101001110 $
1%
b1010101001110 (
b1010101001110 )
b11111111111111111111110101110100 *
b11111111111111111010110010000000 +
#1095000000
0!
0%
#1100000000
1!
b1010101001000 $
1%
b1010101001000 (
b1010101001000 )
b11111111111111111111110010011111 *
b11111111111111111010110110000000 +
#1105000000
0!
0%
#1110000000
1!
b1010101000000 $
1%
b1010101000000 (
b1010101000000 )
b11111111111111111111101111001100 *
b11111111111111111010111010010001 +
#1115000000
0!
0%
#1120000000
1!
b1010100110110 $
1%
b1010100110110 (
b1010100110110 )
b11111111111111111111101011111100 *
b11111111111111111010111110110100 +
#1125000000
0!
0%
#1130000000
1!
b1010100101010 $
1%
b1010100101010 (
b1010100101010 )
b11111111111111111111101000101111 *
b11111111111111111011000011101000 +
#1135000000
0!
0%
#1140000000
1!
b1010100011100 $
1%
b1010100011100 (
b1010100011100 )
b11111111111111111111100101100101 *
b11111111111111111011001000101101 +
#1145000000
0!
0%
#1150000000
1!
b1010100001100 $
1%
b1010100001100 (
b1010100001100 )
b11111111111111111111100010011110 *
b11111111111111111011001110000011 +
#1155000000
0!
0%
#1160000000
1!
b1010011111010 $
1%
b1010011111010 (
b1010011111010 )
b11111111111111111111011111011011 *
b11111111111111111011010011101010 +
#1165000000
0!
0%
#1170000000
1!
b1010011100110 $
1%
b1010011100110 (
b1010011100110 )
b11111111111111111111011100011011 *
b11111111111111111011011001100001 +
#1175000000
0!
0%
#1180000000
1!
b1010011010000 $
1%
b1010011010000 (
b1010011010000 )
b11111111111111111111011001011111 *
b11111111111111111011011111101001 +
#1185000000
0!
0%
#1190000000
1!
b1010010111000 $
1%
b1010010111000 (
b1010010111000 )
b11111111111111111111010110100111 *
b11111111111111111011100110000001 +
#1195000000
0!
0%
#1200000000
1!
b1010010011110 $
1%
b1010010011110 (
b1010010011110 )
b11111111111111111111010011110011 *
b11111111111111111011101100101001 +
#1205000000
0!
0%
#1210000000
1!
b1010010000010 $
1%
b1010010000010 (
b1010010000010 )
b11111111111111111111010001000011 *
b11111111111111111011110011100001 +
#1215000000
0!
0%
#1220000000
1!
b1010001100100 $
1%
b1010001100100 (
b1010001100100 )
b11111111111111111111001110011000 *
b11111111111111111011111010101001 +
#1225000000
0!
0%
#1230000000
1!
b1010001000101 $
1%
b1010001000101 (
b1010001000101 )
b11111111111111111111001011110001 *
b11111111111111111100000010000000 +
#1235000000
0!
0%
#1240000000
1!
b1010000100100 $
1%
b1010000100100 (
b1010000100100 )
b11111111111111111111001001001111 *
b11111111111111111100001001011101 +
#1245000000
0!
0%
#1250000000
1!
b1010000000001 $
1%
b1010000000001 (
b1010000000001 )
b11111111111111111111000110110010 *
b11111111111111111100010001001001 +
#1255000000
0!
0%
#1260000000
1!
b1001111011101 $
1%
b1001111011101 (
b1001111011101 )
b11111111111111111111000100011010 *
b11111111111111111100011001000100 +
#1265000000
0!
0%
#1270000000
1!
b1001110110111 $
1%
b1001110110111 (
b1001110110111 )
b11111111111111111111000010000111 *
b11111111111111111100100001000100 +
#1275000000
0!
0%
#1280000000
1!
b1001110010000 $
1%
b1001110010000 (
b1001110010000 )
b11111111111111111110111111111001 *
b11111111111111111100101001010011 +
#1285000000
0!
0%
#1290000000
1!
b1001101100111 $
1%
b1001101100111 (
b1001101100111 )
b11111111111111111110111101110000 *
b11111111111111111100110001100111 +
#1295000000
0!
0%
#1300000000
1!
b1001100111101 $
1%
b1001100111101 (
b1001100111101 )
b11111111111111111110111011101100 *
b11111111111111111100111010001010 +
#1305000000
0!
0%
#1310000000
1!
b1001100010010 $
1%
b1001100010010 (
b1001100010010 )
b11111111111111111110111001101110 *
b11111111111111111101000010110010 +
#1315000000
0!
0%
#1320000000
1!
b1001011100110 $
1%
b1001011100110 (
b1001011100110 )
b11111111111111111110110111110101 *
b11111111111111111101001011011110 +
#1325000000
0!
0%
#1330000000
1!
b1001010111000 $
1%
b1001010111000 (
b1001010111000 )
b11111111111111111110110110000010 *
b11111111111111111101010100001111 +
#1335000000
0!
0%
#1340000000
1!
b1001010001001 $
1%
b1001010001001 (
b1001010001001 )
b11111111111111111110110100010101 *
b11111111111111111101011101001110 +
#1345000000
0!
0%
#1350000000
1!
b1001001011001 $
1%
b1001001011001 (
b1001001011001 )
b11111111111111111110110010101101 *
b11111111111111111101100110010001 +
#1355000000
0!
0%
#1360000000
1!
b1001000101000 $
1%
b1001000101000 (
b1001000101000 )
b11111111111111111110110001001011 *
b11111111111111111101101111011001 +
#1365000000
0!
0%
#1370000000
1!
b1000111110110 $
1%
b1000111110110 (
b1000111110110 )
b11111111111111111110101111101111 *
b11111111111111111101111000100101 +
#1375000000
0!
0%
#1380000000
1!
b1000111000011 $
1%
b1000111000011 (
b1000111000011 )
b11111111111111111110101110011001 *
b11111111111111111110000001110101 +
#1385000000
0!
0%
#1390000000
1!
b1000110001111 $
1%
b1000110001111 (
b1000110001111 )
b11111111111111111110101101001001 *
b11111111111111111110001011001001 +
#1395000000
0!
0%
#1400000000
1!
b1000101011010 $
1%
b1000101011010 (
b1000101011010 )
b11111111111111111110101011111111 *
b11111111111111111110010100100001 +
#1405000000
0!
0%
#1410000000
1!
b1000100100101 $
1%
b1000100100101 (
b1000100100101 )
b11111111111111111110101010111011 *
b11111111111111111110011101111101 +
#1415000000
0!
0%
#1420000000
1!
b1000011101111 $
1%
b1000011101111 (
b1000011101111 )
b11111111111111111110101001111101 *
b11111111111111111110100111010011 +
#1425000000
0!
0%
#1430000000
1!
b1000010111000 $
1%
b1000010111000 (
b1000010111000 )
b11111111111111111110101001000101 *
b11111111111111111110110000101101 +
#1435000000
0!
0%
#1440000000
1!
b1000010000001 $
1%
b1000010000001 (
b1000010000001 )
b11111111111111111110101000010011 *
b11111111111111111110111010001011 +
#1445000000
0!
0%
#1450000000
1!
b1000001001001 $
1%
b1000001001001 (
b1000001001001 )
b11111111111111111110100111100111 *
b11111111111111111111000011100011 +
#1455000000
0!
0%
#1460000000
1!
b1000000010001 $
1%
b1000000010001 (
b1000000010001 )
b11111111111111111110100111000001 *
b11111111111111111111001100111111 +
#1465000000
0!
0%
#1470000000
1!
b111111011001 $
1%
b111111011001 (
b111111011001 )
b11111111111111111110100110100001 *
b11111111111111111111010110010101 +
#1475000000
0!
0%
#1480000000
1!
b111110100000 $
1%
b111110100000 (
b111110100000 )
b11111111111111111110100110000111 *
b11111111111111111111011111100101 +
#1485000000
0!
0%
#1490000000
1!
b111101100111 $
1%
b111101100111 (
b111101100111 )
b11111111111111111110100101110011 *
b11111111111111111111101000111001 +
#1495000000
0!
0%
#1500000000
1!
b111100101110 $
1%
b111100101110 (
b111100101110 )
b11111111111111111110100101100101 *
b11111111111111111111110010000111 +
#1505000000
0!
0%
#1510000000
1!
b111011110101 $
1%
b111011110101 (
b111011110101 )
b11111111111111111110100101011101 *
b11111111111111111111111011001111 +
#1515000000
0!
0%
#1520000000
1!
b111010111100 $
1%
b111010111100 (
b111010111100 )
b11111111111111111110100101011010 *
b100010001 +
#1525000000
0!
0%
#1530000000
1!
b111010000011 $
1%
b111010000011 (
b111010000011 )
b11111111111111111110100101011100 *
b1101001110 +
#1535000000
0!
0%
#1540000000
1!
b111001001010 $
1%
b111001001010 (
b111001001010 )
b11111111111111111110100101100100 *
b10110000110 +
#1545000000
0!
0%
#1550000000
1!
b111000010001 $
1%
b111000010001 (
b111000010001 )
b11111111111111111110100101110010 *
b11110111000 +
#1555000000
0!
0%
#1560000000
1!
b110111011000 $
1%
b110111011000 (
b110111011000 )
b11111111111111111110100110000101 *
b100111100100 +
#1565000000
0!
0%
#1570000000
1!
b110110011111 $
1%
b110110011111 (
b110110011111 )
b11111111111111111110100110011110 *
b110000001011 +
#1575000000
0!
0%
#1580000000
1!
b110101100110 $
1%
b110101100110 (
b110101100110 )
b11111111111111111110100110111100 *
b111000101100 +
#1585000000
0!
0%
#1590000000
1!
b110100101101 $
1%
b110100101101 (
b110100101101 )
b11111111111111111110100111100000 *
b1000001001000 +
#1595000000
0!
0%
#1600000000
1!
b110011110101 $
1%
b110011110101 (
b110011110101 )
b11111111111111111110101000001001 *
b1001001011110 +
#1605000000
0!
0%
#1610000000
1!
b110010111101 $
1%
b110010111101 (
b110010111101 )
b11111111111111111110101000111000 *
b1010001100101 +
#1615000000
0!
0%
#1620000000
1!
b110010000110 $
1%
b110010000110 (
b110010000110 )
b11111111111111111110101001101100 *
b1011001100110 +
#1625000000
0!
0%
#1630000000
1!
b110001001111 $
1%
b110001001111 (
b110001001111 )
b11111111111111111110101010100101 *
b1100001011000 +
#1635000000
0!
0%
#1640000000
1!
b110000011001 $
1%
b110000011001 (
b110000011001 )
b11111111111111111110101011100011 *
b1101001000101 +
#1645000000
0!
0%
#1650000000
1!
b101111100011 $
1%
b101111100011 (
b101111100011 )
b11111111111111111110101100100110 *
b1110000100011 +
#1655000000
0!
0%
#1660000000
1!
b101110101110 $
1%
b101110101110 (
b101110101110 )
b11111111111111111110101101101110 *
b1110111111100 +
#1665000000
0!
0%
#1670000000
1!
b101101111010 $
1%
b101101111010 (
b101101111010 )
b11111111111111111110101110111010 *
b1111111000110 +
#1675000000
0!
0%
#1680000000
1!
b101101000111 $
1%
b101101000111 (
b101101000111 )
b11111111111111111110110000001011 *
b10000110000010 +
#1685000000
0!
0%
#1690000000
1!
b101100010100 $
1%
b101100010100 (
b101100010100 )
b11111111111111111110110001100000 *
b10001100101111 +
#1695000000
0!
0%
#1700000000
1!
b101011100010 $
1%
b101011100010 (
b101011100010 )
b11111111111111111110110010111010 *
b10010011011000 +
#1705000000
0!
0%
#1710000000
1!
b101010110001 $
1%
b101010110001 (
b101010110001 )
b11111111111111111110110100011000 *
b10011001110010 +
#1715000000
0!
0%
#1720000000
1!
b101010000001 $
1%
b101010000001 (
b101010000001 )
b11111111111111111110110101111010 *
b10011111111110 +
#1725000000
0!
0%
#1730000000
1!
b101001010010 $
1%
b101001010010 (
b101001010010 )
b11111111111111111110110111100000 *
b10100101111100 +
#1735000000
0!
0%
#1740000000
1!
b101000100100 $
1%
b101000100100 (
b101000100100 )
b11111111111111111110111001001010 *
b10101011101100 +
#1745000000
0!
0%
#1750000000
1!
b100111110111 $
1%
b100111110111 (
b100111110111 )
b11111111111111111110111010110111 *
b10110001001110 +
#1755000000
0!
0%
#1760000000
1!
b100111001011 $
1%
b100111001011 (
b100111001011 )
b11111111111111111110111100101000 *
b10110110100011 +
#1765000000
0!
0%
#1770000000
1!
b100110100000 $
1%
b100110100000 (
b100110100000 )
b11111111111111111110111110011100 *
b10111011101010 +
#1775000000
0!
0%
#1780000000
1!
b100101110111 $
1%
b100101110111 (
b100101110111 )
b11111111111111111111000000010100 *
b11000000100100 +
#1785000000
0!
0%
#1790000000
1!
b100101001111 $
1%
b100101001111 (
b100101001111 )
b11111111111111111111000010001111 *
b11000101000110 +
#1795000000
0!
0%
#1800000000
1!
b100100101000 $
1%
b100100101000 (
b100100101000 )
b11111111111111111111000100001101 *
b11001001011011 +
#1805000000
0!
0%
#1810000000
1!
b100100000010 $
1%
b100100000010 (
b100100000010 )
b11111111111111111111000110001101 *
b11001101100011 +
#1815000000
0!
0%
#1820000000
1!
b100011011110 $
1%
b100011011110 (
b100011011110 )
b11111111111111111111001000010000 *
b11010001011111 +
#1825000000
0!
0%
#1830000000
1!
b100010111011 $
1%
b100010111011 (
b100010111011 )
b11111111111111111111001010010110 *
b11010101000100 +
#1835000000
0!
0%
#1840000000
1!
b100010011001 $
1%
b100010011001 (
b100010011001 )
b11111111111111111111001100011110 *
b11011000011100 +
#1845000000
0!
0%
#1850000000
1!
b100001111001 $
1%
b100001111001 (
b100001111001 )
b11111111111111111111001110101000 *
b11011011101000 +
#1855000000
0!
0%
#1860000000
1!
b100001011010 $
1%
b100001011010 (
b100001011010 )
b11111111111111111111010000110100 *
b11011110011110 +
#1865000000
0!
0%
