src/p1_2nd_module_design/src/main_integer.vhd
library IEEE;
use IEEE.STD_LOGIC_1164.ALL;
use IEEE.NUMERIC_STD.ALL;


-- Declare the entity
entity Main is
    Port (
        clk   : in  std_logic;   -- Clock input
        rst   : in  std_logic;   -- Reset input
        u     : in  integer;     -- Input integer
        y     : out integer      -- Output scaled integer
    );
end Main;

-- Define the architecture
architecture Behavioral of Main is

    signal s_y : integer := 0;   -- Intermediate signal to store scaled value
    signal s_dy : integer := 0;   -- Intermediate signal to store scaled value
    signal s_ddy : integer := 0;   -- Intermediate signal to store scaled value

    constant SCALE_VALUE : integer := 8192; -- Scaled Value to Represent 1
    constant SCALE_DT : integer := 100; -- Scaled Value to Represent 1

    constant MAX_VALUE : integer := 65536;  -- Maximum value to saturate
    constant MIN_VALUE : integer := -65536;  -- Maximum value to saturate

    constant b2 : integer := 1 * SCALE_VALUE;
    constant b1 : integer := 2 * SCALE_VALUE;
    constant b0 : integer := 10 * SCALE_VALUE;

    constant a0 : integer := 4 * SCALE_VALUE;

begin
    -- Process for scaling the input
    process(clk, rst)
    begin
        -- If reset is asserted, reset the scaled output
        if rst = '1' then
            s_y <= 0;
            s_dy <= 0;
            s_ddy <= 0;

        -- Else if rising edge of the clock
        elsif rising_edge(clk) then
            s_ddy <= (u) * (a0 / b2) - s_dy * (b1 / b2) - s_y * (b0 / b2);
            s_dy  <= s_dy + s_ddy / SCALE_DT;
            s_y  <= s_y + s_dy / SCALE_DT;

        -- Saturate the result if it goes beyond the maximum or minimum value
        if s_y > MAX_VALUE then
            s_y <= MAX_VALUE;
        elsif s_y < MIN_VALUE then
            s_y <= MIN_VALUE;
        end if;

        end if;
    end process;

    -- Assign the scaled output to the output port
    y <= s_y;
end Behavioral;

src/p1_2nd_module_design/test/main_testbench.vhd
library IEEE;
use IEEE.STD_LOGIC_1164.ALL;
use IEEE.NUMERIC_STD.ALL;

entity Main_tb is
end Main_tb;

architecture testbench of Main_tb is
    -- Component declaration for the DUT (Design Under Test)
    component Main
        Port (
            clk   : in  std_logic;   -- Clock input
            rst   : in  std_logic;   -- Reset input
            u     : in  integer;     -- Input integer
            y     : out integer      -- Output scaled integer
        );
    end component;

    -- Test signals
    signal clk_tb   : std_logic := '0';   -- Test bench clock signal
    signal rst_tb   : std_logic := '0';   -- Test bench reset signal
    signal u_tb     : integer := 0;       -- Test bench input signal
    signal y_tb     : integer;            -- Test bench output signal

begin
    -- Instantiate the DUT
    dut : Main
        port map (
            clk => clk_tb,
            rst => rst_tb,
            u   => u_tb,
            y   => y_tb
        );

    -- Clock process
    clk_process : process
    begin
        while now < 6200 ns loop  -- Run for 1000 ns
            clk_tb <= not clk_tb;  -- Toggle clock every half period
            wait for 5 ns;         -- Wait for half period
        end loop;
        wait;  -- Stop simulation
    end process;

    -- Stimulus process
    stimulus : process
    begin
        u_tb <= 0;
        rst_tb <= '1';   -- Assert reset

        wait for 20 ns;
        u_tb <= 0;
        rst_tb <= '0';   -- Deassert reset

        wait for 20 ns;  -- u(t) = 0
        u_tb <= 0;

        wait for 20 ns;   -- u(t) = 1
        u_tb <= 8192;

        wait;  -- Stop simulation
    end process;
end testbench;

src/p1_2nd_module_design/test/main_wave.vcd
$date
  Mon May  6 18:47:11 2024
$end
$version
  GHDL v0
$end
$timescale
  1 fs
$end
$scope module standard $end
$upscope $end
$scope module std_logic_1164 $end
$upscope $end
$scope module numeric_std $end
$upscope $end
$scope module main_tb $end
$var reg 1 ! clk_tb $end
$var reg 1 " rst_tb $end
$var integer 32 # u_tb $end
$var integer 32 $ y_tb $end
$scope module dut $end
$var reg 1 % clk $end
$var reg 1 & rst $end
$var integer 32 ' u $end
$var integer 32 ( y $end
$var integer 32 ) s_y $end
$var integer 32 * s_dy $end
$var integer 32 + s_ddy $end
$upscope $end
$upscope $end
$enddefinitions $end
#0
1!
1"
b0 #
b0 $
1%
1&
b0 '
b0 (
b0 )
b0 *
b0 +
#5000000
0!
0%
#10000000
1!
1%
#15000000
0!
0%
#20000000
1!
0"
1%
0&
#25000000
0!
0%
#30000000
1!
1%
#35000000
0!
0%
#40000000
1!
1%
#45000000
0!
0%
#50000000
1!
1%
#55000000
0!
0%
#60000000
1!
b10000000000000 #
1%
b10000000000000 '
b1000000000000000 +
#65000000
0!
0%
#70000000
1!
1%
b101000111 *
#75000000
0!
0%
#80000000
1!
b11 $
1%
b11 (
b11 )
b1010001110 *
b111110101110010 +
#85000000
0!
0%
#90000000
1!
b1001 $
1%
b1001 (
b1001 )
b1111001111 *
b111101011000110 +
#95000000
0!
0%
#100000000
1!
b10010 $
1%
b10010 (
b10010 )
b10100001001 *
b111100000001000 +
#105000000
0!
0%
#110000000
1!
b11110 $
1%
b11110 (
b11110 )
b11000111100 *
b111010100111010 +
#115000000
0!
0%
#120000000
1!
b101101 $
1%
b101101 (
b101101 )
b11101101000 *
b111001001011100 +
#125000000
0!
0%
#130000000
1!
b111111 $
1%
b111111 (
b111111 )
b100010001100 *
b110111101101110 +
#135000000
0!
0%
#140000000
1!
b1010100 $
1%
b1010100 (
b1010100 )
b100110101001 *
b110110001110010 +
#145000000
0!
0%
#150000000
1!
b1101100 $
1%
b1101100 (
b1101100 )
b101010111110 *
b110100101100110 +
#155000000
0!
0%
#160000000
1!
b10000111 $
1%
b10000111 (
b10000111 )
b101111001011 *
b110011001001100 +
#165000000
0!
0%
#170000000
1!
b10100101 $
1%
b10100101 (
b10100101 )
b110011010000 *
b110001100100100 +
#175000000
0!
0%
#180000000
1!
b11000101 $
1%
b11000101 (
b11000101 )
b110111001101 *
b101111111101110 +
#185000000
0!
0%
#190000000
1!
b11101000 $
1%
b11101000 (
b11101000 )
b111011000010 *
b101110010110100 +
#195000000
0!
0%
#200000000
1!
b100001101 $
1%
b100001101 (
b100001101 )
b111110101111 *
b101100101101100 +
#205000000
0!
0%
#210000000
1!
b100110101 $
1%
b100110101 (
b100110101 )
b1000010010011 *
b101011000100000 +
#215000000
0!
0%
#220000000
1!
b101011111 $
1%
b101011111 (
b101011111 )
b1000101101111 *
b101001011001000 +
#225000000
0!
0%
#230000000
1!
b110001011 $
1%
b110001011 (
b110001011 )
b1001001000010 *
b100111101101100 +
#235000000
0!
0%
#240000000
1!
b110111001 $
1%
b110111001 (
b110111001 )
b1001100001101 *
b100110000001110 +
#245000000
0!
0%
#250000000
1!
b111101001 $
1%
b111101001 (
b111101001 )
b1001111001111 *
b100100010101100 +
#255000000
0!
0%
#260000000
1!
b1000011011 $
1%
b1000011011 (
b1000011011 )
b1010010001001 *
b100010101001000 +
#265000000
0!
0%
#270000000
1!
b1001001111 $
1%
b1001001111 (
b1001001111 )
b1010100111010 *
b100000111100000 +
#275000000
0!
0%
#280000000
1!
b1010000101 $
1%
b1010000101 (
b1010000101 )
b1010111100010 *
b11111001110110 +
#285000000
0!
0%
#290000000
1!
b1010111101 $
1%
b1010111101 (
b1010111101 )
b1011010000001 *
b11101100001010 +
#295000000
0!
0%
#300000000
1!
b1011110110 $
1%
b1011110110 (
b1011110110 )
b1011100011000 *
b11011110011100 +
#305000000
0!
0%
#310000000
1!
b1100110001 $
1%
b1100110001 (
b1100110001 )
b1011110100110 *
b11010000110100 +
#315000000
0!
0%
#320000000
1!
b1101101101 $
1%
b1101101101 (
b1101101101 )
b1100000101011 *
b11000011001010 +
#325000000
0!
0%
#330000000
1!
b1110101010 $
1%
b1110101010 (
b1110101010 )
b1100010100111 *
b10110101101000 +
#335000000
0!
0%
#340000000
1!
b1111101001 $
1%
b1111101001 (
b1111101001 )
b1100100011011 *
b10101000001110 +
#345000000
0!
0%
#350000000
1!
b10000101001 $
1%
b10000101001 (
b10000101001 )
b1100110000110 *
b10011010110000 +
#355000000
0!
0%
#360000000
1!
b10001101010 $
1%
b10001101010 (
b10001101010 )
b1100111101001 *
b10001101011010 +
#365000000
0!
0%
#370000000
1!
b10010101100 $
1%
b10010101100 (
b10010101100 )
b1101001000011 *
b10000000001010 +
#375000000
0!
0%
#380000000
1!
b10011101111 $
1%
b10011101111 (
b10011101111 )
b1101010010101 *
b1110011000010 +
#385000000
0!
0%
#390000000
1!
b10100110011 $
1%
b10100110011 (
b10100110011 )
b1101011011110 *
b1100110000000 +
#395000000
0!
0%
#400000000
1!
b10101110111 $
1%
b10101110111 (
b10101110111 )
b1101100011111 *
b1011001000110 +
#405000000
0!
0%
#410000000
1!
b10110111100 $
1%
b10110111100 (
b10110111100 )
b1101101011000 *
b1001100011100 +
#415000000
0!
0%
#420000000
1!
b11000000010 $
1%
b11000000010 (
b11000000010 )
b1101110001000 *
b111111111000 +
#425000000
0!
0%
#430000000
1!
b11001001000 $
1%
b11001001000 (
b11001001000 )
b1101110110000 *
b110011011100 +
#435000000
0!
0%
#440000000
1!
b11010001110 $
1%
b11010001110 (
b11010001110 )
b1101111010000 *
b100111010000 +
#445000000
0!
0%
#450000000
1!
b11011010101 $
1%
b11011010101 (
b11011010101 )
b1101111101001 *
b11011010100 +
#455000000
0!
0%
#460000000
1!
b11100011100 $
1%
b11100011100 (
b11100011100 )
b1101111111010 *
b1111011100 +
#465000000
0!
0%
#470000000
1!
b11101100011 $
1%
b11101100011 (
b11101100011 )
b1110000000011 *
b11110100 +
#475000000
0!
0%
#480000000
1!
b11110101010 $
1%
b11110101010 (
b11110101010 )
b1110000000101 *
b11111111111111111111111000011100 +
#485000000
0!
0%
#490000000
1!
b11111110001 $
1%
b11111110001 (
b11111110001 )
b1110000000001 *
b11111111111111111111101101010010 +
#495000000
0!
0%
#500000000
1!
b100000111000 $
1%
b100000111000 (
b100000111000 )
b1101111110110 *
b11111111111111111111100010010100 +
#505000000
0!
0%
#510000000
1!
b100001111111 $
1%
b100001111111 (
b100001111111 )
b1101111100011 *
b11111111111111111111010111100100 +
#515000000
0!
0%
#520000000
1!
b100011000110 $
1%
b100011000110 (
b100011000110 )
b1101111001010 *
b11111111111111111111001101000100 +
#525000000
0!
0%
#530000000
1!
b100100001101 $
1%
b100100001101 (
b100100001101 )
b1101110101010 *
b11111111111111111111000010110000 +
#535000000
0!
0%
#540000000
1!
b100101010011 $
1%
b100101010011 (
b100101010011 )
b1101110000011 *
b11111111111111111110111000101010 +
#545000000
0!
0%
#550000000
1!
b100110011001 $
1%
b100110011001 (
b100110011001 )
b1101101010110 *
b11111111111111111110101110111100 +
#555000000
0!
0%
#560000000
1!
b100111011110 $
1%
b100111011110 (
b100111011110 )
b1101100100011 *
b11111111111111111110100101011010 +
#565000000
0!
0%
#570000000
1!
b101000100011 $
1%
b101000100011 (
b101000100011 )
b1101011101010 *
b11111111111111111110011100001110 +
#575000000
0!
0%
#580000000
1!
b101001100111 $
1%
b101001100111 (
b101001100111 )
b1101010101011 *
b11111111111111111110010011001110 +
#585000000
0!
0%
#590000000
1!
b101010101011 $
1%
b101010101011 (
b101010101011 )
b1101001100110 *
b11111111111111111110001010100100 +
#595000000
0!
0%
#600000000
1!
b101011101110 $
1%
b101011101110 (
b101011101110 )
b1101000011011 *
b11111111111111111110000010000110 +
#605000000
0!
0%
#610000000
1!
b101100110000 $
1%
b101100110000 (
b101100110000 )
b1100111001011 *
b11111111111111111101111001111110 +
#615000000
0!
0%
#620000000
1!
b101101110010 $
1%
b101101110010 (
b101101110010 )
b1100101110110 *
b11111111111111111101110010001010 +
#625000000
0!
0%
#630000000
1!
b101110110011 $
1%
b101110110011 (
b101110110011 )
b1100100011100 *
b11111111111111111101101010100000 +
#635000000
0!
0%
#640000000
1!
b101111110011 $
1%
b101111110011 (
b101111110011 )
b1100010111101 *
b11111111111111111101100011001010 +
#645000000
0!
0%
#650000000
1!
b110000110010 $
1%
b110000110010 (
b110000110010 )
b1100001011001 *
b11111111111111111101011100001000 +
#655000000
0!
0%
#660000000
1!
b110001110000 $
1%
b110001110000 (
b110001110000 )
b1011111110001 *
b11111111111111111101010101011010 +
#665000000
0!
0%
#670000000
1!
b110010101101 $
1%
b110010101101 (
b110010101101 )
b1011110000100 *
b11111111111111111101001110111110 +
#675000000
0!
0%
#680000000
1!
b110011101001 $
1%
b110011101001 (
b110011101001 )
b1011100010011 *
b11111111111111111101001000110110 +
#685000000
0!
0%
#690000000
1!
b110100100100 $
1%
b110100100100 (
b110100100100 )
b1011010011110 *
b11111111111111111101000011000000 +
#695000000
0!
0%
#700000000
1!
b110101011101 $
1%
b110101011101 (
b110101011101 )
b1011000100110 *
b11111111111111111100111101011100 +
#705000000
0!
0%
#710000000
1!
b110110010101 $
1%
b110110010101 (
b110110010101 )
b1010110101010 *
b11111111111111111100111000010010 +
#715000000
0!
0%
#720000000
1!
b110111001100 $
1%
b110111001100 (
b110111001100 )
b1010100101011 *
b11111111111111111100110011011010 +
#725000000
0!
0%
#730000000
1!
b111000000010 $
1%
b111000000010 (
b111000000010 )
b1010010101001 *
b11111111111111111100101110110010 +
#735000000
0!
0%
#740000000
1!
b111000110110 $
1%
b111000110110 (
b111000110110 )
b1010000100100 *
b11111111111111111100101010011010 +
#745000000
0!
0%
#750000000
1!
b111001101001 $
1%
b111001101001 (
b111001101001 )
b1001110011100 *
b11111111111111111100100110011100 +
#755000000
0!
0%
#760000000
1!
b111010011011 $
1%
b111010011011 (
b111010011011 )
b1001100010001 *
b11111111111111111100100010101110 +
#765000000
0!
0%
#770000000
1!
b111011001011 $
1%
b111011001011 (
b111011001011 )
b1001010000100 *
b11111111111111111100011111010000 +
#775000000
0!
0%
#780000000
1!
b111011111010 $
1%
b111011111010 (
b111011111010 )
b1000111110101 *
b11111111111111111100011100001010 +
#785000000
0!
0%
#790000000
1!
b111100100111 $
1%
b111100100111 (
b111100100111 )
b1000101100100 *
b11111111111111111100011001010010 +
#795000000
0!
0%
#800000000
1!
b111101010011 $
1%
b111101010011 (
b111101010011 )
b1000011010001 *
b11111111111111111100010110110010 +
#805000000
0!
0%
#810000000
1!
b111101111110 $
1%
b111101111110 (
b111101111110 )
b1000000111100 *
b11111111111111111100010100100000 +
#815000000
0!
0%
#820000000
1!
b111110100111 $
1%
b111110100111 (
b111110100111 )
b111110100110 *
b11111111111111111100010010011100 +
#825000000
0!
0%
#830000000
1!
b111111001111 $
1%
b111111001111 (
b111111001111 )
b111100001110 *
b11111111111111111100010000101110 +
#835000000
0!
0%
#840000000
1!
b111111110101 $
1%
b111111110101 (
b111111110101 )
b111001110101 *
b11111111111111111100001111001110 +
#845000000
0!
0%
#850000000
1!
b1000000011010 $
1%
b1000000011010 (
b1000000011010 )
b110111011011 *
b11111111111111111100001110000100 +
#855000000
0!
0%
#860000000
1!
b1000000111101 $
1%
b1000000111101 (
b1000000111101 )
b110101000001 *
b11111111111111111100001101000110 +
#865000000
0!
0%
#870000000
1!
b1000001011110 $
1%
b1000001011110 (
b1000001011110 )
b110010100110 *
b11111111111111111100001100011100 +
#875000000
0!
0%
#880000000
1!
b1000001111110 $
1%
b1000001111110 (
b1000001111110 )
b110000001011 *
b11111111111111111100001100001000 +
#885000000
0!
0%
#890000000
1!
b1000010011100 $
1%
b1000010011100 (
b1000010011100 )
b101101101111 *
b11111111111111111100001011111110 +
#895000000
0!
0%
#900000000
1!
b1000010111001 $
1%
b1000010111001 (
b1000010111001 )
b101011010011 *
b11111111111111111100001100001010 +
#905000000
0!
0%
#910000000
1!
b1000011010100 $
1%
b1000011010100 (
b1000011010100 )
b101000110111 *
b11111111111111111100001100100000 +
#915000000
0!
0%
#920000000
1!
b1000011101110 $
1%
b1000011101110 (
b1000011101110 )
b100110011100 *
b11111111111111111100001101001010 +
#925000000
0!
0%
#930000000
1!
b1000100000110 $
1%
b1000100000110 (
b1000100000110 )
b100100000001 *
b11111111111111111100001101111100 +
#935000000
0!
0%
#940000000
1!
b1000100011101 $
1%
b1000100011101 (
b1000100011101 )
b100001100111 *
b11111111111111111100001111000010 +
#945000000
0!
0%
#950000000
1!
b1000100110010 $
1%
b1000100110010 (
b1000100110010 )
b11111001101 *
b11111111111111111100010000010000 +
#955000000
0!
0%
#960000000
1!
b1000101000101 $
1%
b1000101000101 (
b1000101000101 )
b11100110100 *
b11111111111111111100010001110010 +
#965000000
0!
0%
#970000000
1!
b1000101010111 $
1%
b1000101010111 (
b1000101010111 )
b11010011100 *
b11111111111111111100010011100110 +
#975000000
0!
0%
#980000000
1!
b1000101100111 $
1%
b1000101100111 (
b1000101100111 )
b11000000101 *
b11111111111111111100010101100010 +
#985000000
0!
0%
#990000000
1!
b1000101110110 $
1%
b1000101110110 (
b1000101110110 )
b10101101111 *
b11111111111111111100010111110000 +
#995000000
0!
0%
#1000000000
1!
b1000110000011 $
1%
b1000110000011 (
b1000110000011 )
b10011011011 *
b11111111111111111100011010000110 +
#1005000000
0!
0%
#1010000000
1!
b1000110001111 $
1%
b1000110001111 (
b1000110001111 )
b10001001000 *
b11111111111111111100011100101100 +
#1015000000
0!
0%
#1020000000
1!
b1000110011001 $
1%
b1000110011001 (
b1000110011001 )
b1110110111 *
b11111111111111111100011111011010 +
#1025000000
0!
0%
#1030000000
1!
b1000110100010 $
1%
b1000110100010 (
b1000110100010 )
b1100101000 *
b11111111111111111100100010011000 +
#1035000000
0!
0%
#1040000000
1!
b1000110101010 $
1%
b1000110101010 (
b1000110101010 )
b1010011011 *
b11111111111111111100100101011100 +
#1045000000
0!
0%
#1050000000
1!
b1000110110000 $
1%
b1000110110000 (
b1000110110000 )
b1000010000 *
b11111111111111111100101000100110 +
#1055000000
0!
0%
#1060000000
1!
b1000110110101 $
1%
b1000110110101 (
b1000110110101 )
b110000111 *
b11111111111111111100101100000000 +
#1065000000
0!
0%
#1070000000
1!
b1000110111000 $
1%
b1000110111000 (
b1000110111000 )
b100000000 *
b11111111111111111100101111100000 +
#1075000000
0!
0%
#1080000000
1!
b1000110111010 $
1%
b1000110111010 (
b1000110111010 )
b1111011 *
b11111111111111111100110011010000 +
#1085000000
0!
0%
#1090000000
1!
b1000110111011 $
1%
b1000110111011 (
b1000110111011 )
b11111111111111111111111111111000 *
b11111111111111111100110111000110 +
#1095000000
0!
0%
#1100000000
1!
1%
b11111111111111111111111101111000 *
b11111111111111111100111011000010 +
#1105000000
0!
0%
#1110000000
1!
b1000110111010 $
1%
b1000110111010 (
b1000110111010 )
b11111111111111111111111011111010 *
b11111111111111111100111111000010 +
#1115000000
0!
0%
#1120000000
1!
b1000110111000 $
1%
b1000110111000 (
b1000110111000 )
b11111111111111111111111001111111 *
b11111111111111111101000011001000 +
#1125000000
0!
0%
#1130000000
1!
b1000110110101 $
1%
b1000110110101 (
b1000110110101 )
b11111111111111111111111000000111 *
b11111111111111111101000111010010 +
#1135000000
0!
0%
#1140000000
1!
b1000110110000 $
1%
b1000110110000 (
b1000110110000 )
b11111111111111111111110110010001 *
b11111111111111111101001011100000 +
#1145000000
0!
0%
#1150000000
1!
b1000110101010 $
1%
b1000110101010 (
b1000110101010 )
b11111111111111111111110100011110 *
b11111111111111111101001111111110 +
#1155000000
0!
0%
#1160000000
1!
b1000110100011 $
1%
b1000110100011 (
b1000110100011 )
b11111111111111111111110010101110 *
b11111111111111111101010100100000 +
#1165000000
0!
0%
#1170000000
1!
b1000110011011 $
1%
b1000110011011 (
b1000110011011 )
b11111111111111111111110001000001 *
b11111111111111111101011001000110 +
#1175000000
0!
0%
#1180000000
1!
b1000110010010 $
1%
b1000110010010 (
b1000110010010 )
b11111111111111111111101111010111 *
b11111111111111111101011101110000 +
#1185000000
0!
0%
#1190000000
1!
b1000110001000 $
1%
b1000110001000 (
b1000110001000 )
b11111111111111111111101101110000 *
b11111111111111111101100010011110 +
#1195000000
0!
0%
#1200000000
1!
b1000101111101 $
1%
b1000101111101 (
b1000101111101 )
b11111111111111111111101100001100 *
b11111111111111111101100111010000 +
#1205000000
0!
0%
#1210000000
1!
b1000101110001 $
1%
b1000101110001 (
b1000101110001 )
b11111111111111111111101010101011 *
b11111111111111111101101100000110 +
#1215000000
0!
0%
#1220000000
1!
b1000101100100 $
1%
b1000101100100 (
b1000101100100 )
b11111111111111111111101001001101 *
b11111111111111111101110001000000 +
#1225000000
0!
0%
#1230000000
1!
b1000101010110 $
1%
b1000101010110 (
b1000101010110 )
b11111111111111111111100111110010 *
b11111111111111111101110101111110 +
#1235000000
0!
0%
#1240000000
1!
b1000101000111 $
1%
b1000101000111 (
b1000101000111 )
b11111111111111111111100110011010 *
b11111111111111111101111011000000 +
#1245000000
0!
0%
#1250000000
1!
b1000100110111 $
1%
b1000100110111 (
b1000100110111 )
b11111111111111111111100101000101 *
b11111111111111111110000000000110 +
#1255000000
0!
0%
#1260000000
1!
b1000100100110 $
1%
b1000100100110 (
b1000100100110 )
b11111111111111111111100011110100 *
b11111111111111111110000101010000 +
#1265000000
0!
0%
#1270000000
1!
b1000100010100 $
1%
b1000100010100 (
b1000100010100 )
b11111111111111111111100010100110 *
b11111111111111111110001010011100 +
#1275000000
0!
0%
#1280000000
1!
b1000100000010 $
1%
b1000100000010 (
b1000100000010 )
b11111111111111111111100001011011 *
b11111111111111111110001111101100 +
#1285000000
0!
0%
#1290000000
1!
b1000011101111 $
1%
b1000011101111 (
b1000011101111 )
b11111111111111111111100000010100 *
b11111111111111111110010100110110 +
#1295000000
0!
0%
#1300000000
1!
b1000011011011 $
1%
b1000011011011 (
b1000011011011 )
b11111111111111111111011111010000 *
b11111111111111111110011010000010 +
#1305000000
0!
0%
#1310000000
1!
b1000011000111 $
1%
b1000011000111 (
b1000011000111 )
b11111111111111111111011110001111 *
b11111111111111111110011111010010 +
#1315000000
0!
0%
#1320000000
1!
b1000010110010 $
1%
b1000010110010 (
b1000010110010 )
b11111111111111111111011101010010 *
b11111111111111111110100100011100 +
#1325000000
0!
0%
#1330000000
1!
b1000010011100 $
1%
b1000010011100 (
b1000010011100 )
b11111111111111111111011100011000 *
b11111111111111111110101001101000 +
#1335000000
0!
0%
#1340000000
1!
b1000010000110 $
1%
b1000010000110 (
b1000010000110 )
b11111111111111111111011011100001 *
b11111111111111111110101110111000 +
#1345000000
0!
0%
#1350000000
1!
b1000001101111 $
1%
b1000001101111 (
b1000001101111 )
b11111111111111111111011010101110 *
b11111111111111111110110100000010 +
#1355000000
0!
0%
#1360000000
1!
b1000001011000 $
1%
b1000001011000 (
b1000001011000 )
b11111111111111111111011001111110 *
b11111111111111111110111001001110 +
#1365000000
0!
0%
#1370000000
1!
b1000001000000 $
1%
b1000001000000 (
b1000001000000 )
b11111111111111111111011001010001 *
b11111111111111111110111110010100 +
#1375000000
0!
0%
#1380000000
1!
b1000000101000 $
1%
b1000000101000 (
b1000000101000 )
b11111111111111111111011000100111 *
b11111111111111111111000011011110 +
#1385000000
0!
0%
#1390000000
1!
b1000000001111 $
1%
b1000000001111 (
b1000000001111 )
b11111111111111111111011000000001 *
b11111111111111111111001000100010 +
#1395000000
0!
0%
#1400000000
1!
b111111110110 $
1%
b111111110110 (
b111111110110 )
b11111111111111111111010111011110 *
b11111111111111111111001101101000 +
#1405000000
0!
0%
#1410000000
1!
b111111011101 $
1%
b111111011101 (
b111111011101 )
b11111111111111111111010110111110 *
b11111111111111111111010010101000 +
#1415000000
0!
0%
#1420000000
1!
b111111000011 $
1%
b111111000011 (
b111111000011 )
b11111111111111111111010110100001 *
b11111111111111111111010111100010 +
#1425000000
0!
0%
#1430000000
1!
b111110101001 $
1%
b111110101001 (
b111110101001 )
b11111111111111111111010110001000 *
b11111111111111111111011100100000 +
#1435000000
0!
0%
#1440000000
1!
b111110001111 $
1%
b111110001111 (
b111110001111 )
b11111111111111111111010101110010 *
b11111111111111111111100001010110 +
#1445000000
0!
0%
#1450000000
1!
b111101110100 $
1%
b111101110100 (
b111101110100 )
b11111111111111111111010101011111 *
b11111111111111111111100110000110 +
#1455000000
0!
0%
#1460000000
1!
b111101011001 $
1%
b111101011001 (
b111101011001 )
b11111111111111111111010101001111 *
b11111111111111111111101010111010 +
#1465000000
0!
0%
#1470000000
1!
b111100111110 $
1%
b111100111110 (
b111100111110 )
b11111111111111111111010101000010 *
b11111111111111111111101111101000 +
#1475000000
0!
0%
#1480000000
1!
b111100100011 $
1%
b111100100011 (
b111100100011 )
b11111111111111111111010100111000 *
b11111111111111111111110100010000 +
#1485000000
0!
0%
#1490000000
1!
b111100001000 $
1%
b111100001000 (
b111100001000 )
b11111111111111111111010100110001 *
b11111111111111111111111000110010 +
#1495000000
0!
0%
#1500000000
1!
b111011101101 $
1%
b111011101101 (
b111011101101 )
b11111111111111111111010100101101 *
b11111111111111111111111101001110 +
#1505000000
0!
0%
#1510000000
1!
b111011010010 $
1%
b111011010010 (
b111011010010 )
b11111111111111111111010100101100 *
b1100100 +
#1515000000
0!
0%
#1520000000
1!
b111010110111 $
1%
b111010110111 (
b111010110111 )
b11111111111111111111010100101101 *
b101110100 +
#1525000000
0!
0%
#1530000000
1!
b111010011100 $
1%
b111010011100 (
b111010011100 )
b11111111111111111111010100110000 *
b1010000000 +
#1535000000
0!
0%
#1540000000
1!
b111010000001 $
1%
b111010000001 (
b111010000001 )
b11111111111111111111010100110110 *
b1110001000 +
#1545000000
0!
0%
#1550000000
1!
b111001100110 $
1%
b111001100110 (
b111001100110 )
b11111111111111111111010100111111 *
b10010001010 +
#1555000000
0!
0%
#1560000000
1!
b111001001011 $
1%
b111001001011 (
b111001001011 )
b11111111111111111111010101001010 *
b10110000110 +
#1565000000
0!
0%
#1570000000
1!
b111000110000 $
1%
b111000110000 (
b111000110000 )
b11111111111111111111010101011000 *
b11001111110 +
#1575000000
0!
0%
#1580000000
1!
b111000010101 $
1%
b111000010101 (
b111000010101 )
b11111111111111111111010101101000 *
b11101110000 +
#1585000000
0!
0%
#1590000000
1!
b110111111010 $
1%
b110111111010 (
b110111111010 )
b11111111111111111111010101111011 *
b100001011110 +
#1595000000
0!
0%
#1600000000
1!
b110111100000 $
1%
b110111100000 (
b110111100000 )
b11111111111111111111010110010000 *
b100101000110 +
#1605000000
0!
0%
#1610000000
1!
b110111000110 $
1%
b110111000110 (
b110111000110 )
b11111111111111111111010110100111 *
b101000100000 +
#1615000000
0!
0%
#1620000000
1!
b110110101100 $
1%
b110110101100 (
b110110101100 )
b11111111111111111111010111000000 *
b101011110110 +
#1625000000
0!
0%
#1630000000
1!
b110110010010 $
1%
b110110010010 (
b110110010010 )
b11111111111111111111010111011100 *
b101111001000 +
#1635000000
0!
0%
#1640000000
1!
b110101111001 $
1%
b110101111001 (
b110101111001 )
b11111111111111111111010111111010 *
b110010010100 +
#1645000000
0!
0%
#1650000000
1!
b110101100000 $
1%
b110101100000 (
b110101100000 )
b11111111111111111111011000011010 *
b110101010010 +
#1655000000
0!
0%
#1660000000
1!
b110101000111 $
1%
b110101000111 (
b110101000111 )
b11111111111111111111011000111100 *
b111000001100 +
#1665000000
0!
0%
#1670000000
1!
b110100101110 $
1%
b110100101110 (
b110100101110 )
b11111111111111111111011001011111 *
b111011000010 +
#1675000000
0!
0%
#1680000000
1!
b110100010110 $
1%
b110100010110 (
b110100010110 )
b11111111111111111111011010000100 *
b111101110110 +
#1685000000
0!
0%
#1690000000
1!
b110011111110 $
1%
b110011111110 (
b110011111110 )
b11111111111111111111011010101011 *
b1000000011100 +
#1695000000
0!
0%
#1700000000
1!
b110011100111 $
1%
b110011100111 (
b110011100111 )
b11111111111111111111011011010100 *
b1000010111110 +
#1705000000
0!
0%
#1710000000
1!
b110011010000 $
1%
b110011010000 (
b110011010000 )
b11111111111111111111011011111110 *
b1000101010010 +
#1715000000
0!
0%
#1720000000
1!
b110010111001 $
1%
b110010111001 (
b110010111001 )
b11111111111111111111011100101010 *
b1000111100100 +
#1725000000
0!
0%
#1730000000
1!
b110010100011 $
1%
b110010100011 (
b110010100011 )
b11111111111111111111011101010111 *
b1001001110010 +
#1735000000
0!
0%
#1740000000
1!
b110010001101 $
1%
b110010001101 (
b110010001101 )
b11111111111111111111011110000110 *
b1001011110100 +
#1745000000
0!
0%
#1750000000
1!
b110001111000 $
1%
b110001111000 (
b110001111000 )
b11111111111111111111011110110110 *
b1001101110010 +
#1755000000
0!
0%
#1760000000
1!
b110001100011 $
1%
b110001100011 (
b110001100011 )
b11111111111111111111011111100111 *
b1001111100100 +
#1765000000
0!
0%
#1770000000
1!
b110001001111 $
1%
b110001001111 (
b110001001111 )
b11111111111111111111100000011001 *
b1010001010100 +
#1775000000
0!
0%
#1780000000
1!
b110000111011 $
1%
b110000111011 (
b110000111011 )
b11111111111111111111100001001101 *
b1010010111000 +
#1785000000
0!
0%
#1790000000
1!
b110000101000 $
1%
b110000101000 (
b110000101000 )
b11111111111111111111100010000010 *
b1010100011000 +
#1795000000
0!
0%
#1800000000
1!
b110000010101 $
1%
b110000010101 (
b110000010101 )
b11111111111111111111100010111000 *
b1010101101100 +
#1805000000
0!
0%
#1810000000
1!
b110000000011 $
1%
b110000000011 (
b110000000011 )
b11111111111111111111100011101110 *
b1010110111110 +
#1815000000
0!
0%
#1820000000
1!
b101111110001 $
1%
b101111110001 (
b101111110001 )
b11111111111111111111100100100101 *
b1011000000110 +
#1825000000
0!
0%
#1830000000
1!
b101111100000 $
1%
b101111100000 (
b101111100000 )
b11111111111111111111100101011101 *
b1011001001100 +
#1835000000
0!
0%
#1840000000
1!
b101111010000 $
1%
b101111010000 (
b101111010000 )
b11111111111111111111100110010110 *
b1011010000110 +
#1845000000
0!
0%
#1850000000
1!
b101111000000 $
1%
b101111000000 (
b101111000000 )
b11111111111111111111100111001111 *
b1011010110100 +
#1855000000
0!
0%
#1860000000
1!
b101110110001 $
1%
b101110110001 (
b101110110001 )
b11111111111111111111101000001001 *
b1011011100010 +
#1865000000
0!
0%
#1870000000
1!
b101110100010 $
1%
b101110100010 (
b101110100010 )
b11111111111111111111101001000011 *
b1011100000100 +
#1875000000
0!
0%
